Workbook

Sheet Summary
B2: Coverage
B4: Companies Covered | C4: =COUNTA(CCA_Defense!C3:C1048576) -> 84

Sheet CCA_Defense
D1: Ticker | M1: P/E | T1: Derived | U1: Mgmt Input | AH1: Platforms | AK1: Tier 1 | AN1: Tier 2 | AP1: Tier 3 | AS1: Tier 4 | AU1: . | AV1: Shares Outstanding (# Mn) | AY1: Revenue ($ Mn) | BC1: EV/EBITDA (x) | BG1: ROE (%) | BK1: ROCE (%) | BO1: Net Debt / EBITDA | BS1: Debt-Equity Ratio | BV1: PAT (%) | BY1: FCFF (Yield on EV) | CB1: Working Capital Cycle | CE1: . | CF1: Performance
B2: # | C2: Company | D2: BB | E2: Exch | F2: Mkt cap $mm | G2: Incorporation Date | H2: Legacy | I2: Type/status | J2: Sub-Segment | K2: TAM CAGR (FY30) | L2: Management Meeting | M2: Current | N2: FY26P | O2: FY27P | P2: FY28P | Q2: FY29P | R2: FY30P | S2: T12 rev YoY (%) | T2: CAGR (5-Yr) (%) | V2: Def. rev% | W2: Orderbook Visibility (x) | X2: Type | Y2: Location | Z2: Promoter | AA2: Prom. own% | AB2: Other s'holders | AC2: Barriers to Entry | AD2: Switching Costs | AE2: Customer Stickiness | AF2: Insights from Mgmt | AG2: Comments | AH2: Aerospace Systems | AI2: Land Systems\ | AJ2: Naval Systems | AK2: Mechanical Systems | AL2: Structural Systems | AM2: Weapon Systems | AN2: Munitions & Ordnance | AO2: Other Stand-Alone Items | AP2: Electrical Equipment & Components | AQ2: Electronic Equipment & Components | AR2: Test Solutions & Engineering | AS2: Raw Materials | AT2: Precision Components | AU2: Value Chain | AV2: FY25 | AW2: FY24 | AX2: FY23 | AY2: FY25E | AZ2: FY24 | BA2: FY23 | BB2: FY22 | BC2: FY25 | BD2: FY24 | BE2: FY23 | BF2: FY22 | BG2: FY25 | BH2: FY24 | BI2: FY23 | BJ2: FY22 | BK2: FY25 | BL2: FY24 | BM2: FY23 | BN2: FY22 | BO2: FY25 | BP2: FY24 | BQ2: FY23 | BR2: FY22 | BS2: FY24 | BT2: FY23 | BU2: FY22 | BV2: FY25 | BW2: FY24 | BX2: FY23 | BY2: FY25 | BZ2: FY24 | CA2: FY23 | CB2: FY25 | CC2: FY24 | CD2: FY23 | CE2: Rev CAGR (4-Yr) | CF2: CAGR (%) | CG2: PE (X) | CH2: ROE (%) | CI2: ROCE (%) | CJ2: Total Score | CK2: BBrow
B3: 1 | C3: Hindustan Aeronautics Limited | D3: HNAL | E3: HAL | F3: =_xlfn.XLOOKUP(CCA_Defense!$D3,BB_Input!$C$4:$C$172,BB_Input!$G$4:$G$172) -> 32941.531 | G3: 1940 | H3: =YEAR(TODAY())-G3 -> 86 | I3: Listed | J3: Aircraft OEM | K3: 0.07 | M3: 39.65 | N3: =IFERROR(_xlfn.XLOOKUP($D3,PE_Projections!$D:$D,PE_Projections!L:L),"") -> 34.750906 | O3: =IFERROR(_xlfn.XLOOKUP($D3,PE_Projections!$D:$D,PE_Projections!M:M),"") -> 29.185423 | P3: =IFERROR(_xlfn.XLOOKUP($D3,PE_Projections!$D:$D,PE_Projections!N:N),"") -> 25.131017 | Q3: =IFERROR(_xlfn.XLOOKUP($D3,PE_Projections!$D:$D,PE_Projections!O:O),"") -> 21.546295 | R3: =IFERROR(_xlfn.XLOOKUP($D3,PE_Projections!$D:$D,PE_Projections!P:P),"") | S3: 79.36 | T3: =IFERROR(RATE(5,,BB3,-AY3),"") -> 0.073652201 | V3: =AVERAGE(0.6,0.7) -> 0.65 | W3: 7.6 | X3: {=_xlfn.IFS($F3<Glossary!$C$54,Glossary!$B$54,$F3<Glossary!$C$55,Glossary!$B$55,$F3>Glossary!$C$56,Glossary!$B$56)} -> Large Cap | Y3: Bangalore | Z3: Government | AA3: 0.7164 | AC3: High | AD3: High | AE3: High | AH3: Y | AM3: Y | AQ3: Y | AT3: Y | AU3: Diversified | AV3: 3344 | AW3: 3344 | AX3: 3344 | AY3: 3929 | AZ3: 3490 | BA3: 3135 | BB3: 2754 | BC3: 24.2 | BD3: 4.7 | BE3: 6.8 | BG3: 0.267 | BH3: 0.289 | BI3: 0.2717 | BJ3: 0.2955 | BK3: 0.338 | BL3: 0.35 | BM3: 0.28 | BN3: 0.27 | BO3: 0 | BP3: 0 | BQ3: 0 | BR3: 0 | BS3: 0 | BT3: 0 | BU3: 0 | CE3: =IFERROR(RATE(4,,BB3,-AY3),"") -> 0.092897728 | CF3: =IF(CE3>='Conviction List'!$D$4,1,"") | CG3: =IF(M1<='Conviction List'!$E$4,1,"") | CH3: =IF(BG3>='Conviction List'!$F$4,1,"") -> 1 | CI3: =IF(BK3>='Conviction List'!$G$4,1,"") -> 1 | CJ3: =SUM(CF3:CI3) -> 2 | CK3: =MATCH($D3,INDIRECT($C$90&"!$C$1:$C$164"),0) -> 5
B4: =B3+1 -> 2 | C4: Bharat Electronics Limited | D4: BHE | E4: BEL | F4: =_xlfn.XLOOKUP(CCA_Defense!$D4,BB_Input!$C$4:$C$172,BB_Input!$G$4:$G$172) -> 32574.519 | G4: 1954 | H4: =YEAR(TODAY())-G4 -> 72 | I4: Listed | J4: Radars/Comms | K4: 0.0618 | M4: 61.39 | N4: =IFERROR(_xlfn.XLOOKUP($D4,PE_Projections!$D:$D,PE_Projections!L:L),"") -> 48.548221 | O4: =IFERROR(_xlfn.XLOOKUP($D4,PE_Projections!$D:$D,PE_Projections!M:M),"") -> 40.935212 | P4: =IFERROR(_xlfn.XLOOKUP($D4,PE_Projections!$D:$D,PE_Projections!N:N),"") -> 34.951751 | Q4: =IFERROR(_xlfn.XLOOKUP($D4,PE_Projections!$D:$D,PE_Projections!O:O),"") -> 31.397174 | R4: =IFERROR(_xlfn.XLOOKUP($D4,PE_Projections!$D:$D,PE_Projections!P:P),"") | S4: 172.03 | T4: =IFERROR(RATE(5,,BB4,-AY4),"") -> 0.069230988 | V4: 0.92 | W4: 3.6 | X4: {=_xlfn.IFS($F4<Glossary!$C$54,Glossary!$B$54,$F4<Glossary!$C$55,Glossary!$B$55,$F4>Glossary!$C$56,Glossary!$B$56)} -> Large Cap | Y4: Bangalore | Z4: Government | AA4: 0.5114 | AC4: High | AD4: High | AE4: High | AH4: Y | AQ4: Y | AU4: Diversified | AV4: 7280 | AW4: 7280 | AX4: 7280 | AY4: 2591 | AZ4: 2318 | BA4: 2144 | BB4: 1854 | BC4: 40.06 | BD4: 8 | BE4: 9.5 | BG4: 0.2932 | BH4: 0.18 | BI4: 0.165 | BJ4: 0.15 | BK4: 0.3899 | BL4: 0.2 | BM4: 0.18 | BN4: 0.165 | BO4: 0 | BP4: 0 | BQ4: 0 | BR4: 0 | BS4: 0 | BT4: 0 | BU4: 0 | CE4: =IFERROR(RATE(4,,BB4,-AY4),"") -> 0.087275046 | CF4: =IF(CE4>='Conviction List'!$D$4,1,"") | CG4: =IF(M2<='Conviction List'!$E$4,1,"") | CH4: =IF(BG4>='Conviction List'!$F$4,1,"") -> 1 | CI4: =IF(BK4>='Conviction List'!$G$4,1,"") -> 1 | CJ4: =SUM(CF4:CI4) -> 2 | CK4: =MATCH($D4,INDIRECT($C$90&"!$C$1:$C$164"),0) -> 6
B5: =B4+1 -> 3 | C5: Bharat Dynamics Limited | D5: BDL | E5: BDL | F5: =_xlfn.XLOOKUP(CCA_Defense!$D5,BB_Input!$C$4:$C$172,BB_Input!$G$4:$G$172) -> 6048.8875 | G5: 1970 | H5: =YEAR(TODAY())-G5 -> 56 | I5: Listed | J5: Missiles | M5: 61.75 | N5: =IFERROR(_xlfn.XLOOKUP($D5,PE_Projections!$D:$D,PE_Projections!L:L),"") -> 58.607226 | O5: =IFERROR(_xlfn.XLOOKUP($D5,PE_Projections!$D:$D,PE_Projections!M:M),"") -> 44.206127 | P5: =IFERROR(_xlfn.XLOOKUP($D5,PE_Projections!$D:$D,PE_Projections!N:N),"") -> 34.064669 | Q5: =IFERROR(_xlfn.XLOOKUP($D5,PE_Projections!$D:$D,PE_Projections!O:O),"") -> 39.967619 | R5: =IFERROR(_xlfn.XLOOKUP($D5,PE_Projections!$D:$D,PE_Projections!P:P),"") | S5: 98.4 | T5: =IFERROR(RATE(5,,BB5,-AY5),"") -> 0.062356498 | V5: 1 | W5: 3.54 | X5: {=_xlfn.IFS($F5<Glossary!$C$54,Glossary!$B$54,$F5<Glossary!$C$55,Glossary!$B$55,$F5>Glossary!$C$56,Glossary!$B$56)} -> Mid Cap | Y5: Hyderabad | Z5: Government | AA5: 0.7493 | AC5: High | AD5: High | AE5: High | AM5: Y | AU5: Tier 1 | AV5: 183.3 | AW5: 183.3 | AX5: 183.3 | AY5: 705 | AZ5: 638 | BA5: 579 | BB5: 521 | BC5: 83.5 | BD5: 10.2 | BE5: 11 | BG5: 0.1438 | BH5: 0.15 | BI5: 0.14 | BJ5: 0.125 | BK5: 0.1965 | BL5: 0.155 | BM5: 0.14 | BN5: 0.125 | BO5: 0 | BP5: 0 | BQ5: 0 | BR5: 0 | BS5: 0 | BT5: 0 | BU5: 0 | CE5: =IFERROR(RATE(4,,BB5,-AY5),"") -> 0.078543953 | CF5: =IF(CE5>='Conviction List'!$D$6,1,"") -> 1 | CG5: =IF(M5<='Conviction List'!$E$6,1,"") -> 1 | CH5: =IF(BG5>='Conviction List'!$F$6,1,"") -> 1 | CI5: =IF(BK5>='Conviction List'!$G$6,1,"") -> 1 | CJ5: =SUM(CF5:CI5) -> 4 | CK5: =MATCH($D5,INDIRECT($C$90&"!$C$1:$C$164"),0) -> 7
B6: =B5+1 -> 4 | C6: Mazagon Dock Shipbuilders Limited | D6: MAZDOCKS | E6: MAZDOCK | F6: =_xlfn.XLOOKUP(CCA_Defense!$D6,BB_Input!$C$4:$C$172,BB_Input!$G$4:$G$172) -> 11415.979 | G6: 1934 | H6: =YEAR(TODAY())-G6 -> 92 | I6: Listed | J6: Warships | M6: 38.06 | N6: =IFERROR(_xlfn.XLOOKUP($D6,PE_Projections!$D:$D,PE_Projections!L:L),"") -> 37.053118 | O6: =IFERROR(_xlfn.XLOOKUP($D6,PE_Projections!$D:$D,PE_Projections!M:M),"") -> 30.396666 | P6: =IFERROR(_xlfn.XLOOKUP($D6,PE_Projections!$D:$D,PE_Projections!N:N),"") -> 28.26324 | Q6: =IFERROR(_xlfn.XLOOKUP($D6,PE_Projections!$D:$D,PE_Projections!O:O),"") | R6: =IFERROR(_xlfn.XLOOKUP($D6,PE_Projections!$D:$D,PE_Projections!P:P),"") | S6: 75.76 | T6: =IFERROR(RATE(5,,BB6,-AY6),"") -> 0.047036671 | V6: 1 | W6: 5.7 | X6: {=_xlfn.IFS($F6<Glossary!$C$54,Glossary!$B$54,$F6<Glossary!$C$55,Glossary!$B$55,$F6>Glossary!$C$56,Glossary!$B$56)} -> Large Cap | Y6: Mumbai | Z6: Government | AA6: 0.8483 | AC6: High | AD6: High | AE6: High | AJ6: Y | AU6: Platforms | AV6: 201.7 | AW6: 201.7 | AX6: 201.7 | AY6: 526 | AZ6: 487 | BA6: 441 | BB6: 418 | BC6: 37.13 | BD6: 9.5 | BE6: 10 | BH6: 0.102 | BI6: 0.098 | BJ6: 0.085 | BL6: 0.12 | BM6: 0.115 | BN6: 0.1 | BO6: 0 | BP6: 0 | BQ6: 0 | BR6: 0 | BS6: 0 | BT6: 0 | BU6: 0 | CE6: =IFERROR(RATE(4,,BB6,-AY6),"") -> 0.05913755 | CF6: =IF(CE6>='Conviction List'!$D$5,1,"") | CG6: =IF(M6<='Conviction List'!$E$5,1,"") -> 1 | CH6: =IF(BG6>='Conviction List'!$F$5,1,"") | CI6: =IF(BK6>='Conviction List'!$G$5,1,"") | CJ6: =SUM(CF6:CI6) -> 1 | CK6: =MATCH($D6,INDIRECT($C$90&"!$C$1:$C$164"),0) -> 8
B7: =B6+1 -> 5 | C7: Garden Reach Shipbuilders & Engineers | D7: GRSE | E7: GRSE | F7: =_xlfn.XLOOKUP(CCA_Defense!$D7,BB_Input!$C$4:$C$172,BB_Input!$G$4:$G$172) -> 3131.5232 | G7: 1934 | H7: =YEAR(TODAY())-G7 -> 92 | I7: Listed | J7: Warships | M7: 88.75 | N7: =IFERROR(_xlfn.XLOOKUP($D7,PE_Projections!$D:$D,PE_Projections!L:L),"") -> 38.480116 | O7: =IFERROR(_xlfn.XLOOKUP($D7,PE_Projections!$D:$D,PE_Projections!M:M),"") -> 28.728985 | P7: =IFERROR(_xlfn.XLOOKUP($D7,PE_Projections!$D:$D,PE_Projections!N:N),"") -> 26.557715 | Q7: =IFERROR(_xlfn.XLOOKUP($D7,PE_Projections!$D:$D,PE_Projections!O:O),"") | R7: =IFERROR(_xlfn.XLOOKUP($D7,PE_Projections!$D:$D,PE_Projections!P:P),"") | S7: 225.73 | T7: =IFERROR(RATE(5,,BB7,-AY7),"") -> 0.043826858 | V7: 1 | W7: 4 | X7: {=_xlfn.IFS($F7<Glossary!$C$54,Glossary!$B$54,$F7<Glossary!$C$55,Glossary!$B$55,$F7>Glossary!$C$56,Glossary!$B$56)} -> Mid Cap | Y7: Kolkata | Z7: Government | AA7: 0.745 | AC7: High | AD7: High | AE7: High | AJ7: Y | AU7: Platforms | AV7: 114.6 | AW7: 114.6 | AX7: 114.6 | AY7: 373 | AZ7: 348 | BA7: 324 | BB7: 301 | BC7: 40.3 | BG7: 0.2811 | BH7: 0.12 | BI7: 0.115 | BJ7: 0.1 | BK7: 0.3728 | BL7: 0.125 | BM7: 0.11 | BN7: 0.105 | BO7: 3.5 | BP7: 3.4 | BQ7: 3.2 | BR7: 3 | BS7: 0.005 | BT7: 0.007 | BU7: 0.008 | CE7: =IFERROR(RATE(4,,BB7,-AY7),"") -> 0.05508047 | CF7: =IF(CE7>='Conviction List'!$D$5,1,"") | CG7: =IF(M7<='Conviction List'!$E$5,1,"") | CH7: =IF(BG7>='Conviction List'!$F$5,1,"") -> 1 | CI7: =IF(BK7>='Conviction List'!$G$5,1,"") -> 1 | CJ7: =SUM(CF7:CI7) -> 2 | CK7: =MATCH($D7,INDIRECT($C$90&"!$C$1:$C$164"),0) -> 9
B8: =B7+1 -> 6 | C8: Cochin Shipyard Limited | D8: COCHIN | E8: COCHINSHIP | F8: =_xlfn.XLOOKUP(CCA_Defense!$D8,BB_Input!$C$4:$C$172,BB_Input!$G$4:$G$172) -> 4833.9547 | G8: 1972 | H8: =YEAR(TODAY())-G8 -> 54 | I8: Listed | J8: Shipbuilding | M8: 48.8 | N8: =IFERROR(_xlfn.XLOOKUP($D8,PE_Projections!$D:$D,PE_Projections!L:L),"") -> 59.974547 | O8: =IFERROR(_xlfn.XLOOKUP($D8,PE_Projections!$D:$D,PE_Projections!M:M),"") -> 45.560775 | P8: =IFERROR(_xlfn.XLOOKUP($D8,PE_Projections!$D:$D,PE_Projections!N:N),"") -> 37.626617 | Q8: =IFERROR(_xlfn.XLOOKUP($D8,PE_Projections!$D:$D,PE_Projections!O:O),"") | R8: =IFERROR(_xlfn.XLOOKUP($D8,PE_Projections!$D:$D,PE_Projections!P:P),"") | S8: 156.7 | T8: =IFERROR(RATE(5,,BB8,-AY8),"") -> 0.15561324 | V8: =AVERAGE(0.6,0.7) -> 0.65 | W8: 5 | X8: {=_xlfn.IFS($F8<Glossary!$C$54,Glossary!$B$54,$F8<Glossary!$C$55,Glossary!$B$55,$F8>Glossary!$C$56,Glossary!$B$56)} -> Mid Cap | Y8: Cochin | Z8: Government | AA8: 0.6791 | AC8: High | AD8: High | AE8: High | AJ8: Y | AU8: Platforms | AV8: 131.6 | AW8: 131.6 | AX8: 131.6 | AY8: 5649 | AZ8: 4439 | BA8: 3698 | BB8: 2741 | BC8: 41.04 | BD8: 36.9 | BE8: 47.3 | BH8: 0.16 | BI8: 0.13 | BJ8: 0.06 | BL8: 0.22 | BM8: 0.2 | BN8: 0.09 | BO8: 3 | BP8: 2.8 | BQ8: 2.5 | BR8: 2.1 | BS8: 1.18 | BT8: 2.1 | BU8: 3.46 | CE8: =IFERROR(RATE(4,,BB8,-AY8),"") -> 0.19816226 | CF8: =IF(CE8>='Conviction List'!$D$5,1,"") -> 1 | CG8: =IF(M8<='Conviction List'!$E$5,1,"") | CH8: =IF(BG8>='Conviction List'!$F$5,1,"") | CI8: =IF(BK8>='Conviction List'!$G$5,1,"") | CJ8: =SUM(CF8:CI8) -> 1 | CK8: =MATCH($D8,INDIRECT($C$90&"!$C$1:$C$164"),0) -> 10
B9: =B8+1 -> 7 | C9: BEML Limited | D9: BEML | E9: BEML | F9: =_xlfn.XLOOKUP(CCA_Defense!$D9,BB_Input!$C$4:$C$172,BB_Input!$G$4:$G$172) -> 1733.2255 | G9: 1964 | H9: =YEAR(TODAY())-G9 -> 62 | I9: Listed | J9: Military vehicles | M9: 59.41 | N9: =IFERROR(_xlfn.XLOOKUP($D9,PE_Projections!$D:$D,PE_Projections!L:L),"") -> 38.8041 | O9: =IFERROR(_xlfn.XLOOKUP($D9,PE_Projections!$D:$D,PE_Projections!M:M),"") -> 27.780973 | P9: =IFERROR(_xlfn.XLOOKUP($D9,PE_Projections!$D:$D,PE_Projections!N:N),"") -> 22.834964 | Q9: =IFERROR(_xlfn.XLOOKUP($D9,PE_Projections!$D:$D,PE_Projections!O:O),"") | R9: =IFERROR(_xlfn.XLOOKUP($D9,PE_Projections!$D:$D,PE_Projections!P:P),"") | S9: 49.9 | T9: =IFERROR(RATE(5,,BB9,-AY9),"") -> 0.051918152 | V9: =AVERAGE(0.45,0.5) -> 0.475 | W9: 3.4 | X9: {=_xlfn.IFS($F9<Glossary!$C$54,Glossary!$B$54,$F9<Glossary!$C$55,Glossary!$B$55,$F9>Glossary!$C$56,Glossary!$B$56)} -> Small Cap | Y9: Bangalore | Z9: Government | AA9: 0.5403 | AC9: Medium | AD9: High | AE9: Medium | AH9: Y | AI9: Y | AT9: Y | AU9: Diversified | AV9: 41.7 | AW9: 41.7 | AX9: 41.7 | AY9: 568 | AZ9: 522 | BA9: 487 | BB9: 441 | BC9: 36.1 | BD9: 11.5 | BE9: 12 | BH9: 0.14 | BI9: 0.125 | BJ9: 0.1 | BL9: 0.125 | BM9: 0.11 | BN9: 0.1 | BO9: 1.2 | BP9: 1 | BQ9: 0.9 | BR9: 0.6 | BS9: 1.18 | BT9: 2.1 | BU9: 3.46 | CE9: =IFERROR(RATE(4,,BB9,-AY9),"") -> 0.065313515 | CF9: =IF(CE9>='Conviction List'!$D$4,1,"") | CG9: =IF(M7<='Conviction List'!$E$4,1,"") | CH9: =IF(BG9>='Conviction List'!$F$4,1,"") | CI9: =IF(BK9>='Conviction List'!$G$4,1,"") | CJ9: =SUM(CF9:CI9) -> 0 | CK9: =MATCH($D9,INDIRECT($C$90&"!$C$1:$C$164"),0) -> 11
B10: =B9+1 -> 8 | C10: Mishra Dhatu Nigam Limited (MIDHANI) | D10: MIDHANI | E10: MIDHANI | F10: =_xlfn.XLOOKUP(CCA_Defense!$D10,BB_Input!$C$4:$C$172,BB_Input!$G$4:$G$172) -> 649.82016 | G10: 1973 | H10: =YEAR(TODAY())-G10 -> 53 | I10: Listed | J10: Special alloys | M10: 73.81 | N10: =IFERROR(_xlfn.XLOOKUP($D10,PE_Projections!$D:$D,PE_Projections!L:L),"") -> 39.336703 | O10: =IFERROR(_xlfn.XLOOKUP($D10,PE_Projections!$D:$D,PE_Projections!M:M),"") -> 30.554466 | P10: =IFERROR(_xlfn.XLOOKUP($D10,PE_Projections!$D:$D,PE_Projections!N:N),"") -> 24.070352 | Q10: =IFERROR(_xlfn.XLOOKUP($D10,PE_Projections!$D:$D,PE_Projections!O:O),"") | R10: =IFERROR(_xlfn.XLOOKUP($D10,PE_Projections!$D:$D,PE_Projections!P:P),"") | S10: -12.63 | T10: =IFERROR(RATE(5,,BB10,-AY10),"") -> 0.053940666 | V10: =AVERAGE(80%,85%) -> 0.825 | W10: 1.9 | X10: {=_xlfn.IFS($F10<Glossary!$C$54,Glossary!$B$54,$F10<Glossary!$C$55,Glossary!$B$55,$F10>Glossary!$C$56,Glossary!$B$56)} -> Small Cap | Y10: Hyderabad | Z10: Government | AA10: 0.74 | AC10: High | AD10: High | AE10: High | AS10: Y | AU10: Tier 4 | AV10: 187.3 | AW10: 187.3 | AX10: 187.3 | AY10: 316 | AZ10: 290 | BA10: 266 | BB10: 243 | BC10: 33.95 | BH10: 0.15 | BI10: 0.14 | BJ10: 0.125 | BL10: 0.15 | BM10: 0.14 | BN10: 0.125 | BO10: 1.3 | BP10: 1.2 | BQ10: 1 | BR10: 0.8 | BS10: 0.25 | BT10: 0.3 | BU10: 0.22 | CE10: =IFERROR(RATE(4,,BB10,-AY10),"") -> 0.067874466 | CF10: =IF(CE10>='Conviction List'!$D$9,1,"") | CG10: =IF(M10<='Conviction List'!$E$9,1,"") -> 1 | CH10: =IF(BG10>='Conviction List'!$F$9,1,"") | CI10: =IF(BK10>='Conviction List'!$G$9,1,"") | CJ10: =SUM(CF10:CI10) -> 1 | CK10: =MATCH($D10,INDIRECT($C$90&"!$C$1:$C$164"),0) -> 12
B11: =B10+1 -> 9 | C11: Data Patterns | D11: DATAPATT | E11: DATAPATT | F11: =_xlfn.XLOOKUP(CCA_Defense!$D11,BB_Input!$C$4:$C$172,BB_Input!$G$4:$G$172) -> 1666.7202 | G11: 1985 | H11: =YEAR(TODAY())-G11 -> 41 | I11: Listed | J11: Avionics | N11: =IFERROR(_xlfn.XLOOKUP($D11,PE_Projections!$D:$D,PE_Projections!L:L),"") -> 48.318593 | O11: =IFERROR(_xlfn.XLOOKUP($D11,PE_Projections!$D:$D,PE_Projections!M:M),"") -> 38.101025 | P11: =IFERROR(_xlfn.XLOOKUP($D11,PE_Projections!$D:$D,PE_Projections!N:N),"") -> 29.124123 | Q11: =IFERROR(_xlfn.XLOOKUP($D11,PE_Projections!$D:$D,PE_Projections!O:O),"") -> 23.970579 | R11: =IFERROR(_xlfn.XLOOKUP($D11,PE_Projections!$D:$D,PE_Projections!P:P),"") | T11: =IFERROR(RATE(5,,BB11,-AY11),"") -> 0.19573801 | V11: 0.9 | W11: 1.3 | X11: {=_xlfn.IFS($F11<Glossary!$C$54,Glossary!$B$54,$F11<Glossary!$C$55,Glossary!$B$55,$F11>Glossary!$C$56,Glossary!$B$56)} -> Small Cap | Y11: Chennai | Z11: Private | AA11: 0.4241 | AB11: Singapore, 5.3% | AC11: High | AD11: High | AE11: High | AP11: Y | AQ11: Y | AU11: Tier 3 | AV11: 52.5 | AW11: 52.5 | AX11: 52.5 | AY11: 88 | AZ11: 66 | BA11: 54 | BB11: 36 | BC11: 51.8 | BG11: 0.1566 | BK11: 0.516 | BO11: 1.8 | BP11: 1.7 | BQ11: 1.5 | BR11: 1.4 | BS11: 0 | BT11: 0.01 | BU11: 0.16 | CE11: =IFERROR(RATE(4,,BB11,-AY11),"") -> 0.25038871 | CF11: =IF(CE11>='Conviction List'!$D$8,1,"") | CG11: =IF(M11<='Conviction List'!$E$8,1,"") -> 1 | CH11: =IF(BG11>='Conviction List'!$F$8,1,"") -> 1 | CI11: =IF(BK11>='Conviction List'!$G$8,1,"") -> 1 | CJ11: =SUM(CF11:CI11) -> 3 | CK11: =MATCH($D11,INDIRECT($C$90&"!$C$1:$C$164"),0) -> 13
B12: =B11+1 -> 10 | C12: Paras Defense and Space | D12: PARAS | E12: PARAS | F12: =_xlfn.XLOOKUP(CCA_Defense!$D12,BB_Input!$C$4:$C$172,BB_Input!$G$4:$G$172) -> 602.33536 | G12: 2009 | H12: =YEAR(TODAY())-G12 -> 17 | I12: Listed | J12: Electro-optics | M12: 105 | N12: =IFERROR(_xlfn.XLOOKUP($D12,PE_Projections!$D:$D,PE_Projections!L:L),"") -> 59.901788 | O12: =IFERROR(_xlfn.XLOOKUP($D12,PE_Projections!$D:$D,PE_Projections!M:M),"") -> 45.026847 | P12: =IFERROR(_xlfn.XLOOKUP($D12,PE_Projections!$D:$D,PE_Projections!N:N),"") | Q12: =IFERROR(_xlfn.XLOOKUP($D12,PE_Projections!$D:$D,PE_Projections!O:O),"") | R12: =IFERROR(_xlfn.XLOOKUP($D12,PE_Projections!$D:$D,PE_Projections!P:P),"") | S12: 47 | T12: =IFERROR(RATE(5,,BB12,-AY12),"") -> 0.10143233 | V12: =AVERAGE(80%,85%) -> 0.825 | W12: 2 | X12: {=_xlfn.IFS($F12<Glossary!$C$54,Glossary!$B$54,$F12<Glossary!$C$55,Glossary!$B$55,$F12>Glossary!$C$56,Glossary!$B$56)} -> Small Cap | Y12: Navi Mumbai | Z12: Private | AA12: 0.5705 | AB12: Abu Dhabi, 1.8% | AC12: High | AD12: High | AE12: High | AH12: Y | AQ12: Y | AU12: Tier 3 | AV12: 39.2 | AW12: 39.2 | AX12: 39.2 | AY12: =AZ12*(1+(RATE(3,,BB12,-AZ12,0))) -> 34.527784 | AZ12: 30.6 | BA12: 26 | BB12: 21.3 | BC12: 70.7 | BH12: 0.0796 | BI12: 0.0909 | BJ12: 0.0922 | BL12: 0.0968 | BM12: 0.1225 | BN12: 0.1032 | BO12: 1 | BP12: 0.9 | BQ12: 0.8 | BR12: 0.6 | BS12: 0.08 | BT12: 0 | BU12: 0.08 | CE12: =IFERROR(RATE(4,,BB12,-AY12),"") -> 0.12835894 | CF12: =IF(CE12>='Conviction List'!$D$8,1,"") | CG12: =IF(M12<='Conviction List'!$E$8,1,"") | CH12: =IF(BG12>='Conviction List'!$F$8,1,"") | CI12: =IF(BK12>='Conviction List'!$G$8,1,"") | CJ12: =SUM(CF12:CI12) -> 0 | CK12: =MATCH($D12,INDIRECT($C$90&"!$C$1:$C$164"),0) -> 14
B13: =B12+1 -> 11 | C13: Astra Microwave | D13: ASTM | E13: ASTM | F13: =_xlfn.XLOOKUP(CCA_Defense!$D13,BB_Input!$C$4:$C$172,BB_Input!$G$4:$G$172) -> 1026.2888 | G13: 1991 | H13: =YEAR(TODAY())-G13 -> 35 | I13: Listed | J13: RF/Microwave | L13: Yes | M13: 58.07 | N13: =IFERROR(_xlfn.XLOOKUP($D13,PE_Projections!$D:$D,PE_Projections!L:L),"") -> 53.831009 | O13: =IFERROR(_xlfn.XLOOKUP($D13,PE_Projections!$D:$D,PE_Projections!M:M),"") -> 44.264576 | P13: =IFERROR(_xlfn.XLOOKUP($D13,PE_Projections!$D:$D,PE_Projections!N:N),"") -> 36.398215 | Q13: =IFERROR(_xlfn.XLOOKUP($D13,PE_Projections!$D:$D,PE_Projections!O:O),"") -> 29.929804 | R13: =IFERROR(_xlfn.XLOOKUP($D13,PE_Projections!$D:$D,PE_Projections!P:P),"") -> 24.610909 | S13: 30.72 | T13: =IFERROR(RATE(5,,BB13,-AY13),"") -> 0.075507965 | U13: 0.26 | V13: =AVERAGE(80%,85%) -> 0.825 | W13: 2.1 | X13: {=_xlfn.IFS($F13<Glossary!$C$54,Glossary!$B$54,$F13<Glossary!$C$55,Glossary!$B$55,$F13>Glossary!$C$56,Glossary!$B$56)} -> Small Cap | Y13: Hyderabad | Z13: Private | AA13: 0.0654 | AB13: TEXINFRA, 2.2% | AC13: High | AD13: High | AE13: High | AQ13: Y | AR13: Y | AU13: Tier 3 | AV13: 91.2 | AW13: 91.2 | AX13: 91.2 | AY13: 118 | AZ13: 105 | BA13: 94 | BB13: 82 | BC13: 35.8 | BD13: 37.6 | BE13: 41 | BG13: 0.148 | BH13: 0.125 | BI13: 0.1 | BJ13: 0.09 | BK13: 0.1914 | BL13: 0.172 | BM13: 0.15 | BN13: 0.14 | BO13: 0.8 | BP13: 0.7 | BQ13: 0.5 | BR13: 0.4 | BS13: 0.23 | BT13: 0.26 | BU13: 0.1 | CE13: =IFERROR(RATE(4,,BB13,-AY13),"") -> 0.095259525 | CF13: =IF(CE13>='Conviction List'!$D$8,1,"") | CG13: =IF(M13<='Conviction List'!$E$8,1,"") -> 1 | CH13: =IF(BG13>='Conviction List'!$F$8,1,"") -> 1 | CI13: =IF(BK13>='Conviction List'!$G$8,1,"") | CJ13: =SUM(CF13:CI13) -> 2 | CK13: =MATCH($D13,INDIRECT($C$90&"!$C$1:$C$164"),0) -> 15
B14: =B13+1 -> 12 | C14: Axiscades Technologies Ltd | D14: AXET | E14: AXISCADES | F14: =_xlfn.XLOOKUP(CCA_Defense!$D14,BB_Input!$C$4:$C$172,BB_Input!$G$4:$G$172) -> 637.04539 | G14: 1990 | H14: =YEAR(TODAY())-G14 -> 36 | I14: Listed | J14: Engineering services | L14: Yes | M14: 76.1 | N14: =IFERROR(_xlfn.XLOOKUP($D14,PE_Projections!$D:$D,PE_Projections!L:L),"") -> 52.028001 | O14: =IFERROR(_xlfn.XLOOKUP($D14,PE_Projections!$D:$D,PE_Projections!M:M),"") -> 35.47271 | P14: =IFERROR(_xlfn.XLOOKUP($D14,PE_Projections!$D:$D,PE_Projections!N:N),"") -> 24.185307 | Q14: =IFERROR(_xlfn.XLOOKUP($D14,PE_Projections!$D:$D,PE_Projections!O:O),"") -> 16.489551 | R14: =IFERROR(_xlfn.XLOOKUP($D14,PE_Projections!$D:$D,PE_Projections!P:P),"") -> 11.242582 | S14: 10 | T14: =IFERROR(RATE(5,,BB14,-AY14),"") -> 0.1088115 | U14: 0.5439 | V14: =AVERAGE(60%,70%) -> 0.65 | W14: 1.68 | X14: {=_xlfn.IFS($F14<Glossary!$C$54,Glossary!$B$54,$F14<Glossary!$C$55,Glossary!$B$55,$F14>Glossary!$C$56,Glossary!$B$56)} -> Small Cap | Y14: Bengaluru | Z14: Private | AA14: 0.5949 | AC14: High | AD14: High | AE14: High | AF14: 70-80% of the projects are fixed under master service agreements; Axiscades was a key operator in setting up Airbus engineering facility in India & ~$30-35 Mn revenue comes from them per year. | AI14: Y | AM14: Y | AP14: Y | AQ14: Y | AR14: Y | AU14: Diversified | AV14: 37.7 | AW14: 37.7 | AX14: 37.7 | AY14: 119 | AZ14: 111 | BA14: 96 | BB14: 71 | BC14: 38.24 | BD14: 15.8 | BE14: 14.08 | BF14: 5.14 | BG14: 0.1261 | BH14: 0.056 | BI14: -0.0141 | BJ14: 0.0671 | BK14: 0.1357 | BL14: 0.1377 | BM14: 0.1041 | BN14: 0.1477 | BS14: 0.54 | BT14: 1.01 | BU14: 0.21 | CE14: =IFERROR(RATE(4,,BB14,-AY14),"") -> 0.13781631 | CF14: =IF(CE14>='Conviction List'!$D$4,1,"") | CG14: =IF(M12<='Conviction List'!$E$4,1,"") | CH14: =IF(BG14>='Conviction List'!$F$4,1,"") | CI14: =IF(BK14>='Conviction List'!$G$4,1,"") | CJ14: =SUM(CF14:CI14) -> 0 | CK14: =MATCH($D14,INDIRECT($C$90&"!$C$1:$C$164"),0) -> 37
B15: =B14+1 -> 13 | C15: DCX Systems | D15: DCXINDIA | E15: DCXINDIA | F15: =_xlfn.XLOOKUP(CCA_Defense!$D15,BB_Input!$C$4:$C$172,BB_Input!$G$4:$G$172) -> 251.06426 | G15: 2011 | H15: =YEAR(TODAY())-G15 -> 15 | I15: Listed | J15: Cable harnesses | M15: 67.45 | N15: =IFERROR(_xlfn.XLOOKUP($D15,PE_Projections!$D:$D,PE_Projections!L:L),"") -> 39.67059 | O15: =IFERROR(_xlfn.XLOOKUP($D15,PE_Projections!$D:$D,PE_Projections!M:M),"") -> 27.340542 | P15: =IFERROR(_xlfn.XLOOKUP($D15,PE_Projections!$D:$D,PE_Projections!N:N),"") -> 21.754839 | Q15: =IFERROR(_xlfn.XLOOKUP($D15,PE_Projections!$D:$D,PE_Projections!O:O),"") | R15: =IFERROR(_xlfn.XLOOKUP($D15,PE_Projections!$D:$D,PE_Projections!P:P),"") | T15: =IFERROR(RATE(5,,BB15,-AY15),"") -> 0.079915006 | V15: =AVERAGE(80%,85%) -> 0.825 | W15: 2.5 | X15: {=_xlfn.IFS($F15<Glossary!$C$54,Glossary!$B$54,$F15<Glossary!$C$55,Glossary!$B$55,$F15>Glossary!$C$56,Glossary!$B$56)} -> Small Cap | Y15: Bangalore | Z15: Private | AA15: 0.568 | AC15: High | AD15: High | AE15: High | AP15: Y | AQ15: Y | AU15: Tier 3 | AV15: 77.1 | AW15: 77.1 | AX15: 77.1 | AY15: 188 | AZ15: 165 | BA15: 145 | BB15: 128 | BC15: 25.37 | BL15: 0.1 | BM15: 0.13 | BN15: 0.22 | BO15: 0.3 | BP15: 0.4 | BQ15: 0.8 | BR15: 1.3 | BS15: 0.24 | BT15: 0.89 | BU15: 4.27 | CE15: =IFERROR(RATE(4,,BB15,-AY15),"") -> 0.10087237 | CF15: =IF(CE15>='Conviction List'!$D$8,1,"") | CG15: =IF(M15<='Conviction List'!$E$8,1,"") -> 1 | CH15: =IF(BG15>='Conviction List'!$F$8,1,"") | CI15: =IF(BK15>='Conviction List'!$G$8,1,"") | CJ15: =SUM(CF15:CI15) -> 1 | CK15: =MATCH($D15,INDIRECT($C$90&"!$C$1:$C$164"),0) -> 17
B16: =B15+1 -> 14 | C16: Avantel | D16: AVTS | E16: AVTS | F16: =_xlfn.XLOOKUP(CCA_Defense!$D16,BB_Input!$C$4:$C$172,BB_Input!$G$4:$G$172) -> 476.85876 | G16: 2010 | H16: =YEAR(TODAY())-G16 -> 16 | I16: Listed | J16: Satcom | N16: =IFERROR(_xlfn.XLOOKUP($D16,PE_Projections!$D:$D,PE_Projections!L:L),"") -> 61.963867 | O16: =IFERROR(_xlfn.XLOOKUP($D16,PE_Projections!$D:$D,PE_Projections!M:M),"") -> 51.794235 | P16: =IFERROR(_xlfn.XLOOKUP($D16,PE_Projections!$D:$D,PE_Projections!N:N),"") -> 43.293663 | Q16: =IFERROR(_xlfn.XLOOKUP($D16,PE_Projections!$D:$D,PE_Projections!O:O),"") -> 36.188222 | R16: =IFERROR(_xlfn.XLOOKUP($D16,PE_Projections!$D:$D,PE_Projections!P:P),"") -> 30.24894 | S16: 3 | T16: =IFERROR(RATE(5,,BB16,-AY16),"") -> 0.25927468 | V16: =AVERAGE(80%,85%) -> 0.825 | X16: {=_xlfn.IFS($F16<Glossary!$C$54,Glossary!$B$54,$F16<Glossary!$C$55,Glossary!$B$55,$F16>Glossary!$C$56,Glossary!$B$56)} -> Small Cap | Y16: Hyderabad | Z16: Family | AA16: 0.3857 | AC16: High | AD16: High | AE16: High | AP16: Y | AQ16: Y | AU16: Tier 3 | AV16: 17.2 | AW16: 17.2 | AX16: 17.2 | AY16: 38 | AZ16: 26 | BA16: 18 | BB16: 12 | BC16: 43.23 | BL16: 0.47 | BM16: 0.35 | BN16: 0.29 | BO16: 0.6 | BP16: 0.5 | BQ16: 0.4 | BR16: 0.3 | BS16: 0.07 | BT16: 0.25 | BU16: 0.15 | CE16: =IFERROR(RATE(4,,BB16,-AY16),"") -> 0.3339839 | CF16: =IF(CE16>='Conviction List'!$D$8,1,"") -> 1 | CG16: =IF(M16<='Conviction List'!$E$8,1,"") -> 1 | CH16: =IF(BG16>='Conviction List'!$F$8,1,"") | CI16: =IF(BK16>='Conviction List'!$G$8,1,"") | CJ16: =SUM(CF16:CI16) -> 2 | CK16: =MATCH($D16,INDIRECT($C$90&"!$C$1:$C$164"),0) -> 18
B17: =B16+1 -> 15 | C17: Apollo Micro Systems | D17: APOLLO | E17: APOLLO | F17: =_xlfn.XLOOKUP(CCA_Defense!$D17,BB_Input!$C$4:$C$172,BB_Input!$G$4:$G$172) -> 983.4285 | G17: 1997 | H17: =YEAR(TODAY())-G17 -> 29 | I17: Listed | J17: Systems integration | N17: =IFERROR(_xlfn.XLOOKUP($D17,PE_Projections!$D:$D,PE_Projections!L:L),"") -> 84.83871 | O17: =IFERROR(_xlfn.XLOOKUP($D17,PE_Projections!$D:$D,PE_Projections!M:M),"") -> 57.173913 | P17: =IFERROR(_xlfn.XLOOKUP($D17,PE_Projections!$D:$D,PE_Projections!N:N),"") -> 35.066667 | Q17: =IFERROR(_xlfn.XLOOKUP($D17,PE_Projections!$D:$D,PE_Projections!O:O),"") | R17: =IFERROR(_xlfn.XLOOKUP($D17,PE_Projections!$D:$D,PE_Projections!P:P),"") | T17: =IFERROR(RATE(5,,BB17,-AY17),"") -> 0.13611833 | V17: =AVERAGE(80%,85%) -> 0.825 | W17: 15.1 | X17: {=_xlfn.IFS($F17<Glossary!$C$54,Glossary!$B$54,$F17<Glossary!$C$55,Glossary!$B$55,$F17>Glossary!$C$56,Glossary!$B$56)} -> Small Cap | Y17: Hyderabad | Z17: Private | AA17: 0.5512 | AC17: High | AD17: High | AE17: High | AQ17: Y | AU17: Tier 3 | AV17: 51.7 | AW17: 51.7 | AX17: 51.7 | AY17: 53 | AZ17: 43 | BA17: 35 | BB17: 28 | BC17: 45.88 | BL17: 0.23 | BM17: 0.22 | BN17: 0.19 | BO17: 0.2 | BP17: 0.3 | BQ17: 0.4 | BR17: 0.5 | BS17: 0.84 | BT17: 0.8 | BU17: 0.87 | CE17: =IFERROR(RATE(4,,BB17,-AY17),"") -> 0.17294989 | CF17: =IF(CE17>='Conviction List'!$D$8,1,"") | CG17: =IF(M17<='Conviction List'!$E$8,1,"") -> 1 | CH17: =IF(BG17>='Conviction List'!$F$8,1,"") | CI17: =IF(BK17>='Conviction List'!$G$8,1,"") | CJ17: =SUM(CF17:CI17) -> 1 | CK17: =MATCH($D17,INDIRECT($C$90&"!$C$1:$C$164"),0) -> 19
B18: =B17+1 -> 16 | C18: Adani Elbit Advanced Systems India | D18: ADE | E18: ADANIENT | F18: =_xlfn.XLOOKUP(CCA_Defense!$D18,BB_Input!$C$4:$C$172,BB_Input!$G$4:$G$172) -> 31344.867 | G18: 2021 | H18: =YEAR(TODAY())-G18 -> 5 | I18: Acquired by/Part of Listed Company | J18: UAVs | M18: 105 | N18: =IFERROR(_xlfn.XLOOKUP($D18,PE_Projections!$D:$D,PE_Projections!L:L),"") -> 66.283299 | O18: =IFERROR(_xlfn.XLOOKUP($D18,PE_Projections!$D:$D,PE_Projections!M:M),"") -> 52.057927 | P18: =IFERROR(_xlfn.XLOOKUP($D18,PE_Projections!$D:$D,PE_Projections!N:N),"") -> 46.357758 | Q18: =IFERROR(_xlfn.XLOOKUP($D18,PE_Projections!$D:$D,PE_Projections!O:O),"") -> 50.407075 | R18: =IFERROR(_xlfn.XLOOKUP($D18,PE_Projections!$D:$D,PE_Projections!P:P),"") | T18: =IFERROR(RATE(5,,BB18,-AY18),"") -> 0.090495011 | V18: 1 | W18: 0.1 | X18: {=_xlfn.IFS($F18<Glossary!$C$54,Glossary!$B$54,$F18<Glossary!$C$55,Glossary!$B$55,$F18>Glossary!$C$56,Glossary!$B$56)} -> Large Cap | Y18: New Delhi | Z18: Family | AC18: High | AD18: High | AE18: High | AG18: Adani Enterprises Ltd on NSE/BSE & Elbit Systems Ltd. on NASDAQ | AH18: Y | AI18: Y | AJ18: Y | AM18: Y | AQ18: Y | AU18: Diversified | AY18: 78514 | AZ18: 67957 | BA18: 59465 | BB18: 50913 | CE18: =IFERROR(RATE(4,,BB18,-AY18),"") -> 0.11437049 | CF18: =IF(CE18>='Conviction List'!$D$4,1,"") | CG18: =IF(M16<='Conviction List'!$E$4,1,"") -> 1 | CH18: =IF(BG18>='Conviction List'!$F$4,1,"") | CI18: =IF(BK18>='Conviction List'!$G$4,1,"") | CJ18: =SUM(CF18:CI18) -> 1 | CK18: =MATCH($D18,INDIRECT($C$90&"!$C$1:$C$164"),0) -> 20
B19: =B18+1 -> 17 | C19: NIBE Ltd | D19: NIBE | E19: NIBE | F19: =_xlfn.XLOOKUP(CCA_Defense!$D19,BB_Input!$C$4:$C$172,BB_Input!$G$4:$G$172) -> 183.75245 | G19: 1986 | H19: =YEAR(TODAY())-G19 -> 40 | I19: Listed | J19: Connectors/Cables | M19: 59 | N19: =IFERROR(_xlfn.XLOOKUP($D19,PE_Projections!$D:$D,PE_Projections!L:L),"") -> 44.785977 | O19: =IFERROR(_xlfn.XLOOKUP($D19,PE_Projections!$D:$D,PE_Projections!M:M),"") -> 32.741084 | P19: =IFERROR(_xlfn.XLOOKUP($D19,PE_Projections!$D:$D,PE_Projections!N:N),"") -> 23.965091 | Q19: =IFERROR(_xlfn.XLOOKUP($D19,PE_Projections!$D:$D,PE_Projections!O:O),"") -> 17.854307 | R19: =IFERROR(_xlfn.XLOOKUP($D19,PE_Projections!$D:$D,PE_Projections!P:P),"") -> 13.527146 | T19: =IFERROR(RATE(5,,BB19,-AY19),"") -> 1.0662908 | V19: =AVERAGE(60%,70%) -> 0.65 | X19: {=_xlfn.IFS($F19<Glossary!$C$54,Glossary!$B$54,$F19<Glossary!$C$55,Glossary!$B$55,$F19>Glossary!$C$56,Glossary!$B$56)} -> Small Cap | Y19: Chakan | Z19: Family | AA19: 0.5374 | AC19: High | AD19: High | AE19: High | AQ19: Y | AU19: Tier 3 | AV19: 13.3 | AW19: 13.3 | AX19: 13.3 | AY19: 113 | AZ19: 32 | BA19: 12 | BB19: 3 | BC19: 38 | BD19: 44.1 | BH19: 0.142 | BO19: 3.9 | BP19: 3.9 | BQ19: 2.1 | BR19: 0.9 | BS19: 0.37 | BT19: 0.27 | BU19: 0.02 | CE19: =IFERROR(RATE(4,,BB19,-AY19),"") -> 1.477361 | CF19: =IF(CE19>='Conviction List'!$D$8,1,"") -> 1 | CG19: =IF(M19<='Conviction List'!$E$8,1,"") -> 1 | CH19: =IF(BG19>='Conviction List'!$F$8,1,"") | CI19: =IF(BK19>='Conviction List'!$G$8,1,"") | CJ19: =SUM(CF19:CI19) -> 2 | CK19: =MATCH($D19,INDIRECT($C$90&"!$C$1:$C$164"),0) -> 21
B20: =B19+1 -> 18 | C20: Azad Engineering | D20: AZAD | E20: AZAD | F20: =_xlfn.XLOOKUP(CCA_Defense!$D20,BB_Input!$C$4:$C$172,BB_Input!$G$4:$G$172) -> 1191.4721 | G20: 1983 | H20: =YEAR(TODAY())-G20 -> 43 | I20: Listed | J20: Aero-engine parts | L20: Yes | M20: 108 | N20: =IFERROR(_xlfn.XLOOKUP($D20,PE_Projections!$D:$D,PE_Projections!L:L),"") -> 84.328635 | O20: =IFERROR(_xlfn.XLOOKUP($D20,PE_Projections!$D:$D,PE_Projections!M:M),"") -> 55.772907 | P20: =IFERROR(_xlfn.XLOOKUP($D20,PE_Projections!$D:$D,PE_Projections!N:N),"") -> 36.886843 | Q20: =IFERROR(_xlfn.XLOOKUP($D20,PE_Projections!$D:$D,PE_Projections!O:O),"") -> 24.39606 | R20: =IFERROR(_xlfn.XLOOKUP($D20,PE_Projections!$D:$D,PE_Projections!P:P),"") -> 16.134961 | S20: 27 | T20: =IFERROR(RATE(5,,BB20,-AY20),"") -> 0.18772564 | U20: 0.44 | V20: =AVERAGE(60%,70%) -> 0.65 | W20: 6.3 | X20: {=_xlfn.IFS($F20<Glossary!$C$54,Glossary!$B$54,$F20<Glossary!$C$55,Glossary!$B$55,$F20>Glossary!$C$56,Glossary!$B$56)} -> Small Cap | Y20: Hyderabad | Z20: Family | AA20: 0.6032 | AC20: High | AD20: High | AE20: High | AT20: Y | AU20: Tier 4 | AV20: 78 | AW20: 78 | AX20: 78 | AY20: 52 | AZ20: 40 | BA20: 29 | BB20: 22 | BC20: 58.74 | BG20: 0.216 | BK20: 0.1223 | BL20: 0.22 | BM20: 0.16 | BN20: 0.22 | CE20: =IFERROR(RATE(4,,BB20,-AY20),"") -> 0.23992428 | CF20: =IF(CE20>='Conviction List'!$D$9,1,"") | CG20: =IF(M20<='Conviction List'!$E$9,1,"") -> 1 | CH20: =IF(BG20>='Conviction List'!$F$9,1,"") -> 1 | CI20: =IF(BK20>='Conviction List'!$G$9,1,"") -> 1 | CJ20: =SUM(CF20:CI20) -> 3 | CK20: =MATCH($D20,INDIRECT($C$90&"!$C$1:$C$164"),0) -> 27
B21: =B20+1 -> 19 | C21: Zen Technologies | D21: ZEN | E21: ZENTEC | F21: =_xlfn.XLOOKUP(CCA_Defense!$D21,BB_Input!$C$4:$C$172,BB_Input!$G$4:$G$172) -> 1399.8115 | G21: 1993 | H21: =YEAR(TODAY())-G21 -> 33 | I21: Listed | J21: Training simulators | L21: Yes | M21: 61 | N21: =IFERROR(_xlfn.XLOOKUP($D21,PE_Projections!$D:$D,PE_Projections!L:L),"") -> 46.506808 | O21: =IFERROR(_xlfn.XLOOKUP($D21,PE_Projections!$D:$D,PE_Projections!M:M),"") -> 30.078893 | P21: =IFERROR(_xlfn.XLOOKUP($D21,PE_Projections!$D:$D,PE_Projections!N:N),"") -> 23.192367 | Q21: =IFERROR(_xlfn.XLOOKUP($D21,PE_Projections!$D:$D,PE_Projections!O:O),"") | R21: =IFERROR(_xlfn.XLOOKUP($D21,PE_Projections!$D:$D,PE_Projections!P:P),"") | T21: =IFERROR(RATE(5,,BB21,-AY21),"") -> 0.39868042 | V21: =AVERAGE(70%,80%) -> 0.75 | W21: 1 | X21: {=_xlfn.IFS($F21<Glossary!$C$54,Glossary!$B$54,$F21<Glossary!$C$55,Glossary!$B$55,$F21>Glossary!$C$56,Glossary!$B$56)} -> Small Cap | Y21: Hyderabad | Z21: Family | AA21: 0.4905 | AC21: Medium | AD21: High | AE21: High | AR21: Y | AU21: Tier 3 | AV21: 83.2 | AW21: 83.2 | AX21: 83.2 | AY21: 91 | AZ21: 53 | BA21: 26 | BB21: 17 | BC21: 38.7 | BD21: 41.2 | BG21: 0.2608 | BH21: 0.269 | BI21: 0.085 | BJ21: 0.003 | BK21: 0.3671 | BL21: 0.33 | BS21: 0 | BT21: 0.02 | BU21: 0.04 | CE21: =IFERROR(RATE(4,,BB21,-AY21),"") -> 0.52106621 | CF21: =IF(CE21>='Conviction List'!$D$8,1,"") -> 1 | CG21: =IF(M21<='Conviction List'!$E$8,1,"") -> 1 | CH21: =IF(BG21>='Conviction List'!$F$8,1,"") -> 1 | CI21: =IF(BK21>='Conviction List'!$G$8,1,"") -> 1 | CJ21: =SUM(CF21:CI21) -> 4 | CK21: =MATCH($D21,INDIRECT($C$90&"!$C$1:$C$164"),0) -> 23
B22: =B21+1 -> 20 | C22: C2C Advanced Systems | D22: C2C | E22: C2C | F22: =_xlfn.XLOOKUP(CCA_Defense!$D22,BB_Input!$C$4:$C$172,BB_Input!$G$4:$G$172) -> 91.853865 | G22: 2012 | H22: =YEAR(TODAY())-G22 -> 14 | I22: Listed | J22: Command systems | L22: Yes | M22: 36 | N22: =IFERROR(_xlfn.XLOOKUP($D22,PE_Projections!$D:$D,PE_Projections!L:L),"") -> 20.472867 | O22: =IFERROR(_xlfn.XLOOKUP($D22,PE_Projections!$D:$D,PE_Projections!M:M),"") -> 17.930853 | P22: =IFERROR(_xlfn.XLOOKUP($D22,PE_Projections!$D:$D,PE_Projections!N:N),"") -> 15.704468 | Q22: =IFERROR(_xlfn.XLOOKUP($D22,PE_Projections!$D:$D,PE_Projections!O:O),"") -> 13.754523 | R22: =IFERROR(_xlfn.XLOOKUP($D22,PE_Projections!$D:$D,PE_Projections!P:P),"") -> 12.046692 | S22: 180 | T22: =IFERROR(RATE(5,,BB22,-AY22),"") | U22: 0.4427 | V22: 0.365 | X22: {=_xlfn.IFS($F22<Glossary!$C$54,Glossary!$B$54,$F22<Glossary!$C$55,Glossary!$B$55,$F22>Glossary!$C$56,Glossary!$B$56)} -> Small Cap | Y22: New Delhi | Z22: Private | AA22: 0.4145 | AC22: High | AD22: High | AE22: High | AF22: Heavy naval business mix dependant on relationships fostered by Cdr Narendra Lanka (COO) & CEO | AQ22: Y | AU22: Tier 3 | AV22: 16.64 | AW22: 17 | AX22: 1.5 | AY22: 13.2 | AZ22: 4.7 | BA22: 0.92 | BC22: 24.7 | BG22: 0.1774 | BH22: 0.1606 | BK22: 0.26 | BL22: 0.225 | BM22: 0.35 | BO22: 1.63 | BS22: 0.24 | CF22: =IF(CE22>='Conviction List'!$D$8,1,"") | CG22: =IF(M22<='Conviction List'!$E$8,1,"") -> 1 | CH22: =IF(BG22>='Conviction List'!$F$8,1,"") -> 1 | CI22: =IF(BK22>='Conviction List'!$G$8,1,"") -> 1 | CJ22: =SUM(CF22:CI22) -> 3 | CK22: =MATCH($D22,INDIRECT($C$90&"!$C$1:$C$164"),0) -> 71
B23: =B22+1 -> 21 | C23: Centum Electronics | D23: CTE | E23: CTE | F23: =_xlfn.XLOOKUP(CCA_Defense!$D23,BB_Input!$C$4:$C$172,BB_Input!$G$4:$G$172) -> 393.71613 | G23: 1993 | H23: =YEAR(TODAY())-G23 -> 33 | I23: Listed | J23: Space electronics | L23: Yes | N23: =IFERROR(_xlfn.XLOOKUP($D23,PE_Projections!$D:$D,PE_Projections!L:L),"") -> 65.524589 | O23: =IFERROR(_xlfn.XLOOKUP($D23,PE_Projections!$D:$D,PE_Projections!M:M),"") -> 35.955022 | P23: =IFERROR(_xlfn.XLOOKUP($D23,PE_Projections!$D:$D,PE_Projections!N:N),"") -> 22.949282 | Q23: =IFERROR(_xlfn.XLOOKUP($D23,PE_Projections!$D:$D,PE_Projections!O:O),"") | R23: =IFERROR(_xlfn.XLOOKUP($D23,PE_Projections!$D:$D,PE_Projections!P:P),"") | T23: =IFERROR(RATE(5,,BB23,-AY23),"") -> 0.072374264 | V23: =AVERAGE(60%,70%) -> 0.65 | W23: 12.8 | X23: {=_xlfn.IFS($F23<Glossary!$C$54,Glossary!$B$54,$F23<Glossary!$C$55,Glossary!$B$55,$F23>Glossary!$C$56,Glossary!$B$56)} -> Small Cap | Y23: Bangalore | Z23: Private | AA23: 0.5152 | AC23: High | AD23: High | AE23: High | AM23: Y | AP23: Y | AQ23: Y | AR23: Y | AU23: Diversified | AV23: 13.1 | AW23: 13.1 | AX23: 13.1 | AY23: 156 | AZ23: 139 | BA23: 127 | BB23: 110 | BC23: 33.4 | BD23: 10.5 | BE23: 12 | BH23: 0.18 | BI23: 0.165 | BJ23: 0.15 | BL23: 0.15 | BM23: 0.14 | BN23: 0.12 | BO23: 0 | BP23: 0 | BQ23: 0.1 | BR23: 0.3 | BS23: 0.85 | BT23: 1.25 | BU23: 1.34 | CE23: =IFERROR(RATE(4,,BB23,-AY23),"") -> 0.091271915 | CF23: =IF(CE23>='Conviction List'!$D$4,1,"") | CG23: =IF(M21<='Conviction List'!$E$4,1,"") -> 1 | CH23: =IF(BG23>='Conviction List'!$F$4,1,"") | CI23: =IF(BK23>='Conviction List'!$G$4,1,"") | CJ23: =SUM(CF23:CI23) -> 1 | CK23: =MATCH($D23,INDIRECT($C$90&"!$C$1:$C$164"),0) -> 16
B24: =B23+1 -> 22 | C24: IdeaForge Technology Ltd | D24: IDEAFORG | E24: IDEAFORGE | F24: =_xlfn.XLOOKUP(CCA_Defense!$D24,BB_Input!$C$4:$C$172,BB_Input!$G$4:$G$172) -> 231.34958 | G24: 2007 | H24: =YEAR(TODAY())-G24 -> 19 | I24: Listed | J24: UAVs | L24: Yes | N24: =IFERROR(_xlfn.XLOOKUP($D24,PE_Projections!$D:$D,PE_Projections!L:L),"") | O24: =IFERROR(_xlfn.XLOOKUP($D24,PE_Projections!$D:$D,PE_Projections!M:M),"") | P24: =IFERROR(_xlfn.XLOOKUP($D24,PE_Projections!$D:$D,PE_Projections!N:N),"") -> 27.268411 | Q24: =IFERROR(_xlfn.XLOOKUP($D24,PE_Projections!$D:$D,PE_Projections!O:O),"") -> 33.792365 | R24: =IFERROR(_xlfn.XLOOKUP($D24,PE_Projections!$D:$D,PE_Projections!P:P),"") -> 25.126303 | T24: =IFERROR(RATE(5,,BB24,-AY24),"") -> 0.25007157 | U24: 0.3449 | V24: =AVERAGE(50%,60%) -> 0.55 | W24: 0.7 | X24: {=_xlfn.IFS($F24<Glossary!$C$54,Glossary!$B$54,$F24<Glossary!$C$55,Glossary!$B$55,$F24>Glossary!$C$56,Glossary!$B$56)} -> Small Cap | Y24: Navi Mumbai | Z24: Private | AA24: 0.2917 | AC24: Medium | AD24: High | AE24: High | AF24: Heavy on R&D & mgmt mentioned that they tend to innovate even prior to RFQs from the govt which can be equated to "taking shots in the dark" | AH24: Y | AU24: Diversified | AV24: 43.8 | AW24: 43.8 | AX24: 43.8 | AY24: 58 | AZ24: 40 | BA24: 23 | BB24: 19 | BC24: -77.4 | BD24: 48.9 | BG24: -0.098 | BH24: 0.144 | BI24: 0.172 | BK24: -0.0936 | BL24: 0.496 | BM24: 0.125 | BN24: 0.112 | BS24: 0 | BT24: 0.27 | CE24: =IFERROR(RATE(4,,BB24,-AY24),"") -> 0.32180868 | CF24: =IF(CE24>='Conviction List'!$D$4,1,"") -> 1 | CG24: =IF(M22<='Conviction List'!$E$4,1,"") -> 1 | CH24: =IF(BG24>='Conviction List'!$F$4,1,"") | CI24: =IF(BK24>='Conviction List'!$G$4,1,"") | CJ24: =SUM(CF24:CI24) -> 2 | CK24: =MATCH($D24,INDIRECT($C$90&"!$C$1:$C$164"),0) -> 26
B25: =B24+1 -> 23 | C25: Cyient DLM Ltd | D25: CYIENTDL | E25: CYIENT | F25: =_xlfn.XLOOKUP(CCA_Defense!$D25,BB_Input!$C$4:$C$172,BB_Input!$G$4:$G$172) -> 376.52703 | G25: 2022 | H25: =YEAR(TODAY())-G25 -> 4 | I25: Listed | J25: EMS | L25: Yes | M25: 54.4 | N25: =IFERROR(_xlfn.XLOOKUP($D25,PE_Projections!$D:$D,PE_Projections!L:L),"") -> 39.887602 | O25: =IFERROR(_xlfn.XLOOKUP($D25,PE_Projections!$D:$D,PE_Projections!M:M),"") -> 26.816751 | P25: =IFERROR(_xlfn.XLOOKUP($D25,PE_Projections!$D:$D,PE_Projections!N:N),"") -> 20.122067 | Q25: =IFERROR(_xlfn.XLOOKUP($D25,PE_Projections!$D:$D,PE_Projections!O:O),"") -> 15.005286 | R25: =IFERROR(_xlfn.XLOOKUP($D25,PE_Projections!$D:$D,PE_Projections!P:P),"") | S25: 23 | T25: =IFERROR(RATE(5,,BB25,-AY25),"") -> 0.16353388 | V25: =AVERAGE(60%,70%) -> 0.65 | W25: 1.6 | X25: {=_xlfn.IFS($F25<Glossary!$C$54,Glossary!$B$54,$F25<Glossary!$C$55,Glossary!$B$55,$F25>Glossary!$C$56,Glossary!$B$56)} -> Small Cap | Y25: Bangalore | Z25: Private | AA25: 0.5216 | AB25: CYIENT, 52% | AC25: High | AD25: High | AE25: High | AP25: Y | AQ25: Y | AR25: Y | AU25: Tier 3 | AV25: 57.1 | AW25: 57.1 | AX25: 57.1 | AY25: 177 | AZ25: 138 | BA25: 96 | BB25: 83 | BC25: 23.32 | BG25: 0.0733 | BK25: 0.109 | BL25: 0.16 | BM25: 0.14 | BN25: 0.2 | BT25: 1.8 | BU25: 4.37 | CE25: =IFERROR(RATE(4,,BB25,-AY25),"") -> 0.20843639 | CF25: =IF(CE25>='Conviction List'!$D$8,1,"") | CG25: =IF(M25<='Conviction List'!$E$8,1,"") -> 1 | CH25: =IF(BG25>='Conviction List'!$F$8,1,"") | CI25: =IF(BK25>='Conviction List'!$G$8,1,"") | CJ25: =SUM(CF25:CI25) -> 1 | CK25: =MATCH($D25,INDIRECT($C$90&"!$C$1:$C$164"),0) -> 30
B26: =B25+1 -> 24 | C26: JayKay Enterprises | D26: JEL | E26: JAYKAY | F26: =_xlfn.XLOOKUP(CCA_Defense!$D26,BB_Input!$C$4:$C$172,BB_Input!$G$4:$G$172) -> 288.03437 | G26: 1978 | H26: =YEAR(TODAY())-G26 -> 48 | I26: Listed | J26: Holding company | M26: 100 | N26: =IFERROR(_xlfn.XLOOKUP($D26,PE_Projections!$D:$D,PE_Projections!L:L),"") -> 78.989184 | O26: =IFERROR(_xlfn.XLOOKUP($D26,PE_Projections!$D:$D,PE_Projections!M:M),"") -> 51.417814 | P26: =IFERROR(_xlfn.XLOOKUP($D26,PE_Projections!$D:$D,PE_Projections!N:N),"") -> 33.470299 | Q26: =IFERROR(_xlfn.XLOOKUP($D26,PE_Projections!$D:$D,PE_Projections!O:O),"") -> 21.787409 | R26: =IFERROR(_xlfn.XLOOKUP($D26,PE_Projections!$D:$D,PE_Projections!P:P),"") -> 14.18246 | S26: 202 | T26: =IFERROR(RATE(5,,BB26,-AY26),"") -> 0.67027765 | V26: =AVERAGE(50%,60%) -> 0.55 | X26: {=_xlfn.IFS($F26<Glossary!$C$54,Glossary!$B$54,$F26<Glossary!$C$55,Glossary!$B$55,$F26>Glossary!$C$56,Glossary!$B$56)} -> Small Cap | Y26: Mumbai | Z26: Family | AA26: 0.6331 | AC26: High | AD26: High | AE26: High | AT26: Y | AU26: Tier 4 | AV26: 72.3 | AW26: 72.3 | AX26: 72.3 | AY26: 13 | AZ26: 6 | BA26: 5 | BB26: 1 | BC26: 70.38 | BG26: 0.143 | BK26: 0.033 | BL26: 0.17 | BM26: 0.03 | BN26: 0.04 | BS26: 0.02 | BT26: 0 | BU26: 0 | CE26: =IFERROR(RATE(4,,BB26,-AY26),"") -> 0.89882892 | CF26: =IF(CE26>='Conviction List'!$D$9,1,"") -> 1 | CG26: =IF(M26<='Conviction List'!$E$9,1,"") -> 1 | CH26: =IF(BG26>='Conviction List'!$F$9,1,"") -> 1 | CI26: =IF(BK26>='Conviction List'!$G$9,1,"") | CJ26: =SUM(CF26:CI26) -> 3 | CK26: =MATCH($D26,INDIRECT($C$90&"!$C$1:$C$164"),0) -> 28
B27: =B26+1 -> 25 | C27: Sika Interplant Systems | D27: SIKA | E27: SIKA | F27: =_xlfn.XLOOKUP(CCA_Defense!$D27,BB_Input!$C$4:$C$172,BB_Input!$G$4:$G$172) -> 213.04636 | G27: 1993 | H27: =YEAR(TODAY())-G27 -> 33 | I27: Listed | J27: Aerospace tooling | M27: 82 | N27: =IFERROR(_xlfn.XLOOKUP($D27,PE_Projections!$D:$D,PE_Projections!L:L),"") -> 73.677848 | O27: =IFERROR(_xlfn.XLOOKUP($D27,PE_Projections!$D:$D,PE_Projections!M:M),"") -> 69.220969 | P27: =IFERROR(_xlfn.XLOOKUP($D27,PE_Projections!$D:$D,PE_Projections!N:N),"") -> 66.946448 | Q27: =IFERROR(_xlfn.XLOOKUP($D27,PE_Projections!$D:$D,PE_Projections!O:O),"") -> 64.746665 | R27: =IFERROR(_xlfn.XLOOKUP($D27,PE_Projections!$D:$D,PE_Projections!P:P),"") -> 60.879744 | S27: 58 | T27: =IFERROR(RATE(5,,BB27,-AY27),"") -> 0.033975227 | V27: =AVERAGE(80%,85%) -> 0.825 | X27: {=_xlfn.IFS($F27<Glossary!$C$54,Glossary!$B$54,$F27<Glossary!$C$55,Glossary!$B$55,$F27>Glossary!$C$56,Glossary!$B$56)} -> Small Cap | Y27: Bangalore | Z27: Family | AA27: 0.7172 | AC27: High | AD27: High | AE27: High | AP27: Y | AQ27: Y | AU27: Tier 3 | AV27: 3.4 | AW27: 3.4 | AX27: 3.4 | AY27: 13 | AZ27: 12 | BA27: 7 | BB27: 11 | BC27: 90.49 | BG27: 0.2204 | BK27: 0.2904 | BL27: 0.26 | BM27: 0.15 | BN27: 0.31 | BS27: 2.84 | BT27: 3.14 | BU27: 0 | CE27: =IFERROR(RATE(4,,BB27,-AY27),"") -> 0.042647885 | CF27: =IF(CE27>='Conviction List'!$D$8,1,"") | CG27: =IF(M27<='Conviction List'!$E$8,1,"") -> 1 | CH27: =IF(BG27>='Conviction List'!$F$8,1,"") -> 1 | CI27: =IF(BK27>='Conviction List'!$G$8,1,"") -> 1 | CJ27: =SUM(CF27:CI27) -> 3 | CK27: =MATCH($D27,INDIRECT($C$90&"!$C$1:$C$164"),0) -> 29
B28: =B27+1 -> 26 | C28: Dynamatic Technologies Ltd | D28: DYTC | E28: DYNAMATECH | F28: =_xlfn.XLOOKUP(CCA_Defense!$D28,BB_Input!$C$4:$C$172,BB_Input!$G$4:$G$172) -> 731.76171 | G28: 1973 | H28: =YEAR(TODAY())-G28 -> 53 | I28: Listed | J28: Aerostructures | L28: Yes | M28: 113 | N28: =IFERROR(_xlfn.XLOOKUP($D28,PE_Projections!$D:$D,PE_Projections!L:L),"") -> 124.15276 | O28: =IFERROR(_xlfn.XLOOKUP($D28,PE_Projections!$D:$D,PE_Projections!M:M),"") -> 68.013361 | P28: =IFERROR(_xlfn.XLOOKUP($D28,PE_Projections!$D:$D,PE_Projections!N:N),"") -> 48.576092 | Q28: =IFERROR(_xlfn.XLOOKUP($D28,PE_Projections!$D:$D,PE_Projections!O:O),"") -> 25.326682 | R28: =IFERROR(_xlfn.XLOOKUP($D28,PE_Projections!$D:$D,PE_Projections!P:P),"") | S28: -2 | T28: =IFERROR(RATE(5,,BB28,-AY28),"") -> 0.022702436 | V28: =AVERAGE(55%,60%) -> 0.575 | W28: 6.8 | X28: {=_xlfn.IFS($F28<Glossary!$C$54,Glossary!$B$54,$F28<Glossary!$C$55,Glossary!$B$55,$F28>Glossary!$C$56,Glossary!$B$56)} -> Small Cap | Y28: Bangalore | Z28: Private | AA28: 0.48 | AC28: High | AD28: High | AE28: High | AG28: Dr. Udayant Malhoutra is the Promoter & CEO | AK28: Y | AL28: Y | AU28: Tier 1 | AV28: 6.3 | AW28: 6.3 | AX28: 6.3 | AY28: 162 | AZ28: 165 | BA28: 152 | BB28: 144.8 | BC28: 30.16 | BG28: 0.062 | BK28: 0.088 | CF28: =IF(CE28>='Conviction List'!$D$8,1,"") | CG28: =IF(M28<='Conviction List'!$E$8,1,"") | CH28: =IF(BG28>='Conviction List'!$F$8,1,"") | CI28: =IF(BK28>='Conviction List'!$G$8,1,"") | CJ28: =SUM(CF28:CI28) -> 0 | CK28: =MATCH($D28,INDIRECT($C$90&"!$C$1:$C$164"),0) -> 48
B29: =B28+1 -> 27 | C29: Kaynes Technology Ltd | D29: KAYNES | E29: KAYNES | F29: =_xlfn.XLOOKUP(CCA_Defense!$D29,BB_Input!$C$4:$C$172,BB_Input!$G$4:$G$172) -> 3075.7585 | G29: 2008 | H29: =YEAR(TODAY())-G29 -> 18 | I29: Listed | J29: EMS | L29: Yes | M29: 146 | N29: =IFERROR(_xlfn.XLOOKUP($D29,PE_Projections!$D:$D,PE_Projections!L:L),"") -> 58.586449 | O29: =IFERROR(_xlfn.XLOOKUP($D29,PE_Projections!$D:$D,PE_Projections!M:M),"") -> 42.16206 | P29: =IFERROR(_xlfn.XLOOKUP($D29,PE_Projections!$D:$D,PE_Projections!N:N),"") -> 30.930776 | Q29: =IFERROR(_xlfn.XLOOKUP($D29,PE_Projections!$D:$D,PE_Projections!O:O),"") -> 20.724359 | R29: =IFERROR(_xlfn.XLOOKUP($D29,PE_Projections!$D:$D,PE_Projections!P:P),"") | S29: 111 | T29: =IFERROR(RATE(5,,BB29,-AY29),"") -> 0.27657457 | V29: =AVERAGE(50%,60%) -> 0.55 | W29: 3.2 | X29: {=_xlfn.IFS($F29<Glossary!$C$54,Glossary!$B$54,$F29<Glossary!$C$55,Glossary!$B$55,$F29>Glossary!$C$56,Glossary!$B$56)} -> Mid Cap | Y29: Mysore | Z29: Family | AA29: 0.5775 | AC29: Medium | AD29: High | AE29: High | AQ29: Y | AU29: Tier 3 | AV29: 36.5 | AW29: 36.5 | AX29: 36.5 | AY29: 278 | AZ29: 211 | BA29: 131 | BB29: 82 | BC29: 79.16 | BD29: 56 | BE29: 26 | BG29: 0.1102 | BH29: 0.0737 | BI29: 0.0993 | BJ29: 0.2057 | BK29: 0.144 | BL29: 0.1127 | BM29: 0.1604 | BN29: 0.3216 | BO29: 3.08 | BS29: 0.11 | BT29: 0.13 | BU29: 0.14 | CE29: =IFERROR(RATE(4,,BB29,-AY29),"") -> 0.35693091 | CF29: =IF(CE29>='Conviction List'!$D$8,1,"") -> 1 | CG29: =IF(M29<='Conviction List'!$E$8,1,"") | CH29: =IF(BG29>='Conviction List'!$F$8,1,"") | CI29: =IF(BK29>='Conviction List'!$G$8,1,"") | CJ29: =SUM(CF29:CI29) -> 1 | CK29: =MATCH($D29,INDIRECT($C$90&"!$C$1:$C$164"),0) -> 31
B30: =B29+1 -> 28 | C30: Syrma SGS Technology Ltd | D30: SYRMA | E30: SYRMA | F30: =_xlfn.XLOOKUP(CCA_Defense!$D30,BB_Input!$C$4:$C$172,BB_Input!$G$4:$G$172) -> 1576.5101 | G30: 1991 | H30: =YEAR(TODAY())-G30 -> 35 | I30: Listed | J30: EMS | M30: 62 | N30: =IFERROR(_xlfn.XLOOKUP($D30,PE_Projections!$D:$D,PE_Projections!L:L),"") -> 52.869449 | O30: =IFERROR(_xlfn.XLOOKUP($D30,PE_Projections!$D:$D,PE_Projections!M:M),"") -> 36.643397 | P30: =IFERROR(_xlfn.XLOOKUP($D30,PE_Projections!$D:$D,PE_Projections!N:N),"") -> 27.262702 | Q30: =IFERROR(_xlfn.XLOOKUP($D30,PE_Projections!$D:$D,PE_Projections!O:O),"") -> 19.449008 | R30: =IFERROR(_xlfn.XLOOKUP($D30,PE_Projections!$D:$D,PE_Projections!P:P),"") | T30: =IFERROR(RATE(5,,BB30,-AY30),"") -> 0.30068267 | V30: =AVERAGE(40%,50%) -> 0.45 | W30: 1.4 | X30: {=_xlfn.IFS($F30<Glossary!$C$54,Glossary!$B$54,$F30<Glossary!$C$55,Glossary!$B$55,$F30>Glossary!$C$56,Glossary!$B$56)} -> Small Cap | Y30: Chennai | Z30: Private | AA30: 0.4653 | AC30: High | AD30: High | AE30: High | AP30: Y | AQ30: Y | AU30: Tier 3 | AV30: 176.8 | AW30: 176.8 | AX30: 176.8 | AY30: 443 | AZ30: 369 | BA30: 240 | BB30: 119 | BC30: 29.82 | BD30: 97.2 | BE30: 44.3 | BF30: 19.46 | BG30: 0.1019 | BH30: 0.0666 | BI30: 0.0775 | BJ30: 0.0971 | BK30: 0.1241 | BL30: 0.0345 | BM30: 0.0645 | BN30: 0.0927 | BO30: 3.6 | BS30: 0.34 | BT30: 0.22 | BU30: 0.33 | CE30: =IFERROR(RATE(4,,BB30,-AY30),"") -> 0.38903821 | CF30: =IF(CE30>='Conviction List'!$D$8,1,"") -> 1 | CG30: =IF(M30<='Conviction List'!$E$8,1,"") -> 1 | CH30: =IF(BG30>='Conviction List'!$F$8,1,"") | CI30: =IF(BK30>='Conviction List'!$G$8,1,"") | CJ30: =SUM(CF30:CI30) -> 2 | CK30: =MATCH($D30,INDIRECT($C$90&"!$C$1:$C$164"),0) -> 32
B31: =B30+1 -> 29 | C31: Solar Industries India Ltd | D31: SOIL | E31: SOLARINDS | F31: =_xlfn.XLOOKUP(CCA_Defense!$D31,BB_Input!$C$4:$C$172,BB_Input!$G$4:$G$172) -> 12586.448 | G31: 1995 | H31: =YEAR(TODAY())-G31 -> 31 | I31: Listed | J31: Explosives | M31: 108 | N31: =IFERROR(_xlfn.XLOOKUP($D31,PE_Projections!$D:$D,PE_Projections!L:L),"") -> 66.813536 | O31: =IFERROR(_xlfn.XLOOKUP($D31,PE_Projections!$D:$D,PE_Projections!M:M),"") -> 52.071217 | P31: =IFERROR(_xlfn.XLOOKUP($D31,PE_Projections!$D:$D,PE_Projections!N:N),"") -> 43.450835 | Q31: =IFERROR(_xlfn.XLOOKUP($D31,PE_Projections!$D:$D,PE_Projections!O:O),"") -> 34.141873 | R31: =IFERROR(_xlfn.XLOOKUP($D31,PE_Projections!$D:$D,PE_Projections!P:P),"") | S31: 9 | T31: =IFERROR(RATE(5,,BB31,-AY31),"") -> 0.12104299 | V31: 5-9% | W31: 2.2 | X31: {=_xlfn.IFS($F31<Glossary!$C$54,Glossary!$B$54,$F31<Glossary!$C$55,Glossary!$B$55,$F31>Glossary!$C$56,Glossary!$B$56)} -> Large Cap | Y31: Nagpur | Z31: Family | AA31: 0.7315 | AC31: High | AD31: High | AE31: High | AH31: Y | AM31: Y | AN31: Y | AO31: Y | AU31: Diversified | AY31: 818 | AZ31: 711 | BA31: 810 | BB31: 462 | BC31: 72.41 | BD31: 56.8 | BE31: 27.84 | BF31: 19.92 | BG31: 0.3264 | BH31: 0.2529 | BI31: 0.2901 | BJ31: 0.235 | BK31: 0.3813 | BL31: 0.299 | BM31: 0.334 | BN31: 0.275 | BS31: 0.19 | BT31: 0.35 | BU31: 0.41 | CE31: =IFERROR(RATE(4,,BB31,-AY31),"") -> 0.15352718 | CF31: =IF(CE31>='Conviction List'!$D$4,1,"") | CG31: =IF(M29<='Conviction List'!$E$4,1,"") | CH31: =IF(BG31>='Conviction List'!$F$4,1,"") -> 1 | CI31: =IF(BK31>='Conviction List'!$G$4,1,"") -> 1 | CJ31: =SUM(CF31:CI31) -> 2 | CK31: =MATCH($D31,INDIRECT($C$90&"!$C$1:$C$164"),0) -> 33
B32: =B31+1 -> 30 | C32: Bharat Forge Ltd | D32: BHFC | E32: BHARATFORG | F32: =_xlfn.XLOOKUP(CCA_Defense!$D32,BB_Input!$C$4:$C$172,BB_Input!$G$4:$G$172) -> 7725.7373 | G32: 1961 | H32: =YEAR(TODAY())-G32 -> 65 | I32: Listed | J32: Defence forgings | M32: 58 | N32: =IFERROR(_xlfn.XLOOKUP($D32,PE_Projections!$D:$D,PE_Projections!L:L),"") -> 54.214166 | O32: =IFERROR(_xlfn.XLOOKUP($D32,PE_Projections!$D:$D,PE_Projections!M:M),"") -> 40.96701 | P32: =IFERROR(_xlfn.XLOOKUP($D32,PE_Projections!$D:$D,PE_Projections!N:N),"") -> 34.129733 | Q32: =IFERROR(_xlfn.XLOOKUP($D32,PE_Projections!$D:$D,PE_Projections!O:O),"") -> 25.76491 | R32: =IFERROR(_xlfn.XLOOKUP($D32,PE_Projections!$D:$D,PE_Projections!P:P),"") | S32: -4 | T32: =IFERROR(RATE(5,,BB32,-AY32),"") -> 0.076451952 | V32: =AVERAGE(10%,15%) -> 0.125 | W32: 9.2 | X32: {=_xlfn.IFS($F32<Glossary!$C$54,Glossary!$B$54,$F32<Glossary!$C$55,Glossary!$B$55,$F32>Glossary!$C$56,Glossary!$B$56)} -> Mid Cap | Y32: Pune | Z32: Government | AA32: 0.44078 | AC32: High | AD32: High | AE32: High | AI32: Y | AK32: Y | AL32: Y | AM32: Y | AN32: Y | AQ32: Y | AU32: Diversified | AV32: 466 | AW32: 466 | AX32: 466 | AY32: 1772 | AZ32: 1827 | BA32: 1513 | BB32: 1226 | BC32: 23.27 | BD32: 21.08 | BE32: 22.3 | BF32: 16.14 | BG32: 0.1227 | BH32: 0.1327 | BI32: 0.0788 | BJ32: 0.1646 | BK32: 0.1309 | BL32: 0.1912 | BM32: 0.1147 | BN32: 0.1667 | BS32: 0.52 | BT32: 0.58 | BU32: 0.2 | CE32: =IFERROR(RATE(4,,BB32,-AY32),"") -> 0.09646131 | CF32: =IF(CE32>='Conviction List'!$D$4,1,"") | CG32: =IF(M30<='Conviction List'!$E$4,1,"") -> 1 | CH32: =IF(BG32>='Conviction List'!$F$4,1,"") | CI32: =IF(BK32>='Conviction List'!$G$4,1,"") | CJ32: =SUM(CF32:CI32) -> 1 | CK32: =MATCH($D32,INDIRECT($C$90&"!$C$1:$C$164"),0) -> 34
B33: =B32+1 -> 31 | C33: Larsen & Toubro Ltd (L&T) | D33: LT | E33: LT | F33: =_xlfn.XLOOKUP(CCA_Defense!$D33,BB_Input!$C$4:$C$172,BB_Input!$G$4:$G$172) -> 62121.34 | G33: 1946 | H33: =YEAR(TODAY())-G33 -> 80 | I33: Acquired by/Part of Listed Company | J33: Defence EPC | M33: 33 | N33: =IFERROR(_xlfn.XLOOKUP($D33,PE_Projections!$D:$D,PE_Projections!L:L),"") -> 30.839425 | O33: =IFERROR(_xlfn.XLOOKUP($D33,PE_Projections!$D:$D,PE_Projections!M:M),"") -> 25.364498 | P33: =IFERROR(_xlfn.XLOOKUP($D33,PE_Projections!$D:$D,PE_Projections!N:N),"") -> 21.507315 | Q33: =IFERROR(_xlfn.XLOOKUP($D33,PE_Projections!$D:$D,PE_Projections!O:O),"") -> 18.582136 | R33: =IFERROR(_xlfn.XLOOKUP($D33,PE_Projections!$D:$D,PE_Projections!P:P),"") | S33: 16 | T33: =IFERROR(RATE(5,,BB33,-AY33),"") -> 0.10317481 | V33: 0.05 | W33: 3 | X33: {=_xlfn.IFS($F33<Glossary!$C$54,Glossary!$B$54,$F33<Glossary!$C$55,Glossary!$B$55,$F33>Glossary!$C$56,Glossary!$B$56)} -> Large Cap | Y33: Mumbai | Z33: Private | AA33: 0.198 | AC33: High | AD33: High | AE33: High | AG33: L&T | AJ33: Y | AT33: Y | AU33: Diversified | AV33: 1403 | AW33: 1403 | AX33: 1403 | AY33: 29972 | AZ33: 25914 | BA33: 21487 | BB33: 18344 | BC33: 15.8 | BD33: 22.55 | BE33: 17.05 | BF33: 17.4 | BG33: 0.1655 | BH33: 0.1512 | BI33: 0.1172 | BJ33: 0.1049 | BK33: 0.1449 | BL33: 0.1476 | BM33: 0.1207 | BN33: 0.1098 | BS33: 0.35 | BT33: 0.25 | BU33: 0.3 | CE33: =IFERROR(RATE(4,,BB33,-AY33),"") -> 0.13059073 | CF33: =IF(CE33>='Conviction List'!$D$4,1,"") | CG33: =IF(M31<='Conviction List'!$E$4,1,"") | CH33: =IF(BG33>='Conviction List'!$F$4,1,"") -> 1 | CI33: =IF(BK33>='Conviction List'!$G$4,1,"") | CJ33: =SUM(CF33:CI33) -> 1 | CK33: =MATCH($D33,INDIRECT($C$90&"!$C$1:$C$164"),0) -> 35
B34: =B33+1 -> 32 | C34: Bharat Heavy Electricals Ltd | D34: BHEL | E34: BHEL | F34: =_xlfn.XLOOKUP(CCA_Defense!$D34,BB_Input!$C$4:$C$172,BB_Input!$G$4:$G$172) -> 10792.141 | G34: 1964 | H34: =YEAR(TODAY())-G34 -> 62 | I34: Listed | J34: Heavy engineering | M34: 156 | N34: =IFERROR(_xlfn.XLOOKUP($D34,PE_Projections!$D:$D,PE_Projections!L:L),"") -> 55.68455 | O34: =IFERROR(_xlfn.XLOOKUP($D34,PE_Projections!$D:$D,PE_Projections!M:M),"") -> 31.449244 | P34: =IFERROR(_xlfn.XLOOKUP($D34,PE_Projections!$D:$D,PE_Projections!N:N),"") -> 22.968009 | Q34: =IFERROR(_xlfn.XLOOKUP($D34,PE_Projections!$D:$D,PE_Projections!O:O),"") | R34: =IFERROR(_xlfn.XLOOKUP($D34,PE_Projections!$D:$D,PE_Projections!P:P),"") | S34: 16 | T34: =IFERROR(RATE(5,,BB34,-AY34),"") -> 0.054167392 | V34: =AVERAGE(5%,10%) -> 0.075 | W34: 7.4 | X34: {=_xlfn.IFS($F34<Glossary!$C$54,Glossary!$B$54,$F34<Glossary!$C$55,Glossary!$B$55,$F34>Glossary!$C$56,Glossary!$B$56)} -> Large Cap | Y34: New Delhi | Z34: Government | AA34: 0.6317 | AC34: High | AD34: High | AE34: High | AI34: Y | AJ34: Y | AK34: Y | AL34: Y | AM34: Y | AR34: Y | AU34: Diversified | AV34: 3476 | AW34: 3476 | AX34: 3476 | AY34: 3235 | AZ34: 2800 | BA34: 2738 | BB34: 2485 | BC34: 51.9 | BD34: 76.6 | BE34: 21.11 | BF34: 18.6 | BG34: 0.0217 | BH34: 0.0115 | BI34: 0.0157 | BJ34: 0.0168 | BK34: 0.0446 | BL34: 0.027 | BM34: 0.026 | BN34: 0.0237 | BS34: 0 | BT34: 0 | BU34: 0 | CE34: =IFERROR(RATE(4,,BB34,-AY34),"") -> 0.068161629 | CF34: =IF(CE34>='Conviction List'!$D$4,1,"") | CG34: =IF(M32<='Conviction List'!$E$4,1,"") -> 1 | CH34: =IF(BG34>='Conviction List'!$F$4,1,"") | CI34: =IF(BK34>='Conviction List'!$G$4,1,"") | CJ34: =SUM(CF34:CI34) -> 1 | CK34: =MATCH($D34,INDIRECT($C$90&"!$C$1:$C$164"),0) -> 36
B35: =B34+1 -> 33 | C35: Kavveri Defence & Wireless Tech | D35: KAVDEFEN | E35: KAVDEFENCE | F35: =_xlfn.XLOOKUP(CCA_Defense!$D35,BB_Input!$C$4:$C$172,BB_Input!$G$4:$G$172) -> 30.544449 | G35: 2014 | H35: =YEAR(TODAY())-G35 -> 12 | I35: Listed | J35: RF antennas | L35: Yes | M35: 31.6 | N35: =IFERROR(_xlfn.XLOOKUP($D35,PE_Projections!$D:$D,PE_Projections!L:L),"") -> 61.262396 | O35: =IFERROR(_xlfn.XLOOKUP($D35,PE_Projections!$D:$D,PE_Projections!M:M),"") -> 41.105771 | P35: =IFERROR(_xlfn.XLOOKUP($D35,PE_Projections!$D:$D,PE_Projections!N:N),"") -> 27.581102 | Q35: =IFERROR(_xlfn.XLOOKUP($D35,PE_Projections!$D:$D,PE_Projections!O:O),"") -> 18.506335 | R35: =IFERROR(_xlfn.XLOOKUP($D35,PE_Projections!$D:$D,PE_Projections!P:P),"") -> 12.417359 | S35: 977 | T35: =IFERROR(RATE(5,,BB35,-AY35),"") | U35: 0.406 | X35: {=_xlfn.IFS($F35<Glossary!$C$54,Glossary!$B$54,$F35<Glossary!$C$55,Glossary!$B$55,$F35>Glossary!$C$56,Glossary!$B$56)} -> Small Cap | Y35: Bangalore | Z35: Private | AA35: 0.1541 | AC35: High | AD35: High | AE35: High | AF35: Started as a telco operator & pivoted into RF Antennas after issues a large order from Videotron was written off around 2014 | AU35: Tier 3 | CF35: =IF(CE35>='Conviction List'!$D$8,1,"") | CG35: =IF(M35<='Conviction List'!$E$8,1,"") -> 1 | CH35: =IF(BG35>='Conviction List'!$F$8,1,"") | CI35: =IF(BK35>='Conviction List'!$G$8,1,"") | CJ35: =SUM(CF35:CI35) -> 1 | CK35: =MATCH($D35,INDIRECT($C$90&"!$C$1:$C$164"),0) -> 79
B36: =B35+1 -> 34 | C36: Taneja Aerospace & Aviation Ltd | D36: TAA | E36: TANEJAERO | F36: =_xlfn.XLOOKUP(CCA_Defense!$D36,BB_Input!$C$4:$C$172,BB_Input!$G$4:$G$172) -> 83.637471 | G36: 2005 | H36: =YEAR(TODAY())-G36 -> 21 | I36: Listed | J36: Aerostructures | M36: 53.5 | N36: =IFERROR(_xlfn.XLOOKUP($D36,PE_Projections!$D:$D,PE_Projections!L:L),"") -> 150.81606 | O36: =IFERROR(_xlfn.XLOOKUP($D36,PE_Projections!$D:$D,PE_Projections!M:M),"") -> 140.63933 | P36: =IFERROR(_xlfn.XLOOKUP($D36,PE_Projections!$D:$D,PE_Projections!N:N),"") -> 131.1493 | Q36: =IFERROR(_xlfn.XLOOKUP($D36,PE_Projections!$D:$D,PE_Projections!O:O),"") -> 122.29964 | R36: =IFERROR(_xlfn.XLOOKUP($D36,PE_Projections!$D:$D,PE_Projections!P:P),"") -> 114.04714 | S36: 13 | T36: =IFERROR(RATE(5,,BB36,-AY36),"") -> 0.021295688 | V36: =AVERAGE(70%,80%) -> 0.75 | X36: {=_xlfn.IFS($F36<Glossary!$C$54,Glossary!$B$54,$F36<Glossary!$C$55,Glossary!$B$55,$F36>Glossary!$C$56,Glossary!$B$56)} -> Small Cap | Y36: Hosur | Z36: Private | AA36: 0.522 | AC36: High | AD36: High | AE36: High | AK36: Y | AL36: Y | AU36: Tier 1 | AV36: 17.6 | AW36: 17.6 | AX36: 17.6 | AY36: 4 | AZ36: 2.5 | BA36: 3.7 | BB36: 3.6 | BC36: 43.47 | BG36: 0.1326 | BK36: 0.1745 | BS36: 0 | BT36: 0 | BU36: 0.03 | CE36: =IFERROR(RATE(4,,BB36,-AY36),"") -> 0.026690096 | CF36: =IF(CE36>='Conviction List'!$D$6,1,"") | CG36: =IF(M36<='Conviction List'!$E$6,1,"") -> 1 | CH36: =IF(BG36>='Conviction List'!$F$6,1,"") -> 1 | CI36: =IF(BK36>='Conviction List'!$G$6,1,"") -> 1 | CJ36: =SUM(CF36:CI36) -> 3 | CK36: =MATCH($D36,INDIRECT($C$90&"!$C$1:$C$164"),0) -> 38
B37: =B36+1 -> 35 | C37: Krishna Defence & Allied Industries | D37: KRISHNDF | E37: KRISHNADEF | F37: =_xlfn.XLOOKUP(CCA_Defense!$D37,BB_Input!$C$4:$C$172,BB_Input!$G$4:$G$172) -> 130.14987 | G37: 2007 | H37: =YEAR(TODAY())-G37 -> 19 | I37: Listed | J37: Field kitchens | L37: Yes | M37: 57 | N37: =IFERROR(_xlfn.XLOOKUP($D37,PE_Projections!$D:$D,PE_Projections!L:L),"") -> 41.345254 | O37: =IFERROR(_xlfn.XLOOKUP($D37,PE_Projections!$D:$D,PE_Projections!M:M),"") -> 27.15616 | P37: =IFERROR(_xlfn.XLOOKUP($D37,PE_Projections!$D:$D,PE_Projections!N:N),"") -> 17.836558 | Q37: =IFERROR(_xlfn.XLOOKUP($D37,PE_Projections!$D:$D,PE_Projections!O:O),"") -> 11.715309 | R37: =IFERROR(_xlfn.XLOOKUP($D37,PE_Projections!$D:$D,PE_Projections!P:P),"") -> 7.6947844 | S37: 84 | T37: =IFERROR(RATE(5,,BB37,-AY37),"") -> 0.3160171 | U37: =(40%+50%)/2 -> 0.45 | V37: 0.95 | W37: 1.1 | X37: {=_xlfn.IFS($F37<Glossary!$C$54,Glossary!$B$54,$F37<Glossary!$C$55,Glossary!$B$55,$F37>Glossary!$C$56,Glossary!$B$56)} -> Small Cap | Y37: Vadodara | Z37: Family | AA37: 0.73 | AC37: High | AD37: High | AE37: High | AF37: Operates in a Duopoly market, manufactures "life critical" niche products for Defense | AG37: Jay Chhalera family | AL37: Y | AQ37: Y | AU37: Diversified | AV37: 100.3 | AW37: 100.3 | AX37: 100.3 | AY37: 22.5 | AZ37: 12.2 | BA37: 7.2 | BB37: 5.7 | BC37: 37.59 | BG37: 0.1846 | BK37: 0.238 | CF37: =IF(CE37>='Conviction List'!$D$8,1,"") | CG37: =IF(M37<='Conviction List'!$E$8,1,"") -> 1 | CH37: =IF(BG37>='Conviction List'!$F$8,1,"") -> 1 | CI37: =IF(BK37>='Conviction List'!$G$8,1,"") | CJ37: =SUM(CF37:CI37) -> 2 | CK37: =MATCH($D37,INDIRECT($C$90&"!$C$1:$C$164"),0) -> 52
B38: =B37+1 -> 36 | C38: HBL Power Systems Ltd | D38: HBLENGINE | E38: HBLENGINE | F38: =_xlfn.XLOOKUP(CCA_Defense!$D38,BB_Input!$C$4:$C$172,BB_Input!$G$4:$G$172) -> 2722.5174 | G38: 1977 | H38: =YEAR(TODAY())-G38 -> 49 | I38: Listed | J38: Batteries | M38: 43 | N38: =IFERROR(_xlfn.XLOOKUP($D38,PE_Projections!$D:$D,PE_Projections!L:L),"") -> 39.533631 | O38: =IFERROR(_xlfn.XLOOKUP($D38,PE_Projections!$D:$D,PE_Projections!M:M),"") -> 31.151943 | P38: =IFERROR(_xlfn.XLOOKUP($D38,PE_Projections!$D:$D,PE_Projections!N:N),"") -> 28.716612 | Q38: =IFERROR(_xlfn.XLOOKUP($D38,PE_Projections!$D:$D,PE_Projections!O:O),"") | R38: =IFERROR(_xlfn.XLOOKUP($D38,PE_Projections!$D:$D,PE_Projections!P:P),"") | S38: 4 | T38: =IFERROR(RATE(5,,BB38,-AY38),"") -> 0.11304961 | V38: 0.2 | W38: 1.8 | X38: {=_xlfn.IFS($F38<Glossary!$C$54,Glossary!$B$54,$F38<Glossary!$C$55,Glossary!$B$55,$F38>Glossary!$C$56,Glossary!$B$56)} -> Mid Cap | Y38: Hyderabad | Z38: Family | AA38: 0.591 | AC38: High | AD38: High | AE38: High | AP38: Y | AU38: Tier 3 | AV38: 277.3 | AW38: 277.3 | AX38: 277.3 | AY38: 24.6 | AZ38: 26.1 | BA38: 16.1 | BB38: 14.4 | BD38: 30.22 | BE38: 15.16 | BF38: 10.38 | BH38: 0.231 | BI38: 0.102 | BJ38: 0.108 | BL38: 0.295 | BM38: 0.1339 | BN38: 0.1408 | BS38: 0.05 | BT38: 0.09 | BU38: 0.07 | CE38: =IFERROR(RATE(4,,BB38,-AY38),"") -> 0.14325512 | CF38: =IF(CE38>='Conviction List'!$D$8,1,"") | CG38: =IF(M38<='Conviction List'!$E$8,1,"") -> 1 | CH38: =IF(BG38>='Conviction List'!$F$8,1,"") | CI38: =IF(BK38>='Conviction List'!$G$8,1,"") | CJ38: =SUM(CF38:CI38) -> 1 | CK38: =MATCH($D38,INDIRECT($C$90&"!$C$1:$C$164"),0) -> 40
B39: =B38+1 -> 37 | C39: Tata Advanced Systems | D39: 4624679Z | F39: =_xlfn.XLOOKUP(CCA_Defense!$D39,BB_Input!$C$4:$C$172,BB_Input!$G$4:$G$172) -> #N/A | G39: 2007 | H39: =YEAR(TODAY())-G39 -> 19 | I39: Unlisted | J39: Aerostructures | N39: =IFERROR(_xlfn.XLOOKUP($D39,PE_Projections!$D:$D,PE_Projections!L:L),"") | O39: =IFERROR(_xlfn.XLOOKUP($D39,PE_Projections!$D:$D,PE_Projections!M:M),"") | P39: =IFERROR(_xlfn.XLOOKUP($D39,PE_Projections!$D:$D,PE_Projections!N:N),"") | Q39: =IFERROR(_xlfn.XLOOKUP($D39,PE_Projections!$D:$D,PE_Projections!O:O),"") | R39: =IFERROR(_xlfn.XLOOKUP($D39,PE_Projections!$D:$D,PE_Projections!P:P),"") | T39: =IFERROR(RATE(5,,BB39,-AY39),"") | W39: 5.5 | Y39: Hyderabad | Z39: Family | AA39: 0.66 | AC39: High | AD39: High | AE39: High | AG39: Owned by Tata Sons | AH39: Y | AI39: Y | AL39: Y | AM39: Y | AQ39: Y | AR39: Y | AU39: Diversified | CF39: =IF(CE39>='Conviction List'!$D$8,1,"") | CG39: =IF(M39<='Conviction List'!$E$8,1,"") -> 1 | CH39: =IF(BG39>='Conviction List'!$F$8,1,"") | CI39: =IF(BK39>='Conviction List'!$G$8,1,"") | CJ39: =SUM(CF39:CI39) -> 1 | CK39: =MATCH($D39,INDIRECT($C$90&"!$C$1:$C$164"),0) -> 41
B40: =B39+1 -> 38 | C40: Reliance Defence | D40: 1254332D | F40: =_xlfn.XLOOKUP(CCA_Defense!$D40,BB_Input!$C$4:$C$172,BB_Input!$G$4:$G$172) -> #N/A | G40: 2015 | H40: =YEAR(TODAY())-G40 -> 11 | I40: Unlisted | J40: Shipbuilding | N40: =IFERROR(_xlfn.XLOOKUP($D40,PE_Projections!$D:$D,PE_Projections!L:L),"") | O40: =IFERROR(_xlfn.XLOOKUP($D40,PE_Projections!$D:$D,PE_Projections!M:M),"") | P40: =IFERROR(_xlfn.XLOOKUP($D40,PE_Projections!$D:$D,PE_Projections!N:N),"") | Q40: =IFERROR(_xlfn.XLOOKUP($D40,PE_Projections!$D:$D,PE_Projections!O:O),"") | R40: =IFERROR(_xlfn.XLOOKUP($D40,PE_Projections!$D:$D,PE_Projections!P:P),"") | T40: =IFERROR(RATE(5,,BB40,-AY40),"") | Y40: Mumbai | Z40: Family | AC40: High | AD40: High | AE40: High | AG40: Owned by Anil Ambani & does not have any relation to Reliance Digital / Retail | AN40: Y | AU40: Tier 2 | CF40: =IF(CE40>='Conviction List'!$D$8,1,"") | CG40: =IF(M40<='Conviction List'!$E$8,1,"") -> 1 | CH40: =IF(BG40>='Conviction List'!$F$8,1,"") | CI40: =IF(BK40>='Conviction List'!$G$8,1,"") | CJ40: =SUM(CF40:CI40) -> 1 | CK40: =MATCH($D40,INDIRECT($C$90&"!$C$1:$C$164"),0) -> 42
B41: =B40+1 -> 39 | C41: Aimtron Electronics | D41: AIMTRON | E41: AIMTRON | F41: =_xlfn.XLOOKUP(CCA_Defense!$D41,BB_Input!$C$4:$C$172,BB_Input!$G$4:$G$172) -> 186.68179 | G41: 2015 | H41: =YEAR(TODAY())-G41 -> 11 | I41: Listed | J41: EMS | M41: 50.25 | N41: =IFERROR(_xlfn.XLOOKUP($D41,PE_Projections!$D:$D,PE_Projections!L:L),"") | O41: =IFERROR(_xlfn.XLOOKUP($D41,PE_Projections!$D:$D,PE_Projections!M:M),"") | P41: =IFERROR(_xlfn.XLOOKUP($D41,PE_Projections!$D:$D,PE_Projections!N:N),"") | Q41: =IFERROR(_xlfn.XLOOKUP($D41,PE_Projections!$D:$D,PE_Projections!O:O),"") | R41: =IFERROR(_xlfn.XLOOKUP($D41,PE_Projections!$D:$D,PE_Projections!P:P),"") | S41: 71 | T41: =IFERROR(RATE(5,,BB41,-AY41),"") -> 0.43413497 | V41: =AVERAGE(5%,10%) -> 0.075 | W41: 2.8 | X41: {=_xlfn.IFS($F41<Glossary!$C$54,Glossary!$B$54,$F41<Glossary!$C$55,Glossary!$B$55,$F41>Glossary!$C$56,Glossary!$B$56)} -> Small Cap | Y41: Vadodara | Z41: Family | AA41: 0.714 | AC41: Medium | AD41: High | AE41: High | AG41: Mukesh & Nirmal Vasani | AQ41: Y | AR41: Y | AT41: Y | AU41: Diversified | AY41: 18.2 | AZ41: 10.7 | BA41: 9.7 | BB41: 3 | BC41: 35.6 | BG41: 0.248 | BK41: 0.2916 | CF41: =IF(CE41>='Conviction List'!$D$8,1,"") | CG41: =IF(M41<='Conviction List'!$E$8,1,"") -> 1 | CH41: =IF(BG41>='Conviction List'!$F$8,1,"") -> 1 | CI41: =IF(BK41>='Conviction List'!$G$8,1,"") -> 1 | CJ41: =SUM(CF41:CI41) -> 3 | CK41: =MATCH($D41,INDIRECT($C$90&"!$C$1:$C$164"),0) -> 43
B42: =B41+1 -> 40 | C42: Ashok Leyland | D42: AL | E42: ASHOKLEY | F42: =_xlfn.XLOOKUP(CCA_Defense!$D42,BB_Input!$C$4:$C$172,BB_Input!$G$4:$G$172) -> 11472.119 | G42: 1948 | H42: =YEAR(TODAY())-G42 -> 78 | I42: Acquired by/Part of Listed Company | J42: Defence trucks | M42: 23.8 | N42: =IFERROR(_xlfn.XLOOKUP($D42,PE_Projections!$D:$D,PE_Projections!L:L),"") -> 35.802943 | O42: =IFERROR(_xlfn.XLOOKUP($D42,PE_Projections!$D:$D,PE_Projections!M:M),"") -> 31.385383 | P42: =IFERROR(_xlfn.XLOOKUP($D42,PE_Projections!$D:$D,PE_Projections!N:N),"") -> 28.046469 | Q42: =IFERROR(_xlfn.XLOOKUP($D42,PE_Projections!$D:$D,PE_Projections!O:O),"") -> 26.82103 | R42: =IFERROR(_xlfn.XLOOKUP($D42,PE_Projections!$D:$D,PE_Projections!P:P),"") -> 26.146572 | S42: 6 | T42: =IFERROR(RATE(5,,BB42,-AY42),"") -> 0.081747729 | V42: =AVERAGE(2%,2,5%) -> 0.69 | X42: {=_xlfn.IFS($F42<Glossary!$C$54,Glossary!$B$54,$F42<Glossary!$C$55,Glossary!$B$55,$F42>Glossary!$C$56,Glossary!$B$56)} -> Large Cap | Y42: Chennai | Z42: Family | AA42: 0.515 | AC42: High | AD42: High | AE42: High | AG42: Owned by Hinduja Group | AI42: Y | AU42: Platforms | AV42: 2935.4 | AW42: 2935.4 | AX42: 2935.4 | AY42: 1699 | AZ42: 1565 | BA42: 1526 | BB42: 1147 | BC42: 12.08 | BG42: 0.2918 | BK42: 0.1437 | CF42: =IF(CE42>='Conviction List'!$D$8,1,"") | CG42: =IF(M42<='Conviction List'!$E$8,1,"") -> 1 | CH42: =IF(BG42>='Conviction List'!$F$8,1,"") -> 1 | CI42: =IF(BK42>='Conviction List'!$G$8,1,"") | CJ42: =SUM(CF42:CI42) -> 2 | CK42: =MATCH($D42,INDIRECT($C$90&"!$C$1:$C$164"),0) -> 44
B43: =B42+1 -> 41 | C43: CFF Fluid Control | D43: CFF | E43: CFF | F43: =_xlfn.XLOOKUP(CCA_Defense!$D43,BB_Input!$C$4:$C$172,BB_Input!$G$4:$G$172) -> 127.45359 | G43: 1964 | H43: =YEAR(TODAY())-G43 -> 62 | I43: Listed | J43: Naval valves | M43: 48 | N43: =IFERROR(_xlfn.XLOOKUP($D43,PE_Projections!$D:$D,PE_Projections!L:L),"") -> 40.805416 | O43: =IFERROR(_xlfn.XLOOKUP($D43,PE_Projections!$D:$D,PE_Projections!M:M),"") -> 31.81151 | P43: =IFERROR(_xlfn.XLOOKUP($D43,PE_Projections!$D:$D,PE_Projections!N:N),"") -> 25.599945 | Q43: =IFERROR(_xlfn.XLOOKUP($D43,PE_Projections!$D:$D,PE_Projections!O:O),"") -> 20.60126 | R43: =IFERROR(_xlfn.XLOOKUP($D43,PE_Projections!$D:$D,PE_Projections!P:P),"") -> 16.578626 | S43: 36 | T43: =IFERROR(RATE(5,,BB43,-AY43),"") -> 0.24263976 | V43: 1 | W43: 4.1 | X43: {=_xlfn.IFS($F43<Glossary!$C$54,Glossary!$B$54,$F43<Glossary!$C$55,Glossary!$B$55,$F43>Glossary!$C$56,Glossary!$B$56)} -> Small Cap | Y43: Mumbai | Z43: Private | AA43: 0.729 | AC43: High | AD43: High | AE43: High | AL43: Y | AU43: Tier 1 | AV43: 10.6 | AW43: 10.6 | AX43: 10.6 | AY43: 16 | AZ43: 12.3 | BA43: 8.2 | BB43: 5.4 | BC43: 30.38 | BG43: 0.1742 | BK43: 0.2213 | CF43: =IF(CE43>='Conviction List'!$D$8,1,"") | CG43: =IF(M43<='Conviction List'!$E$8,1,"") -> 1 | CH43: =IF(BG43>='Conviction List'!$F$8,1,"") -> 1 | CI43: =IF(BK43>='Conviction List'!$G$8,1,"") | CJ43: =SUM(CF43:CI43) -> 2 | CK43: =MATCH($D43,INDIRECT($C$90&"!$C$1:$C$164"),0) -> 45
B44: =B43+1 -> 42 | C44: DEE Development Engineers | D44: DEEDEV | E44: DEEDEV | F44: =_xlfn.XLOOKUP(CCA_Defense!$D44,BB_Input!$C$4:$C$172,BB_Input!$G$4:$G$172) -> 169.74634 | G44: 2008 | H44: =YEAR(TODAY())-G44 -> 18 | I44: Listed | J44: Piping fabrication | M44: 48 | N44: =IFERROR(_xlfn.XLOOKUP($D44,PE_Projections!$D:$D,PE_Projections!L:L),"") -> 27.308231 | O44: =IFERROR(_xlfn.XLOOKUP($D44,PE_Projections!$D:$D,PE_Projections!M:M),"") -> 22.42773 | P44: =IFERROR(_xlfn.XLOOKUP($D44,PE_Projections!$D:$D,PE_Projections!N:N),"") -> 18.529108 | Q44: =IFERROR(_xlfn.XLOOKUP($D44,PE_Projections!$D:$D,PE_Projections!O:O),"") -> 16.485737 | R44: =IFERROR(_xlfn.XLOOKUP($D44,PE_Projections!$D:$D,PE_Projections!P:P),"") -> 14.667707 | S44: 5 | T44: =IFERROR(RATE(5,,BB44,-AY44),"") -> 0.12394779 | V44: 0.08 | W44: 1.4 | X44: {=_xlfn.IFS($F44<Glossary!$C$54,Glossary!$B$54,$F44<Glossary!$C$55,Glossary!$B$55,$F44>Glossary!$C$56,Glossary!$B$56)} -> Small Cap | Y44: Faridabad | Z44: Family | AA44: 0.72 | AC44: High | AD44: High | AE44: Medium | AG44: Owned by Jagjeet Singh Bindra family | AL44: Y | AU44: Tier 1 | AV44: 129.9 | AW44: 129.9 | AX44: 129.9 | AY44: 95.6 | AZ44: 91.2 | BA44: 69.9 | BB44: 53.3 | BC44: 17.61 | BG44: 0.0697 | BK44: 0.0889 | CF44: =IF(CE44>='Conviction List'!$D$8,1,"") | CG44: =IF(M44<='Conviction List'!$E$8,1,"") -> 1 | CH44: =IF(BG44>='Conviction List'!$F$8,1,"") | CI44: =IF(BK44>='Conviction List'!$G$8,1,"") | CJ44: =SUM(CF44:CI44) -> 1 | CK44: =MATCH($D44,INDIRECT($C$90&"!$C$1:$C$164"),0) -> 46
B45: =B44+1 -> 43 | C45: Droneacharya Aerial Innovations | D45: DRONACHR | E45: DRONACHRYA | F45: =_xlfn.XLOOKUP(CCA_Defense!$D45,BB_Input!$C$4:$C$172,BB_Input!$G$4:$G$172) -> 12.771906 | G45: 2019 | H45: =YEAR(TODAY())-G45 -> 7 | I45: Listed | J45: Drone services | M45: 41 | N45: =IFERROR(_xlfn.XLOOKUP($D45,PE_Projections!$D:$D,PE_Projections!L:L),"") | O45: =IFERROR(_xlfn.XLOOKUP($D45,PE_Projections!$D:$D,PE_Projections!M:M),"") | P45: =IFERROR(_xlfn.XLOOKUP($D45,PE_Projections!$D:$D,PE_Projections!N:N),"") | Q45: =IFERROR(_xlfn.XLOOKUP($D45,PE_Projections!$D:$D,PE_Projections!O:O),"") | R45: =IFERROR(_xlfn.XLOOKUP($D45,PE_Projections!$D:$D,PE_Projections!P:P),"") | S45: 39 | T45: =IFERROR(RATE(5,,BB45,-AY45),"") -> 0.8478498 | V45: =AVERAGE(10%,15%) -> 0.125 | X45: {=_xlfn.IFS($F45<Glossary!$C$54,Glossary!$B$54,$F45<Glossary!$C$55,Glossary!$B$55,$F45>Glossary!$C$56,Glossary!$B$56)} -> Small Cap | Y45: Pune | Z45: Private | AA45: 0.63 | AC45: Low | AD45: Medium | AE45: Medium | AG45: Prateek Srivastava is the Founder & majority shareholder | AH45: Y | AU45: Platforms | AV45: 4.1 | AW45: 4.1 | AX45: 4.1 | AY45: =(1+RATE(3,,BB45,-AZ45,0))*AZ45 -> 8.6177388 | AZ45: 4 | BA45: 2.1 | BB45: 0.4 | BC45: 19.37 | BG45: 0.0862 | BK45: 0.118 | CF45: =IF(CE45>='Conviction List'!$D$8,1,"") | CG45: =IF(M45<='Conviction List'!$E$8,1,"") -> 1 | CH45: =IF(BG45>='Conviction List'!$F$8,1,"") | CI45: =IF(BK45>='Conviction List'!$G$8,1,"") | CJ45: =SUM(CF45:CI45) -> 1 | CK45: =MATCH($D45,INDIRECT($C$90&"!$C$1:$C$164"),0) -> 47
B46: =B45+1 -> 44 | C46: MTAR Technologies Ltd | D46: MTARTECH | E46: MTARTECH | F46: =_xlfn.XLOOKUP(CCA_Defense!$D46,BB_Input!$C$4:$C$172,BB_Input!$G$4:$G$172) -> 839.81666 | G46: 1999 | H46: =YEAR(TODAY())-G46 -> 27 | I46: Listed | J46: Precision machining | L46: Yes | M46: 89 | N46: =IFERROR(_xlfn.XLOOKUP($D46,PE_Projections!$D:$D,PE_Projections!L:L),"") -> 302.44683 | O46: =IFERROR(_xlfn.XLOOKUP($D46,PE_Projections!$D:$D,PE_Projections!M:M),"") -> 234.91016 | P46: =IFERROR(_xlfn.XLOOKUP($D46,PE_Projections!$D:$D,PE_Projections!N:N),"") -> 182.45449 | Q46: =IFERROR(_xlfn.XLOOKUP($D46,PE_Projections!$D:$D,PE_Projections!O:O),"") -> 141.71223 | R46: =IFERROR(_xlfn.XLOOKUP($D46,PE_Projections!$D:$D,PE_Projections!P:P),"") -> 110.06775 | T46: =IFERROR(RATE(5,,BB46,-AY46),"") -> 0.34490168 | U46: 0.25 | V46: =AVERAGE(60%,70%) -> 0.65 | W46: 2.8 | X46: {=_xlfn.IFS($F46<Glossary!$C$54,Glossary!$B$54,$F46<Glossary!$C$55,Glossary!$B$55,$F46>Glossary!$C$56,Glossary!$B$56)} -> Small Cap | Y46: Hyderabad | Z46: Private | AA46: 0.3177 | AC46: High | AD46: High | AE46: High | AQ46: Y | AT46: Y | AU46: Diversified | AV46: 31 | AW46: 31 | AX46: 31 | AY46: 110 | AZ46: 67 | BA46: 69 | BB46: 25 | BC46: 39.8 | BD46: 44.8 | BG46: 0.076 | BH46: 0.087 | BI46: 0.126 | BJ46: 0.094 | BK46: 0.1066 | BL46: 0.123 | BM46: 0.496 | BS46: 0.28 | BT46: 0.23 | BU46: 0.18 | CE46: =IFERROR(RATE(4,,BB46,-AY46),"") -> 0.44831547 | CF46: =IF(CE46>='Conviction List'!$D$4,1,"") -> 1 | CG46: =IF(M44<='Conviction List'!$E$4,1,"") -> 1 | CH46: =IF(BG46>='Conviction List'!$F$4,1,"") | CI46: =IF(BK46>='Conviction List'!$G$4,1,"") | CJ46: =SUM(CF46:CI46) -> 2 | CK46: =MATCH($D46,INDIRECT($C$90&"!$C$1:$C$164"),0) -> 25
B47: =B46+1 -> 45 | C47: Godrej Aerospace | D47: 1436Z | F47: =_xlfn.XLOOKUP(CCA_Defense!$D47,BB_Input!$C$4:$C$172,BB_Input!$G$4:$G$172) -> #N/A | G47: 1985 | H47: =YEAR(TODAY())-G47 -> 41 | I47: Unlisted | J47: Aero-engine parts | N47: =IFERROR(_xlfn.XLOOKUP($D47,PE_Projections!$D:$D,PE_Projections!L:L),"") | O47: =IFERROR(_xlfn.XLOOKUP($D47,PE_Projections!$D:$D,PE_Projections!M:M),"") | P47: =IFERROR(_xlfn.XLOOKUP($D47,PE_Projections!$D:$D,PE_Projections!N:N),"") | Q47: =IFERROR(_xlfn.XLOOKUP($D47,PE_Projections!$D:$D,PE_Projections!O:O),"") | R47: =IFERROR(_xlfn.XLOOKUP($D47,PE_Projections!$D:$D,PE_Projections!P:P),"") | T47: =IFERROR(RATE(5,,BB47,-AY47),"") | Y47: Mumbai | Z47: Family | AC47: High | AD47: High | AE47: High | AG47: Godrej Family | AL47: Y | AP47: Y | AQ47: Y | AU47: Diversified | AV47: 1440 | AW47: 1440 | AX47: 1440 | CF47: =IF(CE47>='Conviction List'!$D$8,1,"") | CG47: =IF(M47<='Conviction List'!$E$8,1,"") -> 1 | CH47: =IF(BG47>='Conviction List'!$F$8,1,"") | CI47: =IF(BK47>='Conviction List'!$G$8,1,"") | CJ47: =SUM(CF47:CI47) -> 1 | CK47: =MATCH($D47,INDIRECT($C$90&"!$C$1:$C$164"),0) -> 49
B48: =B47+1 -> 46 | C48: HFCL | D48: HMFC | E48: HFCL | F48: =_xlfn.XLOOKUP(CCA_Defense!$D48,BB_Input!$C$4:$C$172,BB_Input!$G$4:$G$172) -> 1032.4931 | G48: 1987 | H48: =YEAR(TODAY())-G48 -> 39 | I48: Listed | J48: Optical fiber | M48: 70 | N48: =IFERROR(_xlfn.XLOOKUP($D48,PE_Projections!$D:$D,PE_Projections!L:L),"") | O48: =IFERROR(_xlfn.XLOOKUP($D48,PE_Projections!$D:$D,PE_Projections!M:M),"") | P48: =IFERROR(_xlfn.XLOOKUP($D48,PE_Projections!$D:$D,PE_Projections!N:N),"") | Q48: =IFERROR(_xlfn.XLOOKUP($D48,PE_Projections!$D:$D,PE_Projections!O:O),"") | R48: =IFERROR(_xlfn.XLOOKUP($D48,PE_Projections!$D:$D,PE_Projections!P:P),"") | S48: -9 | T48: =IFERROR(RATE(5,,BB48,-AY48),"") -> -0.029945711 | V48: =AVERAGE(5%,7%) -> 0.06 | W48: 2.3 | X48: {=_xlfn.IFS($F48<Glossary!$C$54,Glossary!$B$54,$F48<Glossary!$C$55,Glossary!$B$55,$F48>Glossary!$C$56,Glossary!$B$56)} -> Small Cap | Y48: Gurugram | Z48: Family | AA48: 0.4 | AC48: Medium | AD48: Medium | AE48: Medium | AG48: Mahendra Nahata family | AQ48: Y | AU48: Tier 3 | AV48: 1.1 | AW48: 1.1 | AX48: 1.1 | AY48: 469 | AZ48: 516 | BA48: 548 | BB48: 546 | BC48: 25.69 | BG48: 0.043 | BK48: 0.2922 | CF48: =IF(CE48>='Conviction List'!$D$8,1,"") | CG48: =IF(M48<='Conviction List'!$E$8,1,"") -> 1 | CH48: =IF(BG48>='Conviction List'!$F$8,1,"") | CI48: =IF(BK48>='Conviction List'!$G$8,1,"") -> 1 | CJ48: =SUM(CF48:CI48) -> 2 | CK48: =MATCH($D48,INDIRECT($C$90&"!$C$1:$C$164"),0) -> 50
B49: =B48+1 -> 47 | C49: High Energy Batteries (India) | D49: HIGH | E49: HIGHEEBAT | F49: =_xlfn.XLOOKUP(CCA_Defense!$D49,BB_Input!$C$4:$C$172,BB_Input!$G$4:$G$172) -> 54.330874 | G49: 2011 | H49: =YEAR(TODAY())-G49 -> 15 | I49: Listed | J49: Thermal batteries | M49: 45 | N49: =IFERROR(_xlfn.XLOOKUP($D49,PE_Projections!$D:$D,PE_Projections!L:L),"") -> 33.478578 | O49: =IFERROR(_xlfn.XLOOKUP($D49,PE_Projections!$D:$D,PE_Projections!M:M),"") -> 33.40627 | P49: =IFERROR(_xlfn.XLOOKUP($D49,PE_Projections!$D:$D,PE_Projections!N:N),"") -> 34.286521 | Q49: =IFERROR(_xlfn.XLOOKUP($D49,PE_Projections!$D:$D,PE_Projections!O:O),"") -> 35.218716 | R49: =IFERROR(_xlfn.XLOOKUP($D49,PE_Projections!$D:$D,PE_Projections!P:P),"") -> 35.142649 | S49: 4 | T49: =IFERROR(RATE(5,,BB49,-AY49),"") -> 0.0021645224 | V49: =AVERAGE(70%,75%) -> 0.725 | X49: {=_xlfn.IFS($F49<Glossary!$C$54,Glossary!$B$54,$F49<Glossary!$C$55,Glossary!$B$55,$F49>Glossary!$C$56,Glossary!$B$56)} -> Small Cap | Y49: Mathur | Z49: Family | AA49: 0.34 | AB49: PONNIERODE, 5.6% | AC49: High | AD49: High | AE49: High | AP49: Y | AU49: Tier 3 | AV49: 1 | AW49: 1 | AX49: 1 | AY49: 9.3 | AZ49: 9 | BA49: 10.7 | BB49: 9.2 | BC49: 29.07 | BG49: 0.173 | BK49: 0.229 | CF49: =IF(CE49>='Conviction List'!$D$8,1,"") | CG49: =IF(M49<='Conviction List'!$E$8,1,"") -> 1 | CH49: =IF(BG49>='Conviction List'!$F$8,1,"") -> 1 | CI49: =IF(BK49>='Conviction List'!$G$8,1,"") | CJ49: =SUM(CF49:CI49) -> 2 | CK49: =MATCH($D49,INDIRECT($C$90&"!$C$1:$C$164"),0) -> 51
B50: =B49+1 -> 48 | C50: Premier Explosives Ltd | D50: PRE | E50: PREMEXPLN | F50: =_xlfn.XLOOKUP(CCA_Defense!$D50,BB_Input!$C$4:$C$172,BB_Input!$G$4:$G$172) -> 308.39378 | G50: 1980 | H50: =YEAR(TODAY())-G50 -> 46 | I50: Listed | J50: Propellants | L50: Yes | M50: 77 | N50: =IFERROR(_xlfn.XLOOKUP($D50,PE_Projections!$D:$D,PE_Projections!L:L),"") -> 43.697925 | O50: =IFERROR(_xlfn.XLOOKUP($D50,PE_Projections!$D:$D,PE_Projections!M:M),"") -> 36.502349 | P50: =IFERROR(_xlfn.XLOOKUP($D50,PE_Projections!$D:$D,PE_Projections!N:N),"") -> 30.491642 | Q50: =IFERROR(_xlfn.XLOOKUP($D50,PE_Projections!$D:$D,PE_Projections!O:O),"") -> 25.470696 | R50: =IFERROR(_xlfn.XLOOKUP($D50,PE_Projections!$D:$D,PE_Projections!P:P),"") -> 21.276531 | S50: 81 | T50: =IFERROR(RATE(5,,BB50,-AY50),"") -> 0.16894796 | U50: 0.1912 | V50: 0.84 | W50: 2.8 | X50: {=_xlfn.IFS($F50<Glossary!$C$54,Glossary!$B$54,$F50<Glossary!$C$55,Glossary!$B$55,$F50>Glossary!$C$56,Glossary!$B$56)} -> Small Cap | Y50: Secunderabad | Z50: Family | AA50: 0.4133 | AC50: High | AD50: High | AE50: High | AN50: Y | AU50: Tier 2 | AV50: 10.4 | AW50: 10.4 | AX50: 10.4 | AY50: 5.02 | AZ50: 3.1 | BA50: 2.3 | BB50: 2.3 | BC50: 50.8 | BD50: 26.6 | BE50: 18.6 | BF50: 17.2 | BG50: 0.12255 | BH50: 0.128 | BI50: 0.035 | BJ50: 0.028 | BK50: 0.1688 | BS50: 0.06 | BT50: 0.01 | BU50: 0.4 | CE50: =IFERROR(RATE(4,,BB50,-AY50),"") -> 0.21546923 | CF50: =IF(CE50>='Conviction List'!$D$7,1,"") | CG50: =IF(M50<='Conviction List'!$E$7,1,"") -> 1 | CH50: =IF(BG50>='Conviction List'!$F$7,1,"") -> 1 | CI50: =IF(BK50>='Conviction List'!$G$7,1,"") -> 1 | CJ50: =SUM(CF50:CI50) -> 3 | CK50: =MATCH($D50,INDIRECT($C$90&"!$C$1:$C$164"),0) -> 39
B51: =B50+1 -> 49 | C51: Marine Electricals (India) | D51: MARINE | E51: MARINE | F51: =_xlfn.XLOOKUP(CCA_Defense!$D51,BB_Input!$C$4:$C$172,BB_Input!$G$4:$G$172) -> 324.63404 | G51: 1978 | H51: =YEAR(TODAY())-G51 -> 48 | I51: Listed | J51: Marine electricals | M51: 73 | N51: =IFERROR(_xlfn.XLOOKUP($D51,PE_Projections!$D:$D,PE_Projections!L:L),"") | O51: =IFERROR(_xlfn.XLOOKUP($D51,PE_Projections!$D:$D,PE_Projections!M:M),"") | P51: =IFERROR(_xlfn.XLOOKUP($D51,PE_Projections!$D:$D,PE_Projections!N:N),"") | Q51: =IFERROR(_xlfn.XLOOKUP($D51,PE_Projections!$D:$D,PE_Projections!O:O),"") | R51: =IFERROR(_xlfn.XLOOKUP($D51,PE_Projections!$D:$D,PE_Projections!P:P),"") | S51: 23 | T51: =IFERROR(RATE(5,,BB51,-AY51),"") -> 0.15342351 | V51: =AVERAGE(35%,40%) -> 0.375 | W51: 1.19 | X51: {=_xlfn.IFS($F51<Glossary!$C$54,Glossary!$B$54,$F51<Glossary!$C$55,Glossary!$B$55,$F51>Glossary!$C$56,Glossary!$B$56)} -> Small Cap | Y51: Mumbai | Z51: Family | AA51: 0.66 | AC51: High | AD51: High | AE51: High | AG51: Pritam Chheda & family | AP51: Y | AU51: Tier 3 | AV51: 15.7 | AW51: 15.7 | AX51: 15.7 | AY51: 88.6 | AZ51: 71.9 | BA51: 51.2 | BB51: 43.4 | BC51: 34.38 | BG51: 0.1165 | BK51: 0.163 | CF51: =IF(CE51>='Conviction List'!$D$8,1,"") | CG51: =IF(M51<='Conviction List'!$E$8,1,"") -> 1 | CH51: =IF(BG51>='Conviction List'!$F$8,1,"") | CI51: =IF(BK51>='Conviction List'!$G$8,1,"") | CJ51: =SUM(CF51:CI51) -> 1 | CK51: =MATCH($D51,INDIRECT($C$90&"!$C$1:$C$164"),0) -> 53
B52: =B51+1 -> 50 | C52: Lokesh Machines | D52: LOKM | E52: LOKESHMACH | F52: =_xlfn.XLOOKUP(CCA_Defense!$D52,BB_Input!$C$4:$C$172,BB_Input!$G$4:$G$172) -> 36.711698 | G52: 1991 | H52: =YEAR(TODAY())-G52 -> 35 | I52: Listed | J52: CNC machines | M52: 518 | N52: =IFERROR(_xlfn.XLOOKUP($D52,PE_Projections!$D:$D,PE_Projections!L:L),"") -> 140.75056 | O52: =IFERROR(_xlfn.XLOOKUP($D52,PE_Projections!$D:$D,PE_Projections!M:M),"") -> 138.65048 | P52: =IFERROR(_xlfn.XLOOKUP($D52,PE_Projections!$D:$D,PE_Projections!N:N),"") -> 136.58174 | Q52: =IFERROR(_xlfn.XLOOKUP($D52,PE_Projections!$D:$D,PE_Projections!O:O),"") -> 134.54386 | R52: =IFERROR(_xlfn.XLOOKUP($D52,PE_Projections!$D:$D,PE_Projections!P:P),"") -> 132.53639 | S52: -22 | T52: =IFERROR(RATE(5,,BB52,-AY52),"") -> 0.025400566 | V52: =AVERAGE(5%,8%) -> 0.065 | W52: 0.4 | X52: {=_xlfn.IFS($F52<Glossary!$C$54,Glossary!$B$54,$F52<Glossary!$C$55,Glossary!$B$55,$F52>Glossary!$C$56,Glossary!$B$56)} -> Small Cap | Y52: Hyderabad | Z52: Family | AA52: 0.55 | AC52: High | AD52: Medium | AE52: Medium | AG52: Lokesh Vutukuri & family | AT52: Y | AU52: Tier 4 | AV52: 15.7 | AW52: 15.7 | AX52: 15.7 | AY52: 26.3 | AZ52: 33.8 | BA52: 27.6 | BB52: 23.2 | BC52: 17.8 | BG52: 0.0026 | BK52: 0.048 | CF52: =IF(CE52>='Conviction List'!$D$8,1,"") | CG52: =IF(M52<='Conviction List'!$E$8,1,"") | CH52: =IF(BG52>='Conviction List'!$F$8,1,"") | CI52: =IF(BK52>='Conviction List'!$G$8,1,"") | CJ52: =SUM(CF52:CI52) -> 0 | CK52: =MATCH($D52,INDIRECT($C$90&"!$C$1:$C$164"),0) -> 54
B53: =B52+1 -> 51 | C53: Swan Energy | D53: SWANCORP | E53: SWANENERGY | F53: =_xlfn.XLOOKUP(CCA_Defense!$D53,BB_Input!$C$4:$C$172,BB_Input!$G$4:$G$172) -> 1616.1622 | G53: 1909 | H53: =YEAR(TODAY())-G53 -> 117 | I53: Listed | J53: Shipbuilding | M53: 17.8 | N53: =IFERROR(_xlfn.XLOOKUP($D53,PE_Projections!$D:$D,PE_Projections!L:L),"") -> 15.83296 | O53: =IFERROR(_xlfn.XLOOKUP($D53,PE_Projections!$D:$D,PE_Projections!M:M),"") -> 13.454308 | P53: =IFERROR(_xlfn.XLOOKUP($D53,PE_Projections!$D:$D,PE_Projections!N:N),"") -> 10.732277 | Q53: =IFERROR(_xlfn.XLOOKUP($D53,PE_Projections!$D:$D,PE_Projections!O:O),"") -> 9.1199217 | R53: =IFERROR(_xlfn.XLOOKUP($D53,PE_Projections!$D:$D,PE_Projections!P:P),"") -> 7.5076161 | S53: -2 | T53: =IFERROR(RATE(5,,BB53,-AY53),"") -> 0.58931627 | V53: 0.05 | X53: {=_xlfn.IFS($F53<Glossary!$C$54,Glossary!$B$54,$F53<Glossary!$C$55,Glossary!$B$55,$F53>Glossary!$C$56,Glossary!$B$56)} -> Small Cap | Y53: Mumbai | Z53: Family | AA53: 0.61 | AC53: High | AD53: High | AE53: High | AG53: Shah family | AJ53: Y | AU53: Platforms | AV53: 261.6 | AW53: 261.6 | AX53: 261.6 | AY53: 570.9 | AZ53: 580 | BA53: 166.2 | BB53: 56.3 | BC53: 8.36 | BG53: 0.1111 | BK53: 0.1429 | CF53: =IF(CE53>='Conviction List'!$D$8,1,"") | CG53: =IF(M53<='Conviction List'!$E$8,1,"") -> 1 | CH53: =IF(BG53>='Conviction List'!$F$8,1,"") | CI53: =IF(BK53>='Conviction List'!$G$8,1,"") | CJ53: =SUM(CF53:CI53) -> 1 | CK53: =MATCH($D53,INDIRECT($C$90&"!$C$1:$C$164"),0) -> 55
B54: =B53+1 -> 52 | C54: Walchandnagar Industries | D54: WI | E54: WALCHANNAG | F54: =_xlfn.XLOOKUP(CCA_Defense!$D54,BB_Input!$C$4:$C$172,BB_Input!$G$4:$G$172) -> 147.71937 | G54: 1908 | H54: =YEAR(TODAY())-G54 -> 118 | I54: Listed | J54: Rocket motors | N54: =IFERROR(_xlfn.XLOOKUP($D54,PE_Projections!$D:$D,PE_Projections!L:L),"") | O54: =IFERROR(_xlfn.XLOOKUP($D54,PE_Projections!$D:$D,PE_Projections!M:M),"") | P54: =IFERROR(_xlfn.XLOOKUP($D54,PE_Projections!$D:$D,PE_Projections!N:N),"") -> 371.6376 | Q54: =IFERROR(_xlfn.XLOOKUP($D54,PE_Projections!$D:$D,PE_Projections!O:O),"") -> 229.45656 | R54: =IFERROR(_xlfn.XLOOKUP($D54,PE_Projections!$D:$D,PE_Projections!P:P),"") -> 196.76544 | S54: -14 | T54: =IFERROR(RATE(5,,BB54,-AY54),"") -> -0.028214491 | V54: =AVERAGE(40%,50%) -> 0.45 | W54: 3.4 | X54: {=_xlfn.IFS($F54<Glossary!$C$54,Glossary!$B$54,$F54<Glossary!$C$55,Glossary!$B$55,$F54>Glossary!$C$56,Glossary!$B$56)} -> Small Cap | Y54: Pune | Z54: Family | AA54: 0.48 | AC54: High | AD54: High | AE54: Medium | AG54: Walchand Hirachand family | AK54: Y | AL54: Y | AN54: Y | AS54: Y | AU54: Diversified | AV54: 7.3 | AW54: 7.3 | AX54: 7.3 | AY54: 29.9 | AZ54: 34.9 | BA54: 37.2 | BB54: 34.5 | BC54: -44.8 | BG54: -0.2456 | BK54: -0.0792 | BO54: -2.25 | CF54: =IF(CE54>='Conviction List'!$D$8,1,"") | CG54: =IF(M54<='Conviction List'!$E$8,1,"") -> 1 | CH54: =IF(BG54>='Conviction List'!$F$8,1,"") | CI54: =IF(BK54>='Conviction List'!$G$8,1,"") | CJ54: =SUM(CF54:CI54) -> 1 | CK54: =MATCH($D54,INDIRECT($C$90&"!$C$1:$C$164"),0) -> 56
B55: =B54+1 -> 53 | C55: Advance Weapon Equipment India | D55: 1943634D | F55: =_xlfn.XLOOKUP(CCA_Defense!$D55,BB_Input!$C$4:$C$172,BB_Input!$G$4:$G$172) -> #N/A | G55: 2019 | H55: =YEAR(TODAY())-G55 -> 7 | I55: Unlisted | J55: Small arms | N55: =IFERROR(_xlfn.XLOOKUP($D55,PE_Projections!$D:$D,PE_Projections!L:L),"") | O55: =IFERROR(_xlfn.XLOOKUP($D55,PE_Projections!$D:$D,PE_Projections!M:M),"") | P55: =IFERROR(_xlfn.XLOOKUP($D55,PE_Projections!$D:$D,PE_Projections!N:N),"") | Q55: =IFERROR(_xlfn.XLOOKUP($D55,PE_Projections!$D:$D,PE_Projections!O:O),"") | R55: =IFERROR(_xlfn.XLOOKUP($D55,PE_Projections!$D:$D,PE_Projections!P:P),"") | T55: =IFERROR(RATE(5,,BB55,-AY55),"") | Y55: Kanpur | Z55: Government | AA55: 1 | AC55: High | AD55: High | AE55: High | AN55: Y | AU55: Tier 2 | CF55: =IF(CE55>='Conviction List'!$D$8,1,"") | CG55: =IF(M55<='Conviction List'!$E$8,1,"") -> 1 | CH55: =IF(BG55>='Conviction List'!$F$8,1,"") | CI55: =IF(BK55>='Conviction List'!$G$8,1,"") | CJ55: =SUM(CF55:CI55) -> 1 | CK55: =MATCH($D55,INDIRECT($C$90&"!$C$1:$C$164"),0) -> 57
B56: =B55+1 -> 54 | C56: Armoured Vehicles Nigam | D56: 2300472D | F56: =_xlfn.XLOOKUP(CCA_Defense!$D56,BB_Input!$C$4:$C$172,BB_Input!$G$4:$G$172) -> #N/A | G56: 2021 | H56: =YEAR(TODAY())-G56 -> 5 | I56: Unlisted | J56: Armoured vehicles | N56: =IFERROR(_xlfn.XLOOKUP($D56,PE_Projections!$D:$D,PE_Projections!L:L),"") | O56: =IFERROR(_xlfn.XLOOKUP($D56,PE_Projections!$D:$D,PE_Projections!M:M),"") | P56: =IFERROR(_xlfn.XLOOKUP($D56,PE_Projections!$D:$D,PE_Projections!N:N),"") | Q56: =IFERROR(_xlfn.XLOOKUP($D56,PE_Projections!$D:$D,PE_Projections!O:O),"") | R56: =IFERROR(_xlfn.XLOOKUP($D56,PE_Projections!$D:$D,PE_Projections!P:P),"") | T56: =IFERROR(RATE(5,,BB56,-AY56),"") | W56: 6.9 | Y56: Chennai | Z56: Government | AA56: 1 | AC56: High | AD56: High | AE56: High | AI56: Y | AU56: Platforms | AY56: 544 | CF56: =IF(CE56>='Conviction List'!$D$8,1,"") | CG56: =IF(M56<='Conviction List'!$E$8,1,"") -> 1 | CH56: =IF(BG56>='Conviction List'!$F$8,1,"") | CI56: =IF(BK56>='Conviction List'!$G$8,1,"") | CJ56: =SUM(CF56:CI56) -> 1 | CK56: =MATCH($D56,INDIRECT($C$90&"!$C$1:$C$164"),0) -> 58
B57: =B56+1 -> 55 | C57: Artemon Aerospace | D57: 1637857D | F57: =_xlfn.XLOOKUP(CCA_Defense!$D57,BB_Input!$C$4:$C$172,BB_Input!$G$4:$G$172) -> #N/A | G57: 2019 | H57: =YEAR(TODAY())-G57 -> 7 | I57: Unlisted | J57: UAVs | N57: =IFERROR(_xlfn.XLOOKUP($D57,PE_Projections!$D:$D,PE_Projections!L:L),"") | O57: =IFERROR(_xlfn.XLOOKUP($D57,PE_Projections!$D:$D,PE_Projections!M:M),"") | P57: =IFERROR(_xlfn.XLOOKUP($D57,PE_Projections!$D:$D,PE_Projections!N:N),"") | Q57: =IFERROR(_xlfn.XLOOKUP($D57,PE_Projections!$D:$D,PE_Projections!O:O),"") | R57: =IFERROR(_xlfn.XLOOKUP($D57,PE_Projections!$D:$D,PE_Projections!P:P),"") | T57: =IFERROR(RATE(5,,BB57,-AY57),"") | Y57: Hyderabad | Z57: Private | AC57: High | AD57: High | AE57: High | AN57: Y | AU57: Tier 2 | CF57: =IF(CE57>='Conviction List'!$D$8,1,"") | CG57: =IF(M57<='Conviction List'!$E$8,1,"") -> 1 | CH57: =IF(BG57>='Conviction List'!$F$8,1,"") | CI57: =IF(BK57>='Conviction List'!$G$8,1,"") | CJ57: =SUM(CF57:CI57) -> 1 | CK57: =MATCH($D57,INDIRECT($C$90&"!$C$1:$C$164"),0) -> 59
B58: =B57+1 -> 56 | C58: Gliders India | D58: 0824100D | F58: =_xlfn.XLOOKUP(CCA_Defense!$D58,BB_Input!$C$4:$C$172,BB_Input!$G$4:$G$172) -> #N/A | G58: 1950 | H58: =YEAR(TODAY())-G58 -> 76 | I58: Unlisted | J58: Parachutes | N58: =IFERROR(_xlfn.XLOOKUP($D58,PE_Projections!$D:$D,PE_Projections!L:L),"") | O58: =IFERROR(_xlfn.XLOOKUP($D58,PE_Projections!$D:$D,PE_Projections!M:M),"") | P58: =IFERROR(_xlfn.XLOOKUP($D58,PE_Projections!$D:$D,PE_Projections!N:N),"") | Q58: =IFERROR(_xlfn.XLOOKUP($D58,PE_Projections!$D:$D,PE_Projections!O:O),"") | R58: =IFERROR(_xlfn.XLOOKUP($D58,PE_Projections!$D:$D,PE_Projections!P:P),"") | T58: =IFERROR(RATE(5,,BB58,-AY58),"") | Y58: Kanpur | Z58: Government | AA58: 1 | AC58: High | AD58: High | AE58: High | AO58: Y | AU58: Tier 2 | CK58: =MATCH($D58,INDIRECT($C$90&"!$C$1:$C$164"),0) -> 60
B59: =B58+1 -> 57 | C59: Goa Shipyard | D59: 7559676Z | F59: =_xlfn.XLOOKUP(CCA_Defense!$D59,BB_Input!$C$4:$C$172,BB_Input!$G$4:$G$172) -> #N/A | G59: 1957 | H59: =YEAR(TODAY())-G59 -> 69 | I59: Unlisted | J59: Warships | N59: =IFERROR(_xlfn.XLOOKUP($D59,PE_Projections!$D:$D,PE_Projections!L:L),"") | O59: =IFERROR(_xlfn.XLOOKUP($D59,PE_Projections!$D:$D,PE_Projections!M:M),"") | P59: =IFERROR(_xlfn.XLOOKUP($D59,PE_Projections!$D:$D,PE_Projections!N:N),"") | Q59: =IFERROR(_xlfn.XLOOKUP($D59,PE_Projections!$D:$D,PE_Projections!O:O),"") | R59: =IFERROR(_xlfn.XLOOKUP($D59,PE_Projections!$D:$D,PE_Projections!P:P),"") | T59: =IFERROR(RATE(5,,BB59,-AY59),"") | W59: 5.7 | Y59: Goa | Z59: Government | AA59: 1 | AC59: High | AD59: High | AE59: High | AJ59: Y | AU59: Platforms | AY59: 350.9 | CF59: =IF(CE59>='Conviction List'!$D$8,1,"") | CG59: =IF(M59<='Conviction List'!$E$8,1,"") -> 1 | CH59: =IF(BG59>='Conviction List'!$F$8,1,"") | CI59: =IF(BK59>='Conviction List'!$G$8,1,"") | CJ59: =SUM(CF59:CI59) -> 1 | CK59: =MATCH($D59,INDIRECT($C$90&"!$C$1:$C$164"),0) -> 61
B60: =B59+1 -> 58 | C60: Hindustan Shipyard | D60: 6595300Z | F60: =_xlfn.XLOOKUP(CCA_Defense!$D60,BB_Input!$C$4:$C$172,BB_Input!$G$4:$G$172) -> #N/A | G60: 1941 | H60: =YEAR(TODAY())-G60 -> 85 | I60: Unlisted | J60: Shipbuilding | N60: =IFERROR(_xlfn.XLOOKUP($D60,PE_Projections!$D:$D,PE_Projections!L:L),"") | O60: =IFERROR(_xlfn.XLOOKUP($D60,PE_Projections!$D:$D,PE_Projections!M:M),"") | P60: =IFERROR(_xlfn.XLOOKUP($D60,PE_Projections!$D:$D,PE_Projections!N:N),"") | Q60: =IFERROR(_xlfn.XLOOKUP($D60,PE_Projections!$D:$D,PE_Projections!O:O),"") | R60: =IFERROR(_xlfn.XLOOKUP($D60,PE_Projections!$D:$D,PE_Projections!P:P),"") | T60: =IFERROR(RATE(5,,BB60,-AY60),"") | W60: 11.2 | Y60: Vishakapatnam | Z60: Government | AA60: 1 | AC60: High | AD60: High | AE60: High | AJ60: Y | AU60: Platforms | AY60: 195.8 | CF60: =IF(CE60>='Conviction List'!$D$8,1,"") | CG60: =IF(M60<='Conviction List'!$E$8,1,"") -> 1 | CH60: =IF(BG60>='Conviction List'!$F$8,1,"") | CI60: =IF(BK60>='Conviction List'!$G$8,1,"") | CJ60: =SUM(CF60:CI60) -> 1 | CK60: =MATCH($D60,INDIRECT($C$90&"!$C$1:$C$164"),0) -> 62
B61: =B60+1 -> 59 | C61: India Optel | D61: 1633945D | F61: =_xlfn.XLOOKUP(CCA_Defense!$D61,BB_Input!$C$4:$C$172,BB_Input!$G$4:$G$172) -> #N/A | G61: 2000 | H61: =YEAR(TODAY())-G61 -> 26 | I61: Unlisted | J61: Optronics | N61: =IFERROR(_xlfn.XLOOKUP($D61,PE_Projections!$D:$D,PE_Projections!L:L),"") | O61: =IFERROR(_xlfn.XLOOKUP($D61,PE_Projections!$D:$D,PE_Projections!M:M),"") | P61: =IFERROR(_xlfn.XLOOKUP($D61,PE_Projections!$D:$D,PE_Projections!N:N),"") | Q61: =IFERROR(_xlfn.XLOOKUP($D61,PE_Projections!$D:$D,PE_Projections!O:O),"") | R61: =IFERROR(_xlfn.XLOOKUP($D61,PE_Projections!$D:$D,PE_Projections!P:P),"") | T61: =IFERROR(RATE(5,,BB61,-AY61),"") | W61: 4.9 | Y61: Dehradun | Z61: Government | AA61: 1 | AC61: High | AD61: High | AE61: High | AQ61: Y | AU61: Tier 3 | AZ61: 152 | CF61: =IF(CE61>='Conviction List'!$D$8,1,"") | CG61: =IF(M61<='Conviction List'!$E$8,1,"") -> 1 | CH61: =IF(BG61>='Conviction List'!$F$8,1,"") | CI61: =IF(BK61>='Conviction List'!$G$8,1,"") | CJ61: =SUM(CF61:CI61) -> 1 | CK61: =MATCH($D61,INDIRECT($C$90&"!$C$1:$C$164"),0) -> 63
B62: =B61+1 -> 60 | C62: Munitions India | D62: 1943632D | F62: =_xlfn.XLOOKUP(CCA_Defense!$D62,BB_Input!$C$4:$C$172,BB_Input!$G$4:$G$172) -> #N/A | G62: 2021 | H62: =YEAR(TODAY())-G62 -> 5 | I62: Unlisted | J62: Ammunition | N62: =IFERROR(_xlfn.XLOOKUP($D62,PE_Projections!$D:$D,PE_Projections!L:L),"") | O62: =IFERROR(_xlfn.XLOOKUP($D62,PE_Projections!$D:$D,PE_Projections!M:M),"") | P62: =IFERROR(_xlfn.XLOOKUP($D62,PE_Projections!$D:$D,PE_Projections!N:N),"") | Q62: =IFERROR(_xlfn.XLOOKUP($D62,PE_Projections!$D:$D,PE_Projections!O:O),"") | R62: =IFERROR(_xlfn.XLOOKUP($D62,PE_Projections!$D:$D,PE_Projections!P:P),"") | T62: =IFERROR(RATE(5,,BB62,-AY62),"") | W62: 1.48 | Y62: Pune | Z62: Government | AA62: 1 | AC62: High | AD62: High | AE62: High | AN62: Y | AU62: Tier 2 | AY62: 966 | CF62: =IF(CE62>='Conviction List'!$D$8,1,"") | CG62: =IF(M62<='Conviction List'!$E$8,1,"") -> 1 | CH62: =IF(BG62>='Conviction List'!$F$8,1,"") | CI62: =IF(BK62>='Conviction List'!$G$8,1,"") | CJ62: =SUM(CF62:CI62) -> 1 | CK62: =MATCH($D62,INDIRECT($C$90&"!$C$1:$C$164"),0) -> 64
B63: =B62+1 -> 61 | C63: Raychem RPG | D63: 1315Z | F63: =_xlfn.XLOOKUP(CCA_Defense!$D63,BB_Input!$C$4:$C$172,BB_Input!$G$4:$G$172) -> #N/A | G63: 1989 | H63: =YEAR(TODAY())-G63 -> 37 | I63: Unlisted | J63: Cable accessories | N63: =IFERROR(_xlfn.XLOOKUP($D63,PE_Projections!$D:$D,PE_Projections!L:L),"") | O63: =IFERROR(_xlfn.XLOOKUP($D63,PE_Projections!$D:$D,PE_Projections!M:M),"") | P63: =IFERROR(_xlfn.XLOOKUP($D63,PE_Projections!$D:$D,PE_Projections!N:N),"") | Q63: =IFERROR(_xlfn.XLOOKUP($D63,PE_Projections!$D:$D,PE_Projections!O:O),"") | R63: =IFERROR(_xlfn.XLOOKUP($D63,PE_Projections!$D:$D,PE_Projections!P:P),"") | T63: =IFERROR(RATE(5,,BB63,-AY63),"") | W63: 0.3 | Y63: Mumbai | Z63: Private | AC63: High | AD63: Medium | AE63: Medium | AG63: RPG Group (India) + TE Connectivity 50:50 Joint Venture | AP63: Y | AU63: Tier 3 | AY63: 168 | CF63: =IF(CE63>='Conviction List'!$D$8,1,"") | CG63: =IF(M63<='Conviction List'!$E$8,1,"") -> 1 | CH63: =IF(BG63>='Conviction List'!$F$8,1,"") | CI63: =IF(BK63>='Conviction List'!$G$8,1,"") | CJ63: =SUM(CF63:CI63) -> 1 | CK63: =MATCH($D63,INDIRECT($C$90&"!$C$1:$C$164"),0) -> 65
B64: =B63+1 -> 62 | C64: Sagar Defence and Engineering Private | D64: 2250224D | F64: =_xlfn.XLOOKUP(CCA_Defense!$D64,BB_Input!$C$4:$C$172,BB_Input!$G$4:$G$172) -> #N/A | G64: 2009 | H64: =YEAR(TODAY())-G64 -> 17 | I64: Unlisted | J64: Naval drones | N64: =IFERROR(_xlfn.XLOOKUP($D64,PE_Projections!$D:$D,PE_Projections!L:L),"") | O64: =IFERROR(_xlfn.XLOOKUP($D64,PE_Projections!$D:$D,PE_Projections!M:M),"") | P64: =IFERROR(_xlfn.XLOOKUP($D64,PE_Projections!$D:$D,PE_Projections!N:N),"") | Q64: =IFERROR(_xlfn.XLOOKUP($D64,PE_Projections!$D:$D,PE_Projections!O:O),"") | R64: =IFERROR(_xlfn.XLOOKUP($D64,PE_Projections!$D:$D,PE_Projections!P:P),"") | T64: =IFERROR(RATE(5,,BB64,-AY64),"") | W64: 25.2 | Y64: Navi Mumbai | Z64: Private | AC64: High | AD64: High | AE64: High | AJ64: Y | AU64: Platforms | AY64: 13 | CF64: =IF(CE64>='Conviction List'!$D$8,1,"") | CG64: =IF(M64<='Conviction List'!$E$8,1,"") -> 1 | CH64: =IF(BG64>='Conviction List'!$F$8,1,"") | CI64: =IF(BK64>='Conviction List'!$G$8,1,"") | CJ64: =SUM(CF64:CI64) -> 1 | CK64: =MATCH($D64,INDIRECT($C$90&"!$C$1:$C$164"),0) -> 66
B65: =B64+1 -> 63 | C65: Troop Comforts | D65: 1359165D | F65: =_xlfn.XLOOKUP(CCA_Defense!$D65,BB_Input!$C$4:$C$172,BB_Input!$G$4:$G$172) -> #N/A | G65: 1920 | H65: =YEAR(TODAY())-G65 -> 106 | I65: Unlisted | J65: Soldier gear | N65: =IFERROR(_xlfn.XLOOKUP($D65,PE_Projections!$D:$D,PE_Projections!L:L),"") | O65: =IFERROR(_xlfn.XLOOKUP($D65,PE_Projections!$D:$D,PE_Projections!M:M),"") | P65: =IFERROR(_xlfn.XLOOKUP($D65,PE_Projections!$D:$D,PE_Projections!N:N),"") | Q65: =IFERROR(_xlfn.XLOOKUP($D65,PE_Projections!$D:$D,PE_Projections!O:O),"") | R65: =IFERROR(_xlfn.XLOOKUP($D65,PE_Projections!$D:$D,PE_Projections!P:P),"") | T65: =IFERROR(RATE(5,,BB65,-AY65),"") | W65: 0.3 | Y65: Kanpur | Z65: Government | AA65: 1 | AC65: High | AD65: Medium | AE65: Medium | AO65: Y | AU65: Tier 2 | AY65: 115 | CF65: =IF(CE65>='Conviction List'!$D$8,1,"") | CG65: =IF(M65<='Conviction List'!$E$8,1,"") -> 1 | CH65: =IF(BG65>='Conviction List'!$F$8,1,"") | CI65: =IF(BK65>='Conviction List'!$G$8,1,"") | CJ65: =SUM(CF65:CI65) -> 1 | CK65: =MATCH($D65,INDIRECT($C$90&"!$C$1:$C$164"),0) -> 67
B66: =B65+1 -> 64 | C66: Vijayan Trishul Defence Solutions | D66: 2582619D | F66: =_xlfn.XLOOKUP(CCA_Defense!$D66,BB_Input!$C$4:$C$172,BB_Input!$G$4:$G$172) -> #N/A | G66: 2018 | H66: =YEAR(TODAY())-G66 -> 8 | I66: Unlisted | J66: Systems integration | N66: =IFERROR(_xlfn.XLOOKUP($D66,PE_Projections!$D:$D,PE_Projections!L:L),"") | O66: =IFERROR(_xlfn.XLOOKUP($D66,PE_Projections!$D:$D,PE_Projections!M:M),"") | P66: =IFERROR(_xlfn.XLOOKUP($D66,PE_Projections!$D:$D,PE_Projections!N:N),"") | Q66: =IFERROR(_xlfn.XLOOKUP($D66,PE_Projections!$D:$D,PE_Projections!O:O),"") | R66: =IFERROR(_xlfn.XLOOKUP($D66,PE_Projections!$D:$D,PE_Projections!P:P),"") | T66: =IFERROR(RATE(5,,BB66,-AY66),"") | Y66: Bangalore | Z66: Private | AC66: High | AD66: Medium | AE66: Medium | AN66: Y | AU66: Tier 2 | CF66: =IF(CE66>='Conviction List'!$D$8,1,"") | CG66: =IF(M66<='Conviction List'!$E$8,1,"") -> 1 | CH66: =IF(BG66>='Conviction List'!$F$8,1,"") | CI66: =IF(BK66>='Conviction List'!$G$8,1,"") | CJ66: =SUM(CF66:CI66) -> 1 | CK66: =MATCH($D66,INDIRECT($C$90&"!$C$1:$C$164"),0) -> 68
B67: =B66+1 -> 65 | C67: Yantra India | D67: 1943633D | F67: =_xlfn.XLOOKUP(CCA_Defense!$D67,BB_Input!$C$4:$C$172,BB_Input!$G$4:$G$172) -> #N/A | G67: 2009 | H67: =YEAR(TODAY())-G67 -> 17 | I67: Unlisted | J67: Ammunition components | N67: =IFERROR(_xlfn.XLOOKUP($D67,PE_Projections!$D:$D,PE_Projections!L:L),"") | O67: =IFERROR(_xlfn.XLOOKUP($D67,PE_Projections!$D:$D,PE_Projections!M:M),"") | P67: =IFERROR(_xlfn.XLOOKUP($D67,PE_Projections!$D:$D,PE_Projections!N:N),"") | Q67: =IFERROR(_xlfn.XLOOKUP($D67,PE_Projections!$D:$D,PE_Projections!O:O),"") | R67: =IFERROR(_xlfn.XLOOKUP($D67,PE_Projections!$D:$D,PE_Projections!P:P),"") | T67: =IFERROR(RATE(5,,BB67,-AY67),"") | Y67: Nagpur | Z67: Government | AA67: 1 | AC67: High | AD67: High | AE67: High | AT67: Y | AU67: Tier 4 | CF67: =IF(CE67>='Conviction List'!$D$8,1,"") | CG67: =IF(M67<='Conviction List'!$E$8,1,"") -> 1 | CH67: =IF(BG67>='Conviction List'!$F$8,1,"") | CI67: =IF(BK67>='Conviction List'!$G$8,1,"") | CJ67: =SUM(CF67:CI67) -> 1 | CK67: =MATCH($D67,INDIRECT($C$90&"!$C$1:$C$164"),0) -> 69
B68: =B67+1 -> 66 | C68: Sail Ltd | D68: SAIL | E68: SAIL | F68: =_xlfn.XLOOKUP(CCA_Defense!$D68,BB_Input!$C$4:$C$172,BB_Input!$G$4:$G$172) -> 6066.7163 | G68: 1973 | H68: =YEAR(TODAY())-G68 -> 53 | I68: Listed | J68: Defence steel | M68: 23.7 | N68: =IFERROR(_xlfn.XLOOKUP($D68,PE_Projections!$D:$D,PE_Projections!L:L),"") -> 15.589056 | O68: =IFERROR(_xlfn.XLOOKUP($D68,PE_Projections!$D:$D,PE_Projections!M:M),"") -> 12.706685 | P68: =IFERROR(_xlfn.XLOOKUP($D68,PE_Projections!$D:$D,PE_Projections!N:N),"") -> 11.629351 | Q68: =IFERROR(_xlfn.XLOOKUP($D68,PE_Projections!$D:$D,PE_Projections!O:O),"") -> 12.473984 | R68: =IFERROR(_xlfn.XLOOKUP($D68,PE_Projections!$D:$D,PE_Projections!P:P),"") | S68: -3 | T68: =IFERROR(RATE(5,,BB68,-AY68),"") -> -0.0020937533 | V68: 1 | X68: {=_xlfn.IFS($F68<Glossary!$C$54,Glossary!$B$54,$F68<Glossary!$C$55,Glossary!$B$55,$F68>Glossary!$C$56,Glossary!$B$56)} -> Mid Cap | Y68: New Delhi | Z68: Government | AA68: 1 | AC68: High | AD68: Medium | AE68: Medium | AG68: Under Ministry of Steel, Government of India | AS68: Y | AU68: Tier 4 | AV68: 4173 | AW68: 4170 | AX68: 4140 | AY68: 12340 | AZ68: 12690 | BA68: 12580 | BB68: 12470 | BC68: 6.87 | BD68: 8.8 | BE68: 5.4 | BG68: 0.0403 | BH68: 0.0548 | BI68: 0.04 | BJ68: 0.2458 | BL68: 0.073 | BM68: 0.06285 | BN68: 0.2328 | CF68: =IF(CE68>='Conviction List'!$D$8,1,"") | CG68: =IF(M68<='Conviction List'!$E$8,1,"") -> 1 | CH68: =IF(BG68>='Conviction List'!$F$8,1,"") | CI68: =IF(BK68>='Conviction List'!$G$8,1,"") | CJ68: =SUM(CF68:CI68) -> 1 | CK68: =MATCH($D68,INDIRECT($C$90&"!$C$1:$C$164"),0) -> 70
B69: =B68+1 -> 67 | C69: Rossell Techsys Ltd | D69: ROSSTECH | E69: ROSSTECH | F69: =_xlfn.XLOOKUP(CCA_Defense!$D69,BB_Input!$C$4:$C$172,BB_Input!$G$4:$G$172) -> 266.42668 | G69: 1990 | H69: =YEAR(TODAY())-G69 -> 36 | I69: Listed | J69: Wire harnesses | L69: Yes | M69: 353 | N69: =IFERROR(_xlfn.XLOOKUP($D69,PE_Projections!$D:$D,PE_Projections!L:L),"") -> 77.575308 | O69: =IFERROR(_xlfn.XLOOKUP($D69,PE_Projections!$D:$D,PE_Projections!M:M),"") -> 72.408744 | P69: =IFERROR(_xlfn.XLOOKUP($D69,PE_Projections!$D:$D,PE_Projections!N:N),"") -> 67.586277 | Q69: =IFERROR(_xlfn.XLOOKUP($D69,PE_Projections!$D:$D,PE_Projections!O:O),"") -> 63.084989 | R69: =IFERROR(_xlfn.XLOOKUP($D69,PE_Projections!$D:$D,PE_Projections!P:P),"") -> 58.88349 | T69: =IFERROR(RATE(5,,BB69,-AY69),"") -> 0.10286313 | V69: 0.9 | W69: 11.5 | X69: {=_xlfn.IFS($F69<Glossary!$C$54,Glossary!$B$54,$F69<Glossary!$C$55,Glossary!$B$55,$F69>Glossary!$C$56,Glossary!$B$56)} -> Small Cap | Y69: Bangalore | Z69: Family | AA69: 0.748 | AC69: High | AD69: High | AE69: High | AP69: Y | AQ69: Y | AR69: Y | AU69: Tier 3 | AV69: =37696475/10^6 -> 37.696475 | AW69: =37696475/10^6 -> 37.696475 | AX69: =37696475/10^6 -> 37.696475 | AY69: 31 | AZ69: 26 | BA69: 23 | BB69: 19 | CE69: =IFERROR(RATE(4,,BB69,-AY69),"") -> 0.13019146 | CF69: =IF(CE69>='Conviction List'!$D$8,1,"") | CG69: =IF(M69<='Conviction List'!$E$8,1,"") | CH69: =IF(BG69>='Conviction List'!$F$8,1,"") | CI69: =IF(BK69>='Conviction List'!$G$8,1,"") | CJ69: =SUM(CF69:CI69) -> 0 | CK69: =MATCH($D69,INDIRECT($C$90&"!$C$1:$C$164"),0) -> 22
B70: =B69+1 -> 68 | C70: Mahindra Defence Systems | D70: 1313978D | F70: =_xlfn.XLOOKUP(CCA_Defense!$D70,BB_Input!$C$4:$C$172,BB_Input!$G$4:$G$172) -> #N/A | G70: 2013 | H70: =YEAR(TODAY())-G70 -> 13 | I70: Acquired by/Part of Listed Company | J70: Armoured vehicles | N70: =IFERROR(_xlfn.XLOOKUP($D70,PE_Projections!$D:$D,PE_Projections!L:L),"") | O70: =IFERROR(_xlfn.XLOOKUP($D70,PE_Projections!$D:$D,PE_Projections!M:M),"") | P70: =IFERROR(_xlfn.XLOOKUP($D70,PE_Projections!$D:$D,PE_Projections!N:N),"") | Q70: =IFERROR(_xlfn.XLOOKUP($D70,PE_Projections!$D:$D,PE_Projections!O:O),"") | R70: =IFERROR(_xlfn.XLOOKUP($D70,PE_Projections!$D:$D,PE_Projections!P:P),"") | T70: =IFERROR(RATE(5,,BB70,-AY70),"") | Y70: Mumbai | Z70: Family | AC70: High | AD70: High | AE70: High | AG70: Owned by Mahindra & Mahindra | AQ70: Y | AU70: Tier 3 | CF70: =IF(CE70>='Conviction List'!$D$8,1,"") | CG70: =IF(M70<='Conviction List'!$E$8,1,"") -> 1 | CH70: =IF(BG70>='Conviction List'!$F$8,1,"") | CI70: =IF(BK70>='Conviction List'!$G$8,1,"") | CJ70: =SUM(CF70:CI70) -> 1 | CK70: =MATCH($D70,INDIRECT($C$90&"!$C$1:$C$164"),0) -> 72
B71: =B70+1 -> 69 | C71: Brahmos Aerospace | D71: 2339955Z | F71: =_xlfn.XLOOKUP(CCA_Defense!$D71,BB_Input!$C$4:$C$172,BB_Input!$G$4:$G$172) -> #N/A | G71: 1998 | H71: =YEAR(TODAY())-G71 -> 28 | I71: Unlisted | J71: Cruise missiles | N71: =IFERROR(_xlfn.XLOOKUP($D71,PE_Projections!$D:$D,PE_Projections!L:L),"") | O71: =IFERROR(_xlfn.XLOOKUP($D71,PE_Projections!$D:$D,PE_Projections!M:M),"") | P71: =IFERROR(_xlfn.XLOOKUP($D71,PE_Projections!$D:$D,PE_Projections!N:N),"") | Q71: =IFERROR(_xlfn.XLOOKUP($D71,PE_Projections!$D:$D,PE_Projections!O:O),"") | R71: =IFERROR(_xlfn.XLOOKUP($D71,PE_Projections!$D:$D,PE_Projections!P:P),"") | T71: =IFERROR(RATE(5,,BB71,-AY71),"") | W71: 6 | Y71: New Delhi | Z71: Government | AC71: High | AD71: High | AE71: High | AG71: Join venture between India's DRDO & Russia's NPO Mashinostroyeniya | AM71: Y | AU71: Tier 1 | CF71: =IF(CE71>='Conviction List'!$D$8,1,"") | CG71: =IF(M71<='Conviction List'!$E$8,1,"") -> 1 | CH71: =IF(BG71>='Conviction List'!$F$8,1,"") | CI71: =IF(BK71>='Conviction List'!$G$8,1,"") | CJ71: =SUM(CF71:CI71) -> 1 | CK71: =MATCH($D71,INDIRECT($C$90&"!$C$1:$C$164"),0) -> 73
B72: =B71+1 -> 70 | C72: MKU Ltd | D72: 1471388D | F72: =_xlfn.XLOOKUP(CCA_Defense!$D72,BB_Input!$C$4:$C$172,BB_Input!$G$4:$G$172) -> #N/A | G72: 1985 | H72: =YEAR(TODAY())-G72 -> 41 | I72: Unlisted | J72: Body armour | N72: =IFERROR(_xlfn.XLOOKUP($D72,PE_Projections!$D:$D,PE_Projections!L:L),"") | O72: =IFERROR(_xlfn.XLOOKUP($D72,PE_Projections!$D:$D,PE_Projections!M:M),"") | P72: =IFERROR(_xlfn.XLOOKUP($D72,PE_Projections!$D:$D,PE_Projections!N:N),"") | Q72: =IFERROR(_xlfn.XLOOKUP($D72,PE_Projections!$D:$D,PE_Projections!O:O),"") | R72: =IFERROR(_xlfn.XLOOKUP($D72,PE_Projections!$D:$D,PE_Projections!P:P),"") | T72: =IFERROR(RATE(5,,BB72,-AY72),"") | W72: 1 | Y72: Kanpur | Z72: Private | AC72: Medium | AD72: Medium | AE72: Medium | AO72: Y | AU72: Tier 2 | CF72: =IF(CE72>='Conviction List'!$D$8,1,"") | CG72: =IF(M72<='Conviction List'!$E$8,1,"") -> 1 | CH72: =IF(BG72>='Conviction List'!$F$8,1,"") | CI72: =IF(BK72>='Conviction List'!$G$8,1,"") | CJ72: =SUM(CF72:CI72) -> 1 | CK72: =MATCH($D72,INDIRECT($C$90&"!$C$1:$C$164"),0) -> 74
B73: =B72+1 -> 71 | C73: Samtel Avionics | D73: 6594164Z | F73: =_xlfn.XLOOKUP(CCA_Defense!$D73,BB_Input!$C$4:$C$172,BB_Input!$G$4:$G$172) -> #N/A | G73: 2000 | H73: =YEAR(TODAY())-G73 -> 26 | I73: Unlisted | J73: Avionics displays | N73: =IFERROR(_xlfn.XLOOKUP($D73,PE_Projections!$D:$D,PE_Projections!L:L),"") | O73: =IFERROR(_xlfn.XLOOKUP($D73,PE_Projections!$D:$D,PE_Projections!M:M),"") | P73: =IFERROR(_xlfn.XLOOKUP($D73,PE_Projections!$D:$D,PE_Projections!N:N),"") | Q73: =IFERROR(_xlfn.XLOOKUP($D73,PE_Projections!$D:$D,PE_Projections!O:O),"") | R73: =IFERROR(_xlfn.XLOOKUP($D73,PE_Projections!$D:$D,PE_Projections!P:P),"") | T73: =IFERROR(RATE(5,,BB73,-AY73),"") | W73: 6 | Y73: New Delhi | Z73: Private | AC73: High | AD73: High | AE73: High | AG73: JV with HAL for avionics | AQ73: Y | AU73: Tier 3 | AY73: 16.5 | CF73: =IF(CE73>='Conviction List'!$D$8,1,"") | CG73: =IF(M73<='Conviction List'!$E$8,1,"") -> 1 | CH73: =IF(BG73>='Conviction List'!$F$8,1,"") | CI73: =IF(BK73>='Conviction List'!$G$8,1,"") | CJ73: =SUM(CF73:CI73) -> 1 | CK73: =MATCH($D73,INDIRECT($C$90&"!$C$1:$C$164"),0) -> 75
B74: =B73+1 -> 72 | C74: Tonbo Imaging | D74: 1537114D | F74: =_xlfn.XLOOKUP(CCA_Defense!$D74,BB_Input!$C$4:$C$172,BB_Input!$G$4:$G$172) -> #N/A | G74: 2008 | H74: =YEAR(TODAY())-G74 -> 18 | I74: Unlisted | J74: Thermal imaging | N74: =IFERROR(_xlfn.XLOOKUP($D74,PE_Projections!$D:$D,PE_Projections!L:L),"") | O74: =IFERROR(_xlfn.XLOOKUP($D74,PE_Projections!$D:$D,PE_Projections!M:M),"") | P74: =IFERROR(_xlfn.XLOOKUP($D74,PE_Projections!$D:$D,PE_Projections!N:N),"") | Q74: =IFERROR(_xlfn.XLOOKUP($D74,PE_Projections!$D:$D,PE_Projections!O:O),"") | R74: =IFERROR(_xlfn.XLOOKUP($D74,PE_Projections!$D:$D,PE_Projections!P:P),"") | T74: =IFERROR(RATE(5,,BB74,-AY74),"") | W74: 0.5 | Y74: Bangalore | Z74: Private | AC74: High | AD74: High | AE74: High | AQ74: Y | AU74: Tier 3 | AY74: 51.5 | CF74: =IF(CE74>='Conviction List'!$D$8,1,"") | CG74: =IF(M74<='Conviction List'!$E$8,1,"") -> 1 | CH74: =IF(BG74>='Conviction List'!$F$8,1,"") | CI74: =IF(BK74>='Conviction List'!$G$8,1,"") | CJ74: =SUM(CF74:CI74) -> 1 | CK74: =MATCH($D74,INDIRECT($C$90&"!$C$1:$C$164"),0) -> 76
B75: =B74+1 -> 73 | C75: VEM Technologies | D75: 0496525D | F75: =_xlfn.XLOOKUP(CCA_Defense!$D75,BB_Input!$C$4:$C$172,BB_Input!$G$4:$G$172) -> #N/A | G75: 2003 | H75: =YEAR(TODAY())-G75 -> 23 | I75: Unlisted | J75: Missile systems | N75: =IFERROR(_xlfn.XLOOKUP($D75,PE_Projections!$D:$D,PE_Projections!L:L),"") | O75: =IFERROR(_xlfn.XLOOKUP($D75,PE_Projections!$D:$D,PE_Projections!M:M),"") | P75: =IFERROR(_xlfn.XLOOKUP($D75,PE_Projections!$D:$D,PE_Projections!N:N),"") | Q75: =IFERROR(_xlfn.XLOOKUP($D75,PE_Projections!$D:$D,PE_Projections!O:O),"") | R75: =IFERROR(_xlfn.XLOOKUP($D75,PE_Projections!$D:$D,PE_Projections!P:P),"") | T75: =IFERROR(RATE(5,,BB75,-AY75),"") | Y75: Hyderabad | Z75: Private | AC75: High | AD75: High | AE75: High | AM75: Y | AU75: Tier 1 | CF75: =IF(CE75>='Conviction List'!$D$8,1,"") | CG75: =IF(M75<='Conviction List'!$E$8,1,"") -> 1 | CH75: =IF(BG75>='Conviction List'!$F$8,1,"") | CI75: =IF(BK75>='Conviction List'!$G$8,1,"") | CJ75: =SUM(CF75:CI75) -> 1 | CK75: =MATCH($D75,INDIRECT($C$90&"!$C$1:$C$164"),0) -> 77
B76: =B75+1 -> 74 | C76: Alpha Design Technologies | D76: 1606516D | F76: =_xlfn.XLOOKUP(CCA_Defense!$D76,BB_Input!$C$4:$C$172,BB_Input!$G$4:$G$172) -> #N/A | G76: 2001 | H76: =YEAR(TODAY())-G76 -> 25 | I76: Unlisted | J76: Electro-optics | N76: =IFERROR(_xlfn.XLOOKUP($D76,PE_Projections!$D:$D,PE_Projections!L:L),"") | O76: =IFERROR(_xlfn.XLOOKUP($D76,PE_Projections!$D:$D,PE_Projections!M:M),"") | P76: =IFERROR(_xlfn.XLOOKUP($D76,PE_Projections!$D:$D,PE_Projections!N:N),"") | Q76: =IFERROR(_xlfn.XLOOKUP($D76,PE_Projections!$D:$D,PE_Projections!O:O),"") | R76: =IFERROR(_xlfn.XLOOKUP($D76,PE_Projections!$D:$D,PE_Projections!P:P),"") | T76: =IFERROR(RATE(5,,BB76,-AY76),"") | W76: 4.2 | Y76: Bangalore | Z76: Private | AC76: High | AD76: High | AE76: High | AQ76: Y | AU76: Tier 3 | AY76: 125 | CF76: =IF(CE76>='Conviction List'!$D$8,1,"") | CG76: =IF(M76<='Conviction List'!$E$8,1,"") -> 1 | CH76: =IF(BG76>='Conviction List'!$F$8,1,"") | CI76: =IF(BK76>='Conviction List'!$G$8,1,"") | CJ76: =SUM(CF76:CI76) -> 1 | CK76: =MATCH($D76,INDIRECT($C$90&"!$C$1:$C$164"),0) -> 78
B77: =B76+1 -> 75 | C77: Unimech Aerospace & Manufacturing Ltd | D77: UNIMECH | E77: UNIMECH | F77: =_xlfn.XLOOKUP(CCA_Defense!$D77,BB_Input!$C$4:$C$172,BB_Input!$G$4:$G$172) -> 528.31031 | G77: 1991 | H77: =YEAR(TODAY())-G77 -> 35 | I77: Listed | J77: Aero machining | L77: Yes | M77: 64 | N77: =IFERROR(_xlfn.XLOOKUP($D77,PE_Projections!$D:$D,PE_Projections!L:L),"") -> 68.982587 | O77: =IFERROR(_xlfn.XLOOKUP($D77,PE_Projections!$D:$D,PE_Projections!M:M),"") -> 40.407863 | P77: =IFERROR(_xlfn.XLOOKUP($D77,PE_Projections!$D:$D,PE_Projections!N:N),"") -> 23.669674 | Q77: =IFERROR(_xlfn.XLOOKUP($D77,PE_Projections!$D:$D,PE_Projections!O:O),"") -> 13.864962 | R77: =IFERROR(_xlfn.XLOOKUP($D77,PE_Projections!$D:$D,PE_Projections!P:P),"") -> 8.1216651 | T77: =IFERROR(RATE(5,,BB77,-AY77),"") -> 0.70715754 | U77: =(35%+40%)/2 -> 0.375 | V77: =AVERAGE(60%,70%) -> 0.65 | X77: {=_xlfn.IFS($F77<Glossary!$C$54,Glossary!$B$54,$F77<Glossary!$C$55,Glossary!$B$55,$F77>Glossary!$C$56,Glossary!$B$56)} -> Small Cap | Y77: Bangalore | Z77: Private | AA77: 0.7982 | AB77: ValueQuest, 2.9% | AC77: High | AD77: High | AE77: High | AP77: Y | AQ77: Y | AR77: Y | AT77: Y | AU77: Diversified | AY77: 58 | AZ77: 24 | BA77: 11 | BB77: 4 | BC77: 56.3 | BD77: 40 | BG77: 0.238 | BH77: 0.544 | BI77: 0.309 | BJ77: 0.123 | BK77: 0.2147 | BL77: 0.467 | BM77: 0.309 | BN77: 0.122 | BS77: 0.11 | BT77: 0.23 | BU77: 0.2 | CE77: =IFERROR(RATE(4,,BB77,-AY77),"") -> 0.95138068 | CF77: =IF(CE77>='Conviction List'!$D$4,1,"") -> 1 | CG77: =IF(M75<='Conviction List'!$E$4,1,"") -> 1 | CH77: =IF(BG77>='Conviction List'!$F$4,1,"") -> 1 | CI77: =IF(BK77>='Conviction List'!$G$4,1,"") -> 1 | CJ77: =SUM(CF77:CI77) -> 4 | CK77: =MATCH($D77,INDIRECT($C$90&"!$C$1:$C$164"),0) -> 24
B78: =B77+1 -> 76 | C78: Techera Engineering | D78: TECHERA | E78: TECHERA | F78: =_xlfn.XLOOKUP(CCA_Defense!$D78,BB_Input!$C$4:$C$172,BB_Input!$G$4:$G$172) -> 40.354108 | G78: 2012 | H78: =YEAR(TODAY())-G78 -> 14 | I78: Listed | J78: Precision machining | M78: 107 | N78: =IFERROR(_xlfn.XLOOKUP($D78,PE_Projections!$D:$D,PE_Projections!L:L),"") -> 72.40895 | O78: =IFERROR(_xlfn.XLOOKUP($D78,PE_Projections!$D:$D,PE_Projections!M:M),"") -> 46.848027 | P78: =IFERROR(_xlfn.XLOOKUP($D78,PE_Projections!$D:$D,PE_Projections!N:N),"") -> 30.310309 | Q78: =IFERROR(_xlfn.XLOOKUP($D78,PE_Projections!$D:$D,PE_Projections!O:O),"") -> 19.610534 | R78: =IFERROR(_xlfn.XLOOKUP($D78,PE_Projections!$D:$D,PE_Projections!P:P),"") -> 12.687863 | S78: 28 | T78: =IFERROR(RATE(5,,BB78,-AY78),"") -> 0.48616696 | V78: 0.575 | W78: 2.3 | X78: {=_xlfn.IFS($F78<Glossary!$C$54,Glossary!$B$54,$F78<Glossary!$C$55,Glossary!$B$55,$F78>Glossary!$C$56,Glossary!$B$56)} -> Small Cap | Y78: Pune | Z78: Family | AA78: 0.4245 | AC78: High | AD78: Medium | AE78: Medium | AT78: Y | AU78: Tier 4 | AV78: =16520925/10^6 -> 16.520925 | AW78: =12143325/10^6 -> 12.143325 | AX78: =13382257/10^6 -> 13.382257 | AY78: 5.8 | AZ78: 4.55 | BA78: 3.1 | BB78: 0.8 | CF78: =IF(CE78>='Conviction List'!$D$8,1,"") | CG78: =IF(M78<='Conviction List'!$E$8,1,"") | CH78: =IF(BG78>='Conviction List'!$F$8,1,"") | CI78: =IF(BK78>='Conviction List'!$G$8,1,"") | CJ78: =SUM(CF78:CI78) -> 0 | CK78: =MATCH($D78,INDIRECT($C$90&"!$C$1:$C$164"),0) -> 80
B79: =B78+1 -> 77 | C79: PTC Industries | D79: PTCIL | E79: PTCIL | F79: =_xlfn.XLOOKUP(CCA_Defense!$D79,BB_Input!$C$4:$C$172,BB_Input!$G$4:$G$172) -> 3055.6101 | G79: 1963 | H79: =YEAR(TODAY())-G79 -> 63 | I79: Listed | J79: Critical metal components | M79: 396 | N79: =IFERROR(_xlfn.XLOOKUP($D79,PE_Projections!$D:$D,PE_Projections!L:L),"") -> 282.73659 | O79: =IFERROR(_xlfn.XLOOKUP($D79,PE_Projections!$D:$D,PE_Projections!M:M),"") -> 109.57991 | P79: =IFERROR(_xlfn.XLOOKUP($D79,PE_Projections!$D:$D,PE_Projections!N:N),"") -> 40.911531 | Q79: =IFERROR(_xlfn.XLOOKUP($D79,PE_Projections!$D:$D,PE_Projections!O:O),"") -> 23.174123 | R79: =IFERROR(_xlfn.XLOOKUP($D79,PE_Projections!$D:$D,PE_Projections!P:P),"") | S79: 54 | T79: =IFERROR(RATE(5,,BB79,-AY79),"") -> 0.1145288 | V79: ~30% | X79: {=_xlfn.IFS($F79<Glossary!$C$54,Glossary!$B$54,$F79<Glossary!$C$55,Glossary!$B$55,$F79>Glossary!$C$56,Glossary!$B$56)} -> Mid Cap | Y79: New Delhi | Z79: Family | AA79: 0.5975 | AC79: High | AD79: High | AE79: High | AS79: Y | AU79: Tier 4 | AV79: =14984126/10^6 -> 14.984126 | AW79: =14440873/10^6 -> 14.440873 | AX79: =13382257/10^6 -> 13.382257 | AY79: 36.2 | AZ79: 30.22 | BA79: 25.8 | BB79: 21.05 | BC79: 303 | BD79: 169 | BE79: 55.3 | BF79: 63.8 | BG79: 0.026 | BH79: 0.038 | BI79: 0.067 | BJ79: 0.057 | BK79: 0.0407 | BL79: 0.0676 | BM79: 0.1085 | BN79: 0.1051 | CF79: =IF(CE79>='Conviction List'!$D$8,1,"") | CG79: =IF(M79<='Conviction List'!$E$8,1,"") | CH79: =IF(BG79>='Conviction List'!$F$8,1,"") | CI79: =IF(BK79>='Conviction List'!$G$8,1,"") | CJ79: =SUM(CF79:CI79) -> 0 | CK79: =MATCH($D79,INDIRECT($C$90&"!$C$1:$C$164"),0) -> 81
B80: =B79+1 -> 78 | C80: Investment & Precision Castings (IPCL) | D80: IPC | E80: IPCL | F80: =_xlfn.XLOOKUP(CCA_Defense!$D80,BB_Input!$C$4:$C$172,BB_Input!$G$4:$G$172) -> 54.377921 | G80: 1984 | H80: =YEAR(TODAY())-G80 -> 42 | I80: Listed | J80: Critical metal components | M80: 68.9 | N80: =IFERROR(_xlfn.XLOOKUP($D80,PE_Projections!$D:$D,PE_Projections!L:L),"") | O80: =IFERROR(_xlfn.XLOOKUP($D80,PE_Projections!$D:$D,PE_Projections!M:M),"") | P80: =IFERROR(_xlfn.XLOOKUP($D80,PE_Projections!$D:$D,PE_Projections!N:N),"") | Q80: =IFERROR(_xlfn.XLOOKUP($D80,PE_Projections!$D:$D,PE_Projections!O:O),"") | R80: =IFERROR(_xlfn.XLOOKUP($D80,PE_Projections!$D:$D,PE_Projections!P:P),"") | S80: 2 | T80: =IFERROR(RATE(5,,BB80,-AY80),"") | V80: ~2% | X80: {=_xlfn.IFS($F80<Glossary!$C$54,Glossary!$B$54,$F80<Glossary!$C$55,Glossary!$B$55,$F80>Glossary!$C$56,Glossary!$B$56)} -> Small Cap | Y80: Gujarat | Z80: Family | AA80: 0.52 | AC80: High | AD80: Medium | AE80: Medium | AS80: Y | AU80: Tier 4 | CK80: =MATCH($D80,INDIRECT($C$90&"!$C$1:$C$164"),0) -> 82
B81: =B80+1 -> 79 | C81: Aequs | D81: AEQUS | E81: AEQUS | F81: =_xlfn.XLOOKUP(CCA_Defense!$D81,BB_Input!$C$4:$C$172,BB_Input!$G$4:$G$172) -> 1043.2745 | G81: 2001 | H81: =YEAR(TODAY())-G81 -> 25 | I81: Listed | AC81: High | AD81: High | AE81: High | CK81: =MATCH($D81,INDIRECT($C$90&"!$C$1:$C$164"),0) -> 83
B82: =B81+1 -> 80 | C82: SMPP | G82: 2017 | H82: =YEAR(TODAY())-G82 -> 9 | I82: Unlisted | AC82: High | AD82: High | AE82: High
B83: =B82+1 -> 81 | C83: JJG Aero | G83: 2010 | H83: =YEAR(TODAY())-G83 -> 16 | I83: Unlisted | AC83: High | AD83: High | AE83: High
B84: =B83+1 -> 82 | C84: Hikal | G84: 1988 | H84: =YEAR(TODAY())-G84 -> 38 | I84: Unlisted | AC84: High | AD84: Medium | AE84: Medium
D86: placeholders
C89: BBcolumn | F89: =MATCH(F90,INDIRECT($C$90&"!$C$3:$DF$3"),0) -> 5
C90: BB_Input | F90: cur_mkt_cap(currency=USD)/1000000

Sheet Conviction List
B2: Table 1: Average Performance Across the Value Chain
B3: Value Chain | C3: Count | D3: CAGR % (4-Yr) | E3: PE (x) | F3: ROE % FY24 | G3: ROCE % FY24 | I3: Mix (%)
B4: Diversified | C4: =COUNTIF(CCA_Defense!$AU:$AU,'Conviction List'!$B4) -> 18 | D4: =AVERAGEIFS(CCA_Defense!$CE:$CE,CCA_Defense!$AU:$AU,'Conviction List'!$B4) -> 0.21224544 | E4: =AVERAGEIFS(CCA_Defense!M:M,CCA_Defense!$AU:$AU,'Conviction List'!$B4) -> 73.6 | F4: =AVERAGEIFS(CCA_Defense!BG:BG,CCA_Defense!$AU:$AU,'Conviction List'!$B4) -> 0.13273846 | G4: =AVERAGEIFS(CCA_Defense!BK:BK,CCA_Defense!$AU:$AU,'Conviction List'!$B4) -> 0.17256923 | I4: =C4/$C$11 -> 0.23076923
B5: Platforms | C5: =COUNTIF(CCA_Defense!$AU:$AU,'Conviction List'!$B5) -> 10 | D5: =AVERAGEIFS(CCA_Defense!$CE:$CE,CCA_Defense!$AU:$AU,'Conviction List'!B5) -> 0.10412676 | E5: =AVERAGEIFS(CCA_Defense!M:M,CCA_Defense!$AU:$AU,'Conviction List'!$B5) -> 43.035 | F5: =AVERAGEIFS(CCA_Defense!BG:BG,CCA_Defense!$AU:$AU,'Conviction List'!$B5) -> 0.19255 | G5: =AVERAGEIFS(CCA_Defense!BK:BK,CCA_Defense!$AU:$AU,'Conviction List'!$B5) -> 0.19435 | I5: =C5/$C$11 -> 0.12820513
B6: Tier 1 | C6: =COUNTIF(CCA_Defense!$AU:$AU,'Conviction List'!$B6) -> 7 | D6: =AVERAGEIFS(CCA_Defense!$CE:$CE,CCA_Defense!$AU:$AU,'Conviction List'!B6) -> 0.052617025 | E6: =AVERAGEIFS(CCA_Defense!M:M,CCA_Defense!$AU:$AU,'Conviction List'!$B6) -> 64.85 | F6: =AVERAGEIFS(CCA_Defense!BG:BG,CCA_Defense!$AU:$AU,'Conviction List'!$B6) -> 0.11646 | G6: =AVERAGEIFS(CCA_Defense!BK:BK,CCA_Defense!$AU:$AU,'Conviction List'!$B6) -> 0.15384 | I6: =C6/$C$11 -> 0.08974359
B7: Tier 2 | C7: =COUNTIF(CCA_Defense!$AU:$AU,'Conviction List'!$B7) -> 9 | E7: =AVERAGEIFS(CCA_Defense!M:M,CCA_Defense!$AU:$AU,'Conviction List'!$B7) -> 77 | F7: =AVERAGEIFS(CCA_Defense!BG:BG,CCA_Defense!$AU:$AU,'Conviction List'!$B7) -> 0.12255 | G7: =IFERROR(AVERAGEIFS(CCA_Defense!BK:BK,CCA_Defense!$AU:$AU,'Conviction List'!$B7),"") -> 0.1688 | I7: =C7/$C$11 -> 0.11538462
B8: Tier 3 | C8: =COUNTIF(CCA_Defense!$AU:$AU,'Conviction List'!$B8) -> 25 | D8: =AVERAGEIFS(CCA_Defense!$CE:$CE,CCA_Defense!$AU:$AU,'Conviction List'!B8) -> 0.31076718 | E8: =AVERAGEIFS(CCA_Defense!M:M,CCA_Defense!$AU:$AU,'Conviction List'!$B8) -> 84.1575 | F8: =AVERAGEIFS(CCA_Defense!BG:BG,CCA_Defense!$AU:$AU,'Conviction List'!$B8) -> 0.14373636 | G8: =AVERAGEIFS(CCA_Defense!BK:BK,CCA_Defense!$AU:$AU,'Conviction List'!$B8) -> 0.2442 | I8: =C8/$C$11 -> 0.32051282
B9: Tier 4 | C9: =COUNTIF(CCA_Defense!$AU:$AU,'Conviction List'!$B9) -> 9 | D9: =AVERAGEIFS(CCA_Defense!$CE:$CE,CCA_Defense!$AU:$AU,'Conviction List'!B9) -> 0.40220922 | E9: =AVERAGEIFS(CCA_Defense!M:M,CCA_Defense!$AU:$AU,'Conviction List'!$B9) -> 174.42625 | F9: =AVERAGEIFS(CCA_Defense!BG:BG,CCA_Defense!$AU:$AU,'Conviction List'!$B9) -> 0.08558 | G9: =AVERAGEIFS(CCA_Defense!BK:BK,CCA_Defense!$AU:$AU,'Conviction List'!$B9) -> 0.061 | I9: =C9/$C$11 -> 0.11538462
B11: Defence & Aerospace | C11: =SUM(C4:C9) -> 78 | D11: =SUMPRODUCT($I$4:$I$9,D4:D9) -> 0.21306496 | E11: =SUMPRODUCT($I$4:$I$9,E4:E9) -> 84.306074 | F11: =SUMPRODUCT($I$4:$I$9,F4:F9) -> 0.13585374 | G11: =SUMPRODUCT($I$4:$I$9,G4:G9) -> 0.1833311
B13: Table 2: Top Performer Across the Value Chain
B14: Value Chain | C14: Company | D14: CAGR % (4-Yr) | E14: PE (x) | F14: ROE % FY24 | G14: ROCE % FY24
B15: Diversified | C15: Hindustan Aeronautics Limited | D15: 0.092897728 | E15: 39.65 | F15: 0.289 | G15: 0.35
B16: Platforms | C16: Cochin Shipyard Limited | D16: 0.19816226 | E16: 48.8 | F16: 0.16 | G16: 0.22
B17: Tier 1 | C17: Bharat Dynamics Limited | D17: 0.078543953 | E17: 61.75 | F17: 0.15 | G17: 0.155
B18: Tier 2 | C18: Premier Explosives Ltd | D18: 0.21546923 | E18: 77 | F18: 0.128 | G18: 0
B19: Tier 3 | C19: Zen Technologies | D19: 0.52106621 | E19: 61 | F19: 0.269 | G19: 0.33
B20: Tier 4 | C20: Azad Engineering | D20: 0.24 | E20: 108 | G20: 0.22
B22: Table 3: Above Average Performers
B23: Value Chain | C23: Company | D23: CAGR % (4-Yr) | E23: PE (x) | F23: ROE % FY24 | G23: ROCE % FY24
B24: =_xlfn.XLOOKUP($C24,CCA_Defense!$C:$C,CCA_Defense!$AU:$AU) -> Diversified | C24: Hindustan Aeronautics Limited | D24: =_xlfn.XLOOKUP($C24,CCA_Defense!$C:$C,CCA_Defense!CE:CE) -> 0.092897728 | E24: =_xlfn.XLOOKUP($C24,CCA_Defense!$C:$C,CCA_Defense!M:M) -> 39.65 | F24: =_xlfn.XLOOKUP($C24,CCA_Defense!$C:$C,CCA_Defense!BG:BG) -> 0.267 | G24: =_xlfn.XLOOKUP($C24,CCA_Defense!$C:$C,CCA_Defense!BK:BK) -> 0.338
B25: =_xlfn.XLOOKUP($C25,CCA_Defense!$C:$C,CCA_Defense!$AU:$AU) -> Tier 1 | C25: Bharat Dynamics Limited | D25: =_xlfn.XLOOKUP($C25,CCA_Defense!$C:$C,CCA_Defense!CE:CE) -> 0.078543953 | E25: =_xlfn.XLOOKUP($C25,CCA_Defense!$C:$C,CCA_Defense!M:M) -> 61.75 | F25: =_xlfn.XLOOKUP($C25,CCA_Defense!$C:$C,CCA_Defense!BG:BG) -> 0.1438 | G25: =_xlfn.XLOOKUP($C25,CCA_Defense!$C:$C,CCA_Defense!BK:BK) -> 0.1965
B26: =_xlfn.XLOOKUP($C26,CCA_Defense!$C:$C,CCA_Defense!$AU:$AU) -> Platforms | C26: Cochin Shipyard Limited | D26: =_xlfn.XLOOKUP($C26,CCA_Defense!$C:$C,CCA_Defense!CE:CE) -> 0.19816226 | E26: =_xlfn.XLOOKUP($C26,CCA_Defense!$C:$C,CCA_Defense!M:M) -> 48.8 | F26: =_xlfn.XLOOKUP($C26,CCA_Defense!$C:$C,CCA_Defense!BG:BG) -> 0 | G26: =_xlfn.XLOOKUP($C26,CCA_Defense!$C:$C,CCA_Defense!BK:BK) -> 0
B27: =_xlfn.XLOOKUP($C27,CCA_Defense!$C:$C,CCA_Defense!$AU:$AU) -> Tier 3 | C27: Zen Technologies | D27: =_xlfn.XLOOKUP($C27,CCA_Defense!$C:$C,CCA_Defense!CE:CE) -> 0.52106621 | E27: =_xlfn.XLOOKUP($C27,CCA_Defense!$C:$C,CCA_Defense!M:M) -> 61 | F27: =_xlfn.XLOOKUP($C27,CCA_Defense!$C:$C,CCA_Defense!BG:BG) -> 0.2608 | G27: =_xlfn.XLOOKUP($C27,CCA_Defense!$C:$C,CCA_Defense!BK:BK) -> 0.3671
B28: =_xlfn.XLOOKUP($C28,CCA_Defense!$C:$C,CCA_Defense!$AU:$AU) -> Diversified | C28: Unimech Aerospace & Manufacturing Ltd | D28: =_xlfn.XLOOKUP($C28,CCA_Defense!$C:$C,CCA_Defense!CE:CE) -> 0.95138068 | E28: =_xlfn.XLOOKUP($C28,CCA_Defense!$C:$C,CCA_Defense!M:M) -> 64 | F28: =_xlfn.XLOOKUP($C28,CCA_Defense!$C:$C,CCA_Defense!BG:BG) -> 0.238 | G28: =_xlfn.XLOOKUP($C28,CCA_Defense!$C:$C,CCA_Defense!BK:BK) -> 0.2147
B29: =_xlfn.XLOOKUP($C29,CCA_Defense!$C:$C,CCA_Defense!$AU:$AU) -> Diversified | C29: IdeaForge Technology Ltd | D29: =_xlfn.XLOOKUP($C29,CCA_Defense!$C:$C,CCA_Defense!CE:CE) -> 0.32180868 | E29: =_xlfn.XLOOKUP($C29,CCA_Defense!$C:$C,CCA_Defense!M:M) -> 0 | F29: =_xlfn.XLOOKUP($C29,CCA_Defense!$C:$C,CCA_Defense!BG:BG) -> -0.098 | G29: =_xlfn.XLOOKUP($C29,CCA_Defense!$C:$C,CCA_Defense!BK:BK) -> -0.0936
B30: =_xlfn.XLOOKUP($C30,CCA_Defense!$C:$C,CCA_Defense!$AU:$AU) -> Tier 2 | C30: Premier Explosives Ltd | D30: =_xlfn.XLOOKUP($C30,CCA_Defense!$C:$C,CCA_Defense!CE:CE) -> 0.21546923 | E30: =_xlfn.XLOOKUP($C30,CCA_Defense!$C:$C,CCA_Defense!M:M) -> 77 | F30: =_xlfn.XLOOKUP($C30,CCA_Defense!$C:$C,CCA_Defense!BG:BG) -> 0.12255 | G30: =_xlfn.XLOOKUP($C30,CCA_Defense!$C:$C,CCA_Defense!BK:BK) -> 0.1688
B31: =_xlfn.XLOOKUP($C31,CCA_Defense!$C:$C,CCA_Defense!$AU:$AU) -> Tier 3 | C31: HBL Power Systems Ltd | D31: =_xlfn.XLOOKUP($C31,CCA_Defense!$C:$C,CCA_Defense!CE:CE) -> 0.14325512 | E31: =_xlfn.XLOOKUP($C31,CCA_Defense!$C:$C,CCA_Defense!M:M) -> 43 | F31: =_xlfn.XLOOKUP($C31,CCA_Defense!$C:$C,CCA_Defense!BG:BG) -> 0 | G31: =_xlfn.XLOOKUP($C31,CCA_Defense!$C:$C,CCA_Defense!BK:BK) -> 0
B35: Parameters | C35: High Attractiveness | D35: Medium Attractiveness | E35: Low Attractiveness
B36: Financial Ratios:
B37: CAGR % (4-Yr) | C37: >25% | D37: <20% | E37: <10%
B38: PE (x) | C38: <30 | D38: 30-50 | E38: >50
B39: ROE (%) | C39: >18% | D39: 12% to 18% | E39: <12%
B40: ROCE (%) | C40: >20% | D40: 14% to 20% | E40: <14%
B41: Debt to Equity Ratio | C41: <0.4 | D41: 0.4 to 1.0 | E41: >1.0
B42: Orderbook Visibility | C42: >3 | D42: 1.5 to 3 | E42: <1.5
B43: Qualitative Factors
B44: Legacy | C44: >25 | D44: 10 to 25 | E44: <10
B45: Promoter Holding (%) | C45: >70% | D45: 40% to 70% | E45: <40%
B46: TAM Growth | C46: >15% | D46: 8% to 10% | E46: <8%
B47: Regulatory Environment | C47: Tailwinds: localisation push, higher defence budgets, export relaxations, offset policies favouring local players. | D47: Neutral: some policy support but also periodic procurement freezes or bureaucracy. | E47: Persistent policy uncertainty, sanctions risk, adverse offset/tax changes, frequent tender cancellations.
B48: Barriers to Entry | C48: Proprietary IP, export controls, deep integration into platforms, unique certifications, long qualification & testing cycles. | D48: Some IP and process know-how; new entrants possible but slow. | E48: Build-to-print components, easily substitutable, low technical complexity.
B49: Switching Costs | C49: Safety-critical or mission-critical systems; switching requires full recertification and re-qualification; significant retraining and integration. | D49: Non-critical subsystems but embedded in designs; switching possible but painful. | E49: Off-the-shelf components; customers dual-source and switch frequently.
B50: Customer Stickiness / Contract | C50: Long-term, often sole-source contracts; “life-of-platform” support; clear indexation clauses for inflation and FX. | D50: Multi-year but rebid regularly; incumbency advantage but not guaranteed. | E50: Short-term, price-only tenders; frequent rebids.
B51: Customer Concentration | C51: <10% | D51: 10% to 40% | E51: >40%

Sheet Financial Summary
D1: Ticker | G1: P/E | M1: Derived | N1: Mgmt Input | O1: Revenue (INR Mn)
B2: # | C2: Company | D2: BB | E2: Exch | F2: Mkt cap $mm | G2: Current | H2: FY26P | I2: FY27P | J2: FY28P | K2: FY29P | L2: FY30P | M2: Revenue CAGR (5-Yr) (%) | O2: Current | P2: FY26P | Q2: FY27P | R2: FY28P | S2: FY29P | T2: FY30P
B3: 1 | C3: Hindustan Aeronautics Limited | D3: HNAL | E3: HAL | F3: =_xlfn.XLOOKUP($D3,BB_Input!$C$4:$C$172,BB_Input!$G$4:$G$172) -> 32941.531 | G3: =_xlfn.XLOOKUP($D3,CCA_Defense!$D:$D,CCA_Defense!M:M) -> 39.65 | H3: =_xlfn.XLOOKUP($D3,CCA_Defense!$D:$D,CCA_Defense!N:N) -> 34.750906 | I3: =_xlfn.XLOOKUP($D3,CCA_Defense!$D:$D,CCA_Defense!O:O) -> 29.185423 | J3: =_xlfn.XLOOKUP($D3,CCA_Defense!$D:$D,CCA_Defense!P:P) -> 25.131017 | K3: =_xlfn.XLOOKUP($D3,CCA_Defense!$D:$D,CCA_Defense!Q:Q) -> 21.546295 | L3: =_xlfn.XLOOKUP($D3,CCA_Defense!$D:$D,CCA_Defense!R:R) | M3: =_xlfn.XLOOKUP($D3,CCA_Defense!$D:$D,CCA_Defense!T:T) -> 0.073652201 | N3: =_xlfn.XLOOKUP($D3,CCA_Defense!$D:$D,CCA_Defense!U:U) -> 0 | O3: =IFERROR(_xlfn.XLOOKUP($D3,BB_Input!$C$4:$C$163,BB_Input!$CY$4:$CY$163),"") -> 309809.5 | P3: =IFERROR(O3*(1+$M3),"") -> 332627.65 | Q3: =IFERROR(P3*(1+$M3),"") -> 357126.41 | R3: =IFERROR(Q3*(1+$M3),"") -> 383429.56 | S3: =IFERROR(R3*(1+$M3),"") -> 411669.99 | T3: =IFERROR(S3*(1+$M3),"") -> 441990.39
B4: =B3+1 -> 2 | C4: Bharat Electronics Limited | D4: BHE | E4: BEL | F4: =_xlfn.XLOOKUP($D4,BB_Input!$C$4:$C$172,BB_Input!$G$4:$G$172) -> 32574.519 | G4: =_xlfn.XLOOKUP($D4,CCA_Defense!$D:$D,CCA_Defense!M:M) -> 61.39 | H4: =_xlfn.XLOOKUP($D4,CCA_Defense!$D:$D,CCA_Defense!N:N) -> 48.548221 | I4: =_xlfn.XLOOKUP($D4,CCA_Defense!$D:$D,CCA_Defense!O:O) -> 40.935212 | J4: =_xlfn.XLOOKUP($D4,CCA_Defense!$D:$D,CCA_Defense!P:P) -> 34.951751 | K4: =_xlfn.XLOOKUP($D4,CCA_Defense!$D:$D,CCA_Defense!Q:Q) -> 31.397174 | L4: =_xlfn.XLOOKUP($D4,CCA_Defense!$D:$D,CCA_Defense!R:R) | M4: =_xlfn.XLOOKUP($D4,CCA_Defense!$D:$D,CCA_Defense!T:T) -> 0.069230988 | N4: =_xlfn.XLOOKUP($D4,CCA_Defense!$D:$D,CCA_Defense!U:U) -> 0 | O4: =IFERROR(_xlfn.XLOOKUP($D4,BB_Input!$C$4:$C$163,BB_Input!$CY$4:$CY$163),"") -> 230241 | P4: =IFERROR(O4*(1+$M4),"") -> 246180.81 | Q4: =IFERROR(P4*(1+$M4),"") -> 263224.15 | R4: =IFERROR(Q4*(1+$M4),"") -> 281447.42 | S4: =IFERROR(R4*(1+$M4),"") -> 300932.3 | T4: =IFERROR(S4*(1+$M4),"") -> 321766.14
B5: =B4+1 -> 3 | C5: Bharat Dynamics Limited | D5: BDL | E5: BDL | F5: =_xlfn.XLOOKUP($D5,BB_Input!$C$4:$C$172,BB_Input!$G$4:$G$172) -> 6048.8875 | G5: =_xlfn.XLOOKUP($D5,CCA_Defense!$D:$D,CCA_Defense!M:M) -> 61.75 | H5: =_xlfn.XLOOKUP($D5,CCA_Defense!$D:$D,CCA_Defense!N:N) -> 58.607226 | I5: =_xlfn.XLOOKUP($D5,CCA_Defense!$D:$D,CCA_Defense!O:O) -> 44.206127 | J5: =_xlfn.XLOOKUP($D5,CCA_Defense!$D:$D,CCA_Defense!P:P) -> 34.064669 | K5: =_xlfn.XLOOKUP($D5,CCA_Defense!$D:$D,CCA_Defense!Q:Q) -> 39.967619 | L5: =_xlfn.XLOOKUP($D5,CCA_Defense!$D:$D,CCA_Defense!R:R) | M5: =_xlfn.XLOOKUP($D5,CCA_Defense!$D:$D,CCA_Defense!T:T) -> 0.062356498 | N5: =_xlfn.XLOOKUP($D5,CCA_Defense!$D:$D,CCA_Defense!U:U) -> 0 | O5: =IFERROR(_xlfn.XLOOKUP($D5,BB_Input!$C$4:$C$163,BB_Input!$CY$4:$CY$163),"") -> 33230.729 | P5: =IFERROR(O5*(1+$M5),"") -> 35302.881 | Q5: =IFERROR(P5*(1+$M5),"") -> 37504.245 | R5: =IFERROR(Q5*(1+$M5),"") -> 39842.878 | S5: =IFERROR(R5*(1+$M5),"") -> 42327.341 | T5: =IFERROR(S5*(1+$M5),"") -> 44966.725
B6: =B5+1 -> 4 | C6: Mazagon Dock Shipbuilders Limited | D6: MAZDOCKS | E6: MAZDOCK | F6: =_xlfn.XLOOKUP($D6,BB_Input!$C$4:$C$172,BB_Input!$G$4:$G$172) -> 11415.979 | G6: =_xlfn.XLOOKUP($D6,CCA_Defense!$D:$D,CCA_Defense!M:M) -> 38.06 | H6: =_xlfn.XLOOKUP($D6,CCA_Defense!$D:$D,CCA_Defense!N:N) -> 37.053118 | I6: =_xlfn.XLOOKUP($D6,CCA_Defense!$D:$D,CCA_Defense!O:O) -> 30.396666 | J6: =_xlfn.XLOOKUP($D6,CCA_Defense!$D:$D,CCA_Defense!P:P) -> 28.26324 | K6: =_xlfn.XLOOKUP($D6,CCA_Defense!$D:$D,CCA_Defense!Q:Q) | L6: =_xlfn.XLOOKUP($D6,CCA_Defense!$D:$D,CCA_Defense!R:R) | M6: =_xlfn.XLOOKUP($D6,CCA_Defense!$D:$D,CCA_Defense!T:T) -> 0.047036671 | N6: =_xlfn.XLOOKUP($D6,CCA_Defense!$D:$D,CCA_Defense!U:U) -> 0 | O6: =IFERROR(_xlfn.XLOOKUP($D6,BB_Input!$C$4:$C$163,BB_Input!$CY$4:$CY$163),"") -> 114318.8 | P6: =IFERROR(O6*(1+$M6),"") -> 119695.98 | Q6: =IFERROR(P6*(1+$M6),"") -> 125326.08 | R6: =IFERROR(Q6*(1+$M6),"") -> 131221 | S6: =IFERROR(R6*(1+$M6),"") -> 137393.2 | T6: =IFERROR(S6*(1+$M6),"") -> 143855.71
B7: =B6+1 -> 5 | C7: Garden Reach Shipbuilders & Engineers | D7: GRSE | E7: GRSE | F7: =_xlfn.XLOOKUP($D7,BB_Input!$C$4:$C$172,BB_Input!$G$4:$G$172) -> 3131.5232 | G7: =_xlfn.XLOOKUP($D7,CCA_Defense!$D:$D,CCA_Defense!M:M) -> 88.75 | H7: =_xlfn.XLOOKUP($D7,CCA_Defense!$D:$D,CCA_Defense!N:N) -> 38.480116 | I7: =_xlfn.XLOOKUP($D7,CCA_Defense!$D:$D,CCA_Defense!O:O) -> 28.728985 | J7: =_xlfn.XLOOKUP($D7,CCA_Defense!$D:$D,CCA_Defense!P:P) -> 26.557715 | K7: =_xlfn.XLOOKUP($D7,CCA_Defense!$D:$D,CCA_Defense!Q:Q) | L7: =_xlfn.XLOOKUP($D7,CCA_Defense!$D:$D,CCA_Defense!R:R) | M7: =_xlfn.XLOOKUP($D7,CCA_Defense!$D:$D,CCA_Defense!T:T) -> 0.043826858 | N7: =_xlfn.XLOOKUP($D7,CCA_Defense!$D:$D,CCA_Defense!U:U) -> 0 | O7: =IFERROR(_xlfn.XLOOKUP($D7,BB_Input!$C$4:$C$163,BB_Input!$CY$4:$CY$163),"") -> 50756.877 | P7: =IFERROR(O7*(1+$M7),"") -> 52981.391 | Q7: =IFERROR(P7*(1+$M7),"") -> 55303.399 | R7: =IFERROR(Q7*(1+$M7),"") -> 57727.174 | S7: =IFERROR(R7*(1+$M7),"") -> 60257.174 | T7: =IFERROR(S7*(1+$M7),"") -> 62898.057
B8: =B7+1 -> 6 | C8: Cochin Shipyard Limited | D8: COCHIN | E8: COCHINSHIP | F8: =_xlfn.XLOOKUP($D8,BB_Input!$C$4:$C$172,BB_Input!$G$4:$G$172) -> 4833.9547 | G8: =_xlfn.XLOOKUP($D8,CCA_Defense!$D:$D,CCA_Defense!M:M) -> 48.8 | H8: =_xlfn.XLOOKUP($D8,CCA_Defense!$D:$D,CCA_Defense!N:N) -> 59.974547 | I8: =_xlfn.XLOOKUP($D8,CCA_Defense!$D:$D,CCA_Defense!O:O) -> 45.560775 | J8: =_xlfn.XLOOKUP($D8,CCA_Defense!$D:$D,CCA_Defense!P:P) -> 37.626617 | K8: =_xlfn.XLOOKUP($D8,CCA_Defense!$D:$D,CCA_Defense!Q:Q) | L8: =_xlfn.XLOOKUP($D8,CCA_Defense!$D:$D,CCA_Defense!R:R) | M8: =_xlfn.XLOOKUP($D8,CCA_Defense!$D:$D,CCA_Defense!T:T) -> 0.15561324 | N8: =_xlfn.XLOOKUP($D8,CCA_Defense!$D:$D,CCA_Defense!U:U) -> 0 | O8: =IFERROR(_xlfn.XLOOKUP($D8,BB_Input!$C$4:$C$163,BB_Input!$CY$4:$CY$163),"") -> 48199.588 | P8: =IFERROR(O8*(1+$M8),"") -> 55700.082 | Q8: =IFERROR(P8*(1+$M8),"") -> 64367.752 | R8: =IFERROR(Q8*(1+$M8),"") -> 74384.226 | S8: =IFERROR(R8*(1+$M8),"") -> 85959.396 | T8: =IFERROR(S8*(1+$M8),"") -> 99335.816
B9: =B8+1 -> 7 | C9: BEML Limited | D9: BEML | E9: BEML | F9: =_xlfn.XLOOKUP($D9,BB_Input!$C$4:$C$172,BB_Input!$G$4:$G$172) -> 1733.2255 | G9: =_xlfn.XLOOKUP($D9,CCA_Defense!$D:$D,CCA_Defense!M:M) -> 59.41 | H9: =_xlfn.XLOOKUP($D9,CCA_Defense!$D:$D,CCA_Defense!N:N) -> 38.8041 | I9: =_xlfn.XLOOKUP($D9,CCA_Defense!$D:$D,CCA_Defense!O:O) -> 27.780973 | J9: =_xlfn.XLOOKUP($D9,CCA_Defense!$D:$D,CCA_Defense!P:P) -> 22.834964 | K9: =_xlfn.XLOOKUP($D9,CCA_Defense!$D:$D,CCA_Defense!Q:Q) | L9: =_xlfn.XLOOKUP($D9,CCA_Defense!$D:$D,CCA_Defense!R:R) | M9: =_xlfn.XLOOKUP($D9,CCA_Defense!$D:$D,CCA_Defense!T:T) -> 0.051918152 | N9: =_xlfn.XLOOKUP($D9,CCA_Defense!$D:$D,CCA_Defense!U:U) -> 0 | O9: =IFERROR(_xlfn.XLOOKUP($D9,BB_Input!$C$4:$C$163,BB_Input!$CY$4:$CY$163),"") -> 40222.227 | P9: =IFERROR(O9*(1+$M9),"") -> 42310.491 | Q9: =IFERROR(P9*(1+$M9),"") -> 44507.173 | R9: =IFERROR(Q9*(1+$M9),"") -> 46817.903 | S9: =IFERROR(R9*(1+$M9),"") -> 49248.602 | T9: =IFERROR(S9*(1+$M9),"") -> 51805.499
B10: =B9+1 -> 8 | C10: Mishra Dhatu Nigam Limited (MIDHANI) | D10: MIDHANI | E10: MIDHANI | F10: =_xlfn.XLOOKUP($D10,BB_Input!$C$4:$C$172,BB_Input!$G$4:$G$172) -> 649.82016 | G10: =_xlfn.XLOOKUP($D10,CCA_Defense!$D:$D,CCA_Defense!M:M) -> 73.81 | H10: =_xlfn.XLOOKUP($D10,CCA_Defense!$D:$D,CCA_Defense!N:N) -> 39.336703 | I10: =_xlfn.XLOOKUP($D10,CCA_Defense!$D:$D,CCA_Defense!O:O) -> 30.554466 | J10: =_xlfn.XLOOKUP($D10,CCA_Defense!$D:$D,CCA_Defense!P:P) -> 24.070352 | K10: =_xlfn.XLOOKUP($D10,CCA_Defense!$D:$D,CCA_Defense!Q:Q) | L10: =_xlfn.XLOOKUP($D10,CCA_Defense!$D:$D,CCA_Defense!R:R) | M10: =_xlfn.XLOOKUP($D10,CCA_Defense!$D:$D,CCA_Defense!T:T) -> 0.053940666 | N10: =_xlfn.XLOOKUP($D10,CCA_Defense!$D:$D,CCA_Defense!U:U) -> 0 | O10: =IFERROR(_xlfn.XLOOKUP($D10,BB_Input!$C$4:$C$163,BB_Input!$CY$4:$CY$163),"") -> 10527.857 | P10: =IFERROR(O10*(1+$M10),"") -> 11095.737 | Q10: =IFERROR(P10*(1+$M10),"") -> 11694.248 | R10: =IFERROR(Q10*(1+$M10),"") -> 12325.044 | S10: =IFERROR(R10*(1+$M10),"") -> 12989.865 | T10: =IFERROR(S10*(1+$M10),"") -> 13690.547
B11: =B10+1 -> 9 | C11: Data Patterns | D11: DATAPATT | E11: DATAPATT | F11: =_xlfn.XLOOKUP($D11,BB_Input!$C$4:$C$172,BB_Input!$G$4:$G$172) -> 1666.7202 | G11: =_xlfn.XLOOKUP($D11,CCA_Defense!$D:$D,CCA_Defense!M:M) -> 0 | H11: =_xlfn.XLOOKUP($D11,CCA_Defense!$D:$D,CCA_Defense!N:N) -> 48.318593 | I11: =_xlfn.XLOOKUP($D11,CCA_Defense!$D:$D,CCA_Defense!O:O) -> 38.101025 | J11: =_xlfn.XLOOKUP($D11,CCA_Defense!$D:$D,CCA_Defense!P:P) -> 29.124123 | K11: =_xlfn.XLOOKUP($D11,CCA_Defense!$D:$D,CCA_Defense!Q:Q) -> 23.970579 | L11: =_xlfn.XLOOKUP($D11,CCA_Defense!$D:$D,CCA_Defense!R:R) | M11: =_xlfn.XLOOKUP($D11,CCA_Defense!$D:$D,CCA_Defense!T:T) -> 0.19573801 | N11: =_xlfn.XLOOKUP($D11,CCA_Defense!$D:$D,CCA_Defense!U:U) -> 0 | O11: =IFERROR(_xlfn.XLOOKUP($D11,BB_Input!$C$4:$C$163,BB_Input!$CY$4:$CY$163),"") -> 7083.5 | P11: =IFERROR(O11*(1+$M11),"") -> 8470.0102 | Q11: =IFERROR(P11*(1+$M11),"") -> 10127.913 | R11: =IFERROR(Q11*(1+$M11),"") -> 12110.331 | S11: =IFERROR(R11*(1+$M11),"") -> 14480.783 | T11: =IFERROR(S11*(1+$M11),"") -> 17315.222
B12: =B11+1 -> 10 | C12: Paras Defense and Space | D12: PARAS | E12: PARAS | F12: =_xlfn.XLOOKUP($D12,BB_Input!$C$4:$C$172,BB_Input!$G$4:$G$172) -> 602.33536 | G12: =_xlfn.XLOOKUP($D12,CCA_Defense!$D:$D,CCA_Defense!M:M) -> 105 | H12: =_xlfn.XLOOKUP($D12,CCA_Defense!$D:$D,CCA_Defense!N:N) -> 59.901788 | I12: =_xlfn.XLOOKUP($D12,CCA_Defense!$D:$D,CCA_Defense!O:O) -> 45.026847 | J12: =_xlfn.XLOOKUP($D12,CCA_Defense!$D:$D,CCA_Defense!P:P) | K12: =_xlfn.XLOOKUP($D12,CCA_Defense!$D:$D,CCA_Defense!Q:Q) | L12: =_xlfn.XLOOKUP($D12,CCA_Defense!$D:$D,CCA_Defense!R:R) | M12: =_xlfn.XLOOKUP($D12,CCA_Defense!$D:$D,CCA_Defense!T:T) -> 0.10143233 | N12: =_xlfn.XLOOKUP($D12,CCA_Defense!$D:$D,CCA_Defense!U:U) -> 0 | O12: =IFERROR(_xlfn.XLOOKUP($D12,BB_Input!$C$4:$C$163,BB_Input!$CY$4:$CY$163),"") -> 3646.612 | P12: =IFERROR(O12*(1+$M12),"") -> 4016.4963 | Q12: =IFERROR(P12*(1+$M12),"") -> 4423.8989 | R12: =IFERROR(Q12*(1+$M12),"") -> 4872.6253 | S12: =IFERROR(R12*(1+$M12),"") -> 5366.867 | T12: =IFERROR(S12*(1+$M12),"") -> 5911.2408
B13: =B12+1 -> 11 | C13: Astra Microwave | D13: ASTM | E13: ASTM | F13: =_xlfn.XLOOKUP($D13,BB_Input!$C$4:$C$172,BB_Input!$G$4:$G$172) -> 1026.2888 | G13: =_xlfn.XLOOKUP($D13,CCA_Defense!$D:$D,CCA_Defense!M:M) -> 58.07 | H13: =_xlfn.XLOOKUP($D13,CCA_Defense!$D:$D,CCA_Defense!N:N) -> 53.831009 | I13: =_xlfn.XLOOKUP($D13,CCA_Defense!$D:$D,CCA_Defense!O:O) -> 44.264576 | J13: =_xlfn.XLOOKUP($D13,CCA_Defense!$D:$D,CCA_Defense!P:P) -> 36.398215 | K13: =_xlfn.XLOOKUP($D13,CCA_Defense!$D:$D,CCA_Defense!Q:Q) -> 29.929804 | L13: =_xlfn.XLOOKUP($D13,CCA_Defense!$D:$D,CCA_Defense!R:R) -> 24.610909 | M13: =_xlfn.XLOOKUP($D13,CCA_Defense!$D:$D,CCA_Defense!T:T) -> 0.075507965 | N13: =_xlfn.XLOOKUP($D13,CCA_Defense!$D:$D,CCA_Defense!U:U) -> 0.26 | O13: =IFERROR(_xlfn.XLOOKUP($D13,BB_Input!$C$4:$C$163,BB_Input!$CY$4:$CY$163),"") -> 10511.792 | P13: =IFERROR(O13*(1+$N13),"") -> 13244.858 | Q13: =IFERROR(P13*(1+$N13),"") -> 16688.521 | R13: =IFERROR(Q13*(1+$N13),"") -> 21027.536 | S13: =IFERROR(R13*(1+$N13),"") -> 26494.696 | T13: =IFERROR(S13*(1+$N13),"") -> 33383.317
B14: =B13+1 -> 12 | C14: Axiscades Technologies Ltd | D14: AXET | E14: AXISCADES | F14: =_xlfn.XLOOKUP($D14,BB_Input!$C$4:$C$172,BB_Input!$G$4:$G$172) -> 637.04539 | G14: =_xlfn.XLOOKUP($D14,CCA_Defense!$D:$D,CCA_Defense!M:M) -> 76.1 | H14: =_xlfn.XLOOKUP($D14,CCA_Defense!$D:$D,CCA_Defense!N:N) -> 52.028001 | I14: =_xlfn.XLOOKUP($D14,CCA_Defense!$D:$D,CCA_Defense!O:O) -> 35.47271 | J14: =_xlfn.XLOOKUP($D14,CCA_Defense!$D:$D,CCA_Defense!P:P) -> 24.185307 | K14: =_xlfn.XLOOKUP($D14,CCA_Defense!$D:$D,CCA_Defense!Q:Q) -> 16.489551 | L14: =_xlfn.XLOOKUP($D14,CCA_Defense!$D:$D,CCA_Defense!R:R) -> 11.242582 | M14: =_xlfn.XLOOKUP($D14,CCA_Defense!$D:$D,CCA_Defense!T:T) -> 0.1088115 | N14: =_xlfn.XLOOKUP($D14,CCA_Defense!$D:$D,CCA_Defense!U:U) -> 0.5439 | O14: =IFERROR(_xlfn.XLOOKUP($D14,BB_Input!$C$4:$C$163,BB_Input!$CY$4:$CY$163),"") -> 10307.237 | P14: =IFERROR(O14*(1+$N14),"") -> 15913.343 | Q14: =IFERROR(P14*(1+$N14),"") -> 24568.611 | R14: =IFERROR(Q14*(1+$N14),"") -> 37931.478 | S14: =IFERROR(R14*(1+$N14),"") -> 58562.409 | T14: =IFERROR(S14*(1+$N14),"") -> 90414.503
B15: =B14+1 -> 13 | C15: DCX Systems | D15: DCXINDIA | E15: DCXINDIA | F15: =_xlfn.XLOOKUP($D15,BB_Input!$C$4:$C$172,BB_Input!$G$4:$G$172) -> 251.06426 | G15: =_xlfn.XLOOKUP($D15,CCA_Defense!$D:$D,CCA_Defense!M:M) -> 67.45 | H15: =_xlfn.XLOOKUP($D15,CCA_Defense!$D:$D,CCA_Defense!N:N) -> 39.67059 | I15: =_xlfn.XLOOKUP($D15,CCA_Defense!$D:$D,CCA_Defense!O:O) -> 27.340542 | J15: =_xlfn.XLOOKUP($D15,CCA_Defense!$D:$D,CCA_Defense!P:P) -> 21.754839 | K15: =_xlfn.XLOOKUP($D15,CCA_Defense!$D:$D,CCA_Defense!Q:Q) | L15: =_xlfn.XLOOKUP($D15,CCA_Defense!$D:$D,CCA_Defense!R:R) | M15: =_xlfn.XLOOKUP($D15,CCA_Defense!$D:$D,CCA_Defense!T:T) -> 0.079915006 | N15: =_xlfn.XLOOKUP($D15,CCA_Defense!$D:$D,CCA_Defense!U:U) -> 0 | O15: =IFERROR(_xlfn.XLOOKUP($D15,BB_Input!$C$4:$C$163,BB_Input!$CY$4:$CY$163),"") -> 10836.71 | P15: =IFERROR(O15*(1+$M15),"") -> 11702.726 | Q15: =IFERROR(P15*(1+$M15),"") -> 12637.949 | R15: =IFERROR(Q15*(1+$M15),"") -> 13647.911 | S15: =IFERROR(R15*(1+$M15),"") -> 14738.584 | T15: =IFERROR(S15*(1+$M15),"") -> 15916.418
B16: =B15+1 -> 14 | C16: Avantel | D16: AVTS | E16: AVTS | F16: =_xlfn.XLOOKUP($D16,BB_Input!$C$4:$C$172,BB_Input!$G$4:$G$172) -> 476.85876 | G16: =_xlfn.XLOOKUP($D16,CCA_Defense!$D:$D,CCA_Defense!M:M) -> 0 | H16: =_xlfn.XLOOKUP($D16,CCA_Defense!$D:$D,CCA_Defense!N:N) -> 61.963867 | I16: =_xlfn.XLOOKUP($D16,CCA_Defense!$D:$D,CCA_Defense!O:O) -> 51.794235 | J16: =_xlfn.XLOOKUP($D16,CCA_Defense!$D:$D,CCA_Defense!P:P) -> 43.293663 | K16: =_xlfn.XLOOKUP($D16,CCA_Defense!$D:$D,CCA_Defense!Q:Q) -> 36.188222 | L16: =_xlfn.XLOOKUP($D16,CCA_Defense!$D:$D,CCA_Defense!R:R) -> 30.24894 | M16: =_xlfn.XLOOKUP($D16,CCA_Defense!$D:$D,CCA_Defense!T:T) -> 0.25927468 | N16: =_xlfn.XLOOKUP($D16,CCA_Defense!$D:$D,CCA_Defense!U:U) -> 0 | O16: =IFERROR(_xlfn.XLOOKUP($D16,BB_Input!$C$4:$C$163,BB_Input!$CY$4:$CY$163),"") -> 2491.262 | P16: =IFERROR(O16*(1+$M16),"") -> 3137.1832 | Q16: =IFERROR(P16*(1+$M16),"") -> 3950.5753 | R16: =IFERROR(Q16*(1+$M16),"") -> 4974.8594 | S16: =IFERROR(R16*(1+$M16),"") -> 6264.7145 | T16: =IFERROR(S16*(1+$M16),"") -> 7888.9963
B17: =B16+1 -> 15 | C17: Apollo Micro Systems | D17: APOLLO | E17: APOLLO | F17: =_xlfn.XLOOKUP($D17,BB_Input!$C$4:$C$172,BB_Input!$G$4:$G$172) -> 983.4285 | G17: =_xlfn.XLOOKUP($D17,CCA_Defense!$D:$D,CCA_Defense!M:M) -> 0 | H17: =_xlfn.XLOOKUP($D17,CCA_Defense!$D:$D,CCA_Defense!N:N) -> 84.83871 | I17: =_xlfn.XLOOKUP($D17,CCA_Defense!$D:$D,CCA_Defense!O:O) -> 57.173913 | J17: =_xlfn.XLOOKUP($D17,CCA_Defense!$D:$D,CCA_Defense!P:P) -> 35.066667 | K17: =_xlfn.XLOOKUP($D17,CCA_Defense!$D:$D,CCA_Defense!Q:Q) | L17: =_xlfn.XLOOKUP($D17,CCA_Defense!$D:$D,CCA_Defense!R:R) | M17: =_xlfn.XLOOKUP($D17,CCA_Defense!$D:$D,CCA_Defense!T:T) -> 0.13611833 | N17: =_xlfn.XLOOKUP($D17,CCA_Defense!$D:$D,CCA_Defense!U:U) -> 0 | O17: =IFERROR(_xlfn.XLOOKUP($D17,BB_Input!$C$4:$C$163,BB_Input!$CY$4:$CY$163),"") -> 5620.692 | P17: =IFERROR(O17*(1+$M17),"") -> 6385.7712 | Q17: =IFERROR(P17*(1+$M17),"") -> 7254.9918 | R17: =IFERROR(Q17*(1+$M17),"") -> 8242.5291 | S17: =IFERROR(R17*(1+$M17),"") -> 9364.4884 | T17: =IFERROR(S17*(1+$M17),"") -> 10639.167
B18: =B17+1 -> 16 | C18: Adani Elbit Advanced Systems India | D18: ADE | E18: ADANIENT | F18: =_xlfn.XLOOKUP($D18,BB_Input!$C$4:$C$172,BB_Input!$G$4:$G$172) -> 31344.867 | G18: =_xlfn.XLOOKUP($D18,CCA_Defense!$D:$D,CCA_Defense!M:M) -> 105 | H18: =_xlfn.XLOOKUP($D18,CCA_Defense!$D:$D,CCA_Defense!N:N) -> 66.283299 | I18: =_xlfn.XLOOKUP($D18,CCA_Defense!$D:$D,CCA_Defense!O:O) -> 52.057927 | J18: =_xlfn.XLOOKUP($D18,CCA_Defense!$D:$D,CCA_Defense!P:P) -> 46.357758 | K18: =_xlfn.XLOOKUP($D18,CCA_Defense!$D:$D,CCA_Defense!Q:Q) -> 50.407075 | L18: =_xlfn.XLOOKUP($D18,CCA_Defense!$D:$D,CCA_Defense!R:R) | M18: =_xlfn.XLOOKUP($D18,CCA_Defense!$D:$D,CCA_Defense!T:T) -> 0.090495011 | N18: =_xlfn.XLOOKUP($D18,CCA_Defense!$D:$D,CCA_Defense!U:U) -> 0 | O18: =IFERROR(_xlfn.XLOOKUP($D18,BB_Input!$C$4:$C$163,BB_Input!$CY$4:$CY$163),"") -> 977110.8 | P18: =IFERROR(O18*(1+$M18),"") -> 1065534.5 | Q18: =IFERROR(P18*(1+$M18),"") -> 1161960 | R18: =IFERROR(Q18*(1+$M18),"") -> 1267111.6 | S18: =IFERROR(R18*(1+$M18),"") -> 1381778.9 | T18: =IFERROR(S18*(1+$M18),"") -> 1506823
B19: =B18+1 -> 17 | C19: NIBE Ltd | D19: NIBE | E19: NIBE | F19: =_xlfn.XLOOKUP($D19,BB_Input!$C$4:$C$172,BB_Input!$G$4:$G$172) -> 183.75245 | G19: =_xlfn.XLOOKUP($D19,CCA_Defense!$D:$D,CCA_Defense!M:M) -> 59 | H19: =_xlfn.XLOOKUP($D19,CCA_Defense!$D:$D,CCA_Defense!N:N) -> 44.785977 | I19: =_xlfn.XLOOKUP($D19,CCA_Defense!$D:$D,CCA_Defense!O:O) -> 32.741084 | J19: =_xlfn.XLOOKUP($D19,CCA_Defense!$D:$D,CCA_Defense!P:P) -> 23.965091 | K19: =_xlfn.XLOOKUP($D19,CCA_Defense!$D:$D,CCA_Defense!Q:Q) -> 17.854307 | L19: =_xlfn.XLOOKUP($D19,CCA_Defense!$D:$D,CCA_Defense!R:R) -> 13.527146 | M19: =_xlfn.XLOOKUP($D19,CCA_Defense!$D:$D,CCA_Defense!T:T) -> 1.0662908 | N19: =_xlfn.XLOOKUP($D19,CCA_Defense!$D:$D,CCA_Defense!U:U) -> 0 | O19: =IFERROR(_xlfn.XLOOKUP($D19,BB_Input!$C$4:$C$163,BB_Input!$CY$4:$CY$163),"") -> 5073.151 | P19: =IFERROR(O19*(1+$M19),"") -> 10482.605 | Q19: =IFERROR(P19*(1+$M19),"") -> 21660.11 | R19: =IFERROR(Q19*(1+$M19),"") -> 44756.086 | S19: =IFERROR(R19*(1+$M19),"") -> 92479.088 | T19: =IFERROR(S19*(1+$M19),"") -> 191088.69
B20: =B19+1 -> 18 | C20: Azad Engineering | D20: AZAD | E20: AZAD | F20: =_xlfn.XLOOKUP($D20,BB_Input!$C$4:$C$172,BB_Input!$G$4:$G$172) -> 1191.4721 | G20: =_xlfn.XLOOKUP($D20,CCA_Defense!$D:$D,CCA_Defense!M:M) -> 108 | H20: =_xlfn.XLOOKUP($D20,CCA_Defense!$D:$D,CCA_Defense!N:N) -> 84.328635 | I20: =_xlfn.XLOOKUP($D20,CCA_Defense!$D:$D,CCA_Defense!O:O) -> 55.772907 | J20: =_xlfn.XLOOKUP($D20,CCA_Defense!$D:$D,CCA_Defense!P:P) -> 36.886843 | K20: =_xlfn.XLOOKUP($D20,CCA_Defense!$D:$D,CCA_Defense!Q:Q) -> 24.39606 | L20: =_xlfn.XLOOKUP($D20,CCA_Defense!$D:$D,CCA_Defense!R:R) -> 16.134961 | M20: =_xlfn.XLOOKUP($D20,CCA_Defense!$D:$D,CCA_Defense!T:T) -> 0.18772564 | N20: =_xlfn.XLOOKUP($D20,CCA_Defense!$D:$D,CCA_Defense!U:U) -> 0.44 | O20: =IFERROR(_xlfn.XLOOKUP($D20,BB_Input!$C$4:$C$163,BB_Input!$CY$4:$CY$163),"") -> 4437.94 | P20: =IFERROR(O20*(1+$N20),"") -> 6390.6336 | Q20: =IFERROR(P20*(1+$N20),"") -> 9202.5124 | R20: =IFERROR(Q20*(1+$N20),"") -> 13251.618 | S20: =IFERROR(R20*(1+$N20),"") -> 19082.33 | T20: =IFERROR(S20*(1+$N20),"") -> 27478.555
B21: =B20+1 -> 19 | C21: Zen Technologies | D21: ZEN | E21: ZENTEC | F21: =_xlfn.XLOOKUP($D21,BB_Input!$C$4:$C$172,BB_Input!$G$4:$G$172) -> 1399.8115 | G21: =_xlfn.XLOOKUP($D21,CCA_Defense!$D:$D,CCA_Defense!M:M) -> 61 | H21: =_xlfn.XLOOKUP($D21,CCA_Defense!$D:$D,CCA_Defense!N:N) -> 46.506808 | I21: =_xlfn.XLOOKUP($D21,CCA_Defense!$D:$D,CCA_Defense!O:O) -> 30.078893 | J21: =_xlfn.XLOOKUP($D21,CCA_Defense!$D:$D,CCA_Defense!P:P) -> 23.192367 | K21: =_xlfn.XLOOKUP($D21,CCA_Defense!$D:$D,CCA_Defense!Q:Q) | L21: =_xlfn.XLOOKUP($D21,CCA_Defense!$D:$D,CCA_Defense!R:R) | M21: =_xlfn.XLOOKUP($D21,CCA_Defense!$D:$D,CCA_Defense!T:T) -> 0.39868042 | N21: =_xlfn.XLOOKUP($D21,CCA_Defense!$D:$D,CCA_Defense!U:U) -> 0 | O21: =IFERROR(_xlfn.XLOOKUP($D21,BB_Input!$C$4:$C$163,BB_Input!$CY$4:$CY$163),"") -> 9736.416 | P21: =IFERROR(O21*(1+$M21),"") -> 13618.134 | Q21: =IFERROR(P21*(1+$M21),"") -> 19047.418 | R21: =IFERROR(Q21*(1+$M21),"") -> 26641.25 | S21: =IFERROR(R21*(1+$M21),"") -> 37262.595 | T21: =IFERROR(S21*(1+$M21),"") -> 52118.462
B22: =B21+1 -> 20 | C22: C2C Advanced Systems | D22: C2C | E22: C2C | F22: =_xlfn.XLOOKUP($D22,BB_Input!$C$4:$C$172,BB_Input!$G$4:$G$172) -> 91.853865 | G22: =_xlfn.XLOOKUP($D22,CCA_Defense!$D:$D,CCA_Defense!M:M) -> 36 | H22: =_xlfn.XLOOKUP($D22,CCA_Defense!$D:$D,CCA_Defense!N:N) -> 20.472867 | I22: =_xlfn.XLOOKUP($D22,CCA_Defense!$D:$D,CCA_Defense!O:O) -> 17.930853 | J22: =_xlfn.XLOOKUP($D22,CCA_Defense!$D:$D,CCA_Defense!P:P) -> 15.704468 | K22: =_xlfn.XLOOKUP($D22,CCA_Defense!$D:$D,CCA_Defense!Q:Q) -> 13.754523 | L22: =_xlfn.XLOOKUP($D22,CCA_Defense!$D:$D,CCA_Defense!R:R) -> 12.046692 | M22: =_xlfn.XLOOKUP($D22,CCA_Defense!$D:$D,CCA_Defense!T:T) | N22: =_xlfn.XLOOKUP($D22,CCA_Defense!$D:$D,CCA_Defense!U:U) -> 0.4427 | O22: =IFERROR(_xlfn.XLOOKUP($D22,BB_Input!$C$4:$C$163,BB_Input!$CY$4:$CY$163),"") -> 1151.111 | P22: =IFERROR(O22*(1+$N22),"") -> 1660.7078 | Q22: =IFERROR(P22*(1+$N22),"") -> 2395.9032 | R22: =IFERROR(Q22*(1+$N22),"") -> 3456.5695 | S22: =IFERROR(R22*(1+$N22),"") -> 4986.7929 | T22: =IFERROR(S22*(1+$N22),"") -> 7194.4461
B23: =B22+1 -> 21 | C23: Centum Electronics | D23: CTE | E23: CTE | F23: =_xlfn.XLOOKUP($D23,BB_Input!$C$4:$C$172,BB_Input!$G$4:$G$172) -> 393.71613 | G23: =_xlfn.XLOOKUP($D23,CCA_Defense!$D:$D,CCA_Defense!M:M) -> 0 | H23: =_xlfn.XLOOKUP($D23,CCA_Defense!$D:$D,CCA_Defense!N:N) -> 65.524589 | I23: =_xlfn.XLOOKUP($D23,CCA_Defense!$D:$D,CCA_Defense!O:O) -> 35.955022 | J23: =_xlfn.XLOOKUP($D23,CCA_Defense!$D:$D,CCA_Defense!P:P) -> 22.949282 | K23: =_xlfn.XLOOKUP($D23,CCA_Defense!$D:$D,CCA_Defense!Q:Q) | L23: =_xlfn.XLOOKUP($D23,CCA_Defense!$D:$D,CCA_Defense!R:R) | M23: =_xlfn.XLOOKUP($D23,CCA_Defense!$D:$D,CCA_Defense!T:T) -> 0.072374264 | N23: =_xlfn.XLOOKUP($D23,CCA_Defense!$D:$D,CCA_Defense!U:U) -> 0 | O23: =IFERROR(_xlfn.XLOOKUP($D23,BB_Input!$C$4:$C$163,BB_Input!$CY$4:$CY$163),"") -> 11308.64 | P23: =IFERROR(O23*(1+$M23),"") -> 12127.094 | Q23: =IFERROR(P23*(1+$M23),"") -> 13004.784 | R23: =IFERROR(Q23*(1+$M23),"") -> 13945.996 | S23: =IFERROR(R23*(1+$M23),"") -> 14955.327 | T23: =IFERROR(S23*(1+$M23),"") -> 16037.708
B24: =B23+1 -> 22 | C24: IdeaForge Technology Ltd | D24: IDEAFORG | E24: IDEAFORGE | F24: =_xlfn.XLOOKUP($D24,BB_Input!$C$4:$C$172,BB_Input!$G$4:$G$172) -> 231.34958 | G24: =_xlfn.XLOOKUP($D24,CCA_Defense!$D:$D,CCA_Defense!M:M) -> 0 | H24: =_xlfn.XLOOKUP($D24,CCA_Defense!$D:$D,CCA_Defense!N:N) | I24: =_xlfn.XLOOKUP($D24,CCA_Defense!$D:$D,CCA_Defense!O:O) | J24: =_xlfn.XLOOKUP($D24,CCA_Defense!$D:$D,CCA_Defense!P:P) -> 27.268411 | K24: =_xlfn.XLOOKUP($D24,CCA_Defense!$D:$D,CCA_Defense!Q:Q) -> 33.792365 | L24: =_xlfn.XLOOKUP($D24,CCA_Defense!$D:$D,CCA_Defense!R:R) -> 25.126303 | M24: =_xlfn.XLOOKUP($D24,CCA_Defense!$D:$D,CCA_Defense!T:T) -> 0.25007157 | N24: =_xlfn.XLOOKUP($D24,CCA_Defense!$D:$D,CCA_Defense!U:U) -> 0.3449 | O24: =IFERROR(_xlfn.XLOOKUP($D24,BB_Input!$C$4:$C$163,BB_Input!$CY$4:$CY$163),"") -> 1611.48 | P24: =IFERROR(O24*(1+$N24),"") -> 2167.2795 | Q24: =IFERROR(P24*(1+$N24),"") -> 2914.7741 | R24: =IFERROR(Q24*(1+$N24),"") -> 3920.0797 | S24: =IFERROR(R24*(1+$N24),"") -> 5272.1152 | T24: =IFERROR(S24*(1+$N24),"") -> 7090.4678
B25: =B24+1 -> 23 | C25: Cyient DLM Ltd | D25: CYIENTDL | E25: CYIENT | F25: =_xlfn.XLOOKUP($D25,BB_Input!$C$4:$C$172,BB_Input!$G$4:$G$172) -> 376.52703 | G25: =_xlfn.XLOOKUP($D25,CCA_Defense!$D:$D,CCA_Defense!M:M) -> 54.4 | H25: =_xlfn.XLOOKUP($D25,CCA_Defense!$D:$D,CCA_Defense!N:N) -> 39.887602 | I25: =_xlfn.XLOOKUP($D25,CCA_Defense!$D:$D,CCA_Defense!O:O) -> 26.816751 | J25: =_xlfn.XLOOKUP($D25,CCA_Defense!$D:$D,CCA_Defense!P:P) -> 20.122067 | K25: =_xlfn.XLOOKUP($D25,CCA_Defense!$D:$D,CCA_Defense!Q:Q) -> 15.005286 | L25: =_xlfn.XLOOKUP($D25,CCA_Defense!$D:$D,CCA_Defense!R:R) | M25: =_xlfn.XLOOKUP($D25,CCA_Defense!$D:$D,CCA_Defense!T:T) -> 0.16353388 | N25: =_xlfn.XLOOKUP($D25,CCA_Defense!$D:$D,CCA_Defense!U:U) -> 0 | O25: =IFERROR(_xlfn.XLOOKUP($D25,BB_Input!$C$4:$C$163,BB_Input!$CY$4:$CY$163),"") -> 15196.26 | P25: =IFERROR(O25*(1+$M25),"") -> 17681.363 | Q25: =IFERROR(P25*(1+$M25),"") -> 20572.865 | R25: =IFERROR(Q25*(1+$M25),"") -> 23937.226 | S25: =IFERROR(R25*(1+$M25),"") -> 27851.773 | T25: =IFERROR(S25*(1+$M25),"") -> 32406.482
B26: =B25+1 -> 24 | C26: JayKay Enterprises | D26: JEL | E26: JAYKAY | F26: =_xlfn.XLOOKUP($D26,BB_Input!$C$4:$C$172,BB_Input!$G$4:$G$172) -> 288.03437 | G26: =_xlfn.XLOOKUP($D26,CCA_Defense!$D:$D,CCA_Defense!M:M) -> 100 | H26: =_xlfn.XLOOKUP($D26,CCA_Defense!$D:$D,CCA_Defense!N:N) -> 78.989184 | I26: =_xlfn.XLOOKUP($D26,CCA_Defense!$D:$D,CCA_Defense!O:O) -> 51.417814 | J26: =_xlfn.XLOOKUP($D26,CCA_Defense!$D:$D,CCA_Defense!P:P) -> 33.470299 | K26: =_xlfn.XLOOKUP($D26,CCA_Defense!$D:$D,CCA_Defense!Q:Q) -> 21.787409 | L26: =_xlfn.XLOOKUP($D26,CCA_Defense!$D:$D,CCA_Defense!R:R) -> 14.18246 | M26: =_xlfn.XLOOKUP($D26,CCA_Defense!$D:$D,CCA_Defense!T:T) -> 0.67027765 | N26: =_xlfn.XLOOKUP($D26,CCA_Defense!$D:$D,CCA_Defense!U:U) -> 0 | O26: =IFERROR(_xlfn.XLOOKUP($D26,BB_Input!$C$4:$C$163,BB_Input!$CY$4:$CY$163),"") -> 806.398 | P26: =IFERROR(O26*(1+$M26),"") -> 1346.9086 | Q26: =IFERROR(P26*(1+$M26),"") -> 2249.7113 | R26: =IFERROR(Q26*(1+$M26),"") -> 3757.6424 | S26: =IFERROR(R26*(1+$M26),"") -> 6276.3062 | T26: =IFERROR(S26*(1+$M26),"") -> 10483.174
B27: =B26+1 -> 25 | C27: Sika Interplant Systems | D27: SIKA | E27: SIKA | F27: =_xlfn.XLOOKUP($D27,BB_Input!$C$4:$C$172,BB_Input!$G$4:$G$172) -> 213.04636 | G27: =_xlfn.XLOOKUP($D27,CCA_Defense!$D:$D,CCA_Defense!M:M) -> 82 | H27: =_xlfn.XLOOKUP($D27,CCA_Defense!$D:$D,CCA_Defense!N:N) -> 73.677848 | I27: =_xlfn.XLOOKUP($D27,CCA_Defense!$D:$D,CCA_Defense!O:O) -> 69.220969 | J27: =_xlfn.XLOOKUP($D27,CCA_Defense!$D:$D,CCA_Defense!P:P) -> 66.946448 | K27: =_xlfn.XLOOKUP($D27,CCA_Defense!$D:$D,CCA_Defense!Q:Q) -> 64.746665 | L27: =_xlfn.XLOOKUP($D27,CCA_Defense!$D:$D,CCA_Defense!R:R) -> 60.879744 | M27: =_xlfn.XLOOKUP($D27,CCA_Defense!$D:$D,CCA_Defense!T:T) -> 0.033975227 | N27: =_xlfn.XLOOKUP($D27,CCA_Defense!$D:$D,CCA_Defense!U:U) -> 0 | O27: =IFERROR(_xlfn.XLOOKUP($D27,BB_Input!$C$4:$C$163,BB_Input!$CY$4:$CY$163),"") -> 1476.605 | P27: =IFERROR(O27*(1+$M27),"") -> 1526.773 | Q27: =IFERROR(P27*(1+$M27),"") -> 1578.6454 | R27: =IFERROR(Q27*(1+$M27),"") -> 1632.2803 | S27: =IFERROR(R27*(1+$M27),"") -> 1687.7374 | T27: =IFERROR(S27*(1+$M27),"") -> 1745.0786
B28: =B27+1 -> 26 | C28: Dynamatic Technologies Ltd | D28: DYTC | E28: DYNAMATECH | F28: =_xlfn.XLOOKUP($D28,BB_Input!$C$4:$C$172,BB_Input!$G$4:$G$172) -> 731.76171 | G28: =_xlfn.XLOOKUP($D28,CCA_Defense!$D:$D,CCA_Defense!M:M) -> 113 | H28: =_xlfn.XLOOKUP($D28,CCA_Defense!$D:$D,CCA_Defense!N:N) -> 124.15276 | I28: =_xlfn.XLOOKUP($D28,CCA_Defense!$D:$D,CCA_Defense!O:O) -> 68.013361 | J28: =_xlfn.XLOOKUP($D28,CCA_Defense!$D:$D,CCA_Defense!P:P) -> 48.576092 | K28: =_xlfn.XLOOKUP($D28,CCA_Defense!$D:$D,CCA_Defense!Q:Q) -> 25.326682 | L28: =_xlfn.XLOOKUP($D28,CCA_Defense!$D:$D,CCA_Defense!R:R) | M28: =_xlfn.XLOOKUP($D28,CCA_Defense!$D:$D,CCA_Defense!T:T) -> 0.022702436 | N28: =_xlfn.XLOOKUP($D28,CCA_Defense!$D:$D,CCA_Defense!U:U) -> 0 | O28: =IFERROR(_xlfn.XLOOKUP($D28,BB_Input!$C$4:$C$163,BB_Input!$CY$4:$CY$163),"") -> 14038 | P28: =IFERROR(O28*(1+$M28),"") -> 14356.697 | Q28: =IFERROR(P28*(1+$M28),"") -> 14682.629 | R28: =IFERROR(Q28*(1+$M28),"") -> 15015.96 | S28: =IFERROR(R28*(1+$M28),"") -> 15356.859 | T28: =IFERROR(S28*(1+$M28),"") -> 15705.497
B29: =B28+1 -> 27 | C29: Kaynes Technology Ltd | D29: KAYNES | E29: KAYNES | F29: =_xlfn.XLOOKUP($D29,BB_Input!$C$4:$C$172,BB_Input!$G$4:$G$172) -> 3075.7585 | G29: =_xlfn.XLOOKUP($D29,CCA_Defense!$D:$D,CCA_Defense!M:M) -> 146 | H29: =_xlfn.XLOOKUP($D29,CCA_Defense!$D:$D,CCA_Defense!N:N) -> 58.586449 | I29: =_xlfn.XLOOKUP($D29,CCA_Defense!$D:$D,CCA_Defense!O:O) -> 42.16206 | J29: =_xlfn.XLOOKUP($D29,CCA_Defense!$D:$D,CCA_Defense!P:P) -> 30.930776 | K29: =_xlfn.XLOOKUP($D29,CCA_Defense!$D:$D,CCA_Defense!Q:Q) -> 20.724359 | L29: =_xlfn.XLOOKUP($D29,CCA_Defense!$D:$D,CCA_Defense!R:R) | M29: =_xlfn.XLOOKUP($D29,CCA_Defense!$D:$D,CCA_Defense!T:T) -> 0.27657457 | N29: =_xlfn.XLOOKUP($D29,CCA_Defense!$D:$D,CCA_Defense!U:U) -> 0 | O29: =IFERROR(_xlfn.XLOOKUP($D29,BB_Input!$C$4:$C$163,BB_Input!$CY$4:$CY$163),"") -> 27217.52 | P29: =IFERROR(O29*(1+$M29),"") -> 34745.194 | Q29: =IFERROR(P29*(1+$M29),"") -> 44354.831 | R29: =IFERROR(Q29*(1+$M29),"") -> 56622.249 | S29: =IFERROR(R29*(1+$M29),"") -> 72282.523 | T29: =IFERROR(S29*(1+$M29),"") -> 92274.031
B30: =B29+1 -> 28 | C30: Syrma SGS Technology Ltd | D30: SYRMA | E30: SYRMA | F30: =_xlfn.XLOOKUP($D30,BB_Input!$C$4:$C$172,BB_Input!$G$4:$G$172) -> 1576.5101 | G30: =_xlfn.XLOOKUP($D30,CCA_Defense!$D:$D,CCA_Defense!M:M) -> 62 | H30: =_xlfn.XLOOKUP($D30,CCA_Defense!$D:$D,CCA_Defense!N:N) -> 52.869449 | I30: =_xlfn.XLOOKUP($D30,CCA_Defense!$D:$D,CCA_Defense!O:O) -> 36.643397 | J30: =_xlfn.XLOOKUP($D30,CCA_Defense!$D:$D,CCA_Defense!P:P) -> 27.262702 | K30: =_xlfn.XLOOKUP($D30,CCA_Defense!$D:$D,CCA_Defense!Q:Q) -> 19.449008 | L30: =_xlfn.XLOOKUP($D30,CCA_Defense!$D:$D,CCA_Defense!R:R) | M30: =_xlfn.XLOOKUP($D30,CCA_Defense!$D:$D,CCA_Defense!T:T) -> 0.30068267 | N30: =_xlfn.XLOOKUP($D30,CCA_Defense!$D:$D,CCA_Defense!U:U) -> 0 | O30: =IFERROR(_xlfn.XLOOKUP($D30,BB_Input!$C$4:$C$163,BB_Input!$CY$4:$CY$163),"") -> 37159.89 | P30: =IFERROR(O30*(1+$M30),"") -> 48333.225 | Q30: =IFERROR(P30*(1+$M30),"") -> 62866.188 | R30: =IFERROR(Q30*(1+$M30),"") -> 81768.961 | S30: =IFERROR(R30*(1+$M30),"") -> 106355.47 | T30: =IFERROR(S30*(1+$M30),"") -> 138334.72
B31: =B30+1 -> 29 | C31: Solar Industries India Ltd | D31: SOIL | E31: SOLARINDS | F31: =_xlfn.XLOOKUP($D31,BB_Input!$C$4:$C$172,BB_Input!$G$4:$G$172) -> 12586.448 | G31: =_xlfn.XLOOKUP($D31,CCA_Defense!$D:$D,CCA_Defense!M:M) -> 108 | H31: =_xlfn.XLOOKUP($D31,CCA_Defense!$D:$D,CCA_Defense!N:N) -> 66.813536 | I31: =_xlfn.XLOOKUP($D31,CCA_Defense!$D:$D,CCA_Defense!O:O) -> 52.071217 | J31: =_xlfn.XLOOKUP($D31,CCA_Defense!$D:$D,CCA_Defense!P:P) -> 43.450835 | K31: =_xlfn.XLOOKUP($D31,CCA_Defense!$D:$D,CCA_Defense!Q:Q) -> 34.141873 | L31: =_xlfn.XLOOKUP($D31,CCA_Defense!$D:$D,CCA_Defense!R:R) | M31: =_xlfn.XLOOKUP($D31,CCA_Defense!$D:$D,CCA_Defense!T:T) -> 0.12104299 | N31: =_xlfn.XLOOKUP($D31,CCA_Defense!$D:$D,CCA_Defense!U:U) -> 0 | O31: =IFERROR(_xlfn.XLOOKUP($D31,BB_Input!$C$4:$C$163,BB_Input!$CY$4:$CY$163),"") -> 75402.6 | P31: =IFERROR(O31*(1+$M31),"") -> 84529.556 | Q31: =IFERROR(P31*(1+$M31),"") -> 94761.266 | R31: =IFERROR(Q31*(1+$M31),"") -> 106231.45 | S31: =IFERROR(R31*(1+$M31),"") -> 119090.02 | T31: =IFERROR(S31*(1+$M31),"") -> 133505.04
B32: =B31+1 -> 30 | C32: Bharat Forge Ltd | D32: BHFC | E32: BHARATFORG | F32: =_xlfn.XLOOKUP($D32,BB_Input!$C$4:$C$172,BB_Input!$G$4:$G$172) -> 7725.7373 | G32: =_xlfn.XLOOKUP($D32,CCA_Defense!$D:$D,CCA_Defense!M:M) -> 58 | H32: =_xlfn.XLOOKUP($D32,CCA_Defense!$D:$D,CCA_Defense!N:N) -> 54.214166 | I32: =_xlfn.XLOOKUP($D32,CCA_Defense!$D:$D,CCA_Defense!O:O) -> 40.96701 | J32: =_xlfn.XLOOKUP($D32,CCA_Defense!$D:$D,CCA_Defense!P:P) -> 34.129733 | K32: =_xlfn.XLOOKUP($D32,CCA_Defense!$D:$D,CCA_Defense!Q:Q) -> 25.76491 | L32: =_xlfn.XLOOKUP($D32,CCA_Defense!$D:$D,CCA_Defense!R:R) | M32: =_xlfn.XLOOKUP($D32,CCA_Defense!$D:$D,CCA_Defense!T:T) -> 0.076451952 | N32: =_xlfn.XLOOKUP($D32,CCA_Defense!$D:$D,CCA_Defense!U:U) -> 0 | O32: =IFERROR(_xlfn.XLOOKUP($D32,BB_Input!$C$4:$C$163,BB_Input!$CY$4:$CY$163),"") -> 151228.03 | P32: =IFERROR(O32*(1+$M32),"") -> 162789.71 | Q32: =IFERROR(P32*(1+$M32),"") -> 175235.3 | R32: =IFERROR(Q32*(1+$M32),"") -> 188632.38 | S32: =IFERROR(R32*(1+$M32),"") -> 203053.69 | T32: =IFERROR(S32*(1+$M32),"") -> 218577.54
B33: =B32+1 -> 31 | C33: Larsen & Toubro Ltd (L&T) | D33: LT | E33: LT | F33: =_xlfn.XLOOKUP($D33,BB_Input!$C$4:$C$172,BB_Input!$G$4:$G$172) -> 62121.34 | G33: =_xlfn.XLOOKUP($D33,CCA_Defense!$D:$D,CCA_Defense!M:M) -> 33 | H33: =_xlfn.XLOOKUP($D33,CCA_Defense!$D:$D,CCA_Defense!N:N) -> 30.839425 | I33: =_xlfn.XLOOKUP($D33,CCA_Defense!$D:$D,CCA_Defense!O:O) -> 25.364498 | J33: =_xlfn.XLOOKUP($D33,CCA_Defense!$D:$D,CCA_Defense!P:P) -> 21.507315 | K33: =_xlfn.XLOOKUP($D33,CCA_Defense!$D:$D,CCA_Defense!Q:Q) -> 18.582136 | L33: =_xlfn.XLOOKUP($D33,CCA_Defense!$D:$D,CCA_Defense!R:R) | M33: =_xlfn.XLOOKUP($D33,CCA_Defense!$D:$D,CCA_Defense!T:T) -> 0.10317481 | N33: =_xlfn.XLOOKUP($D33,CCA_Defense!$D:$D,CCA_Defense!U:U) -> 0 | O33: =IFERROR(_xlfn.XLOOKUP($D33,BB_Input!$C$4:$C$163,BB_Input!$CY$4:$CY$163),"") -> 2542086.5 | P33: =IFERROR(O33*(1+$M33),"") -> 2804365.8 | Q33: =IFERROR(P33*(1+$M33),"") -> 3093705.7 | R33: =IFERROR(Q33*(1+$M33),"") -> 3412898.2 | S33: =IFERROR(R33*(1+$M33),"") -> 3765023.3 | T33: =IFERROR(S33*(1+$M33),"") -> 4153478.9
B34: =B33+1 -> 32 | C34: Bharat Heavy Electricals Ltd | D34: BHEL | E34: BHEL | F34: =_xlfn.XLOOKUP($D34,BB_Input!$C$4:$C$172,BB_Input!$G$4:$G$172) -> 10792.141 | G34: =_xlfn.XLOOKUP($D34,CCA_Defense!$D:$D,CCA_Defense!M:M) -> 156 | H34: =_xlfn.XLOOKUP($D34,CCA_Defense!$D:$D,CCA_Defense!N:N) -> 55.68455 | I34: =_xlfn.XLOOKUP($D34,CCA_Defense!$D:$D,CCA_Defense!O:O) -> 31.449244 | J34: =_xlfn.XLOOKUP($D34,CCA_Defense!$D:$D,CCA_Defense!P:P) -> 22.968009 | K34: =_xlfn.XLOOKUP($D34,CCA_Defense!$D:$D,CCA_Defense!Q:Q) | L34: =_xlfn.XLOOKUP($D34,CCA_Defense!$D:$D,CCA_Defense!R:R) | M34: =_xlfn.XLOOKUP($D34,CCA_Defense!$D:$D,CCA_Defense!T:T) -> 0.054167392 | N34: =_xlfn.XLOOKUP($D34,CCA_Defense!$D:$D,CCA_Defense!U:U) -> 0 | O34: =IFERROR(_xlfn.XLOOKUP($D34,BB_Input!$C$4:$C$163,BB_Input!$CY$4:$CY$163),"") -> 273551.7 | P34: =IFERROR(O34*(1+$M34),"") -> 288369.28 | Q34: =IFERROR(P34*(1+$M34),"") -> 303989.49 | R34: =IFERROR(Q34*(1+$M34),"") -> 320455.81 | S34: =IFERROR(R34*(1+$M34),"") -> 337814.07 | T34: =IFERROR(S34*(1+$M34),"") -> 356112.58
B35: =B34+1 -> 33 | C35: Kavveri Defence & Wireless Tech | D35: KAVDEFEN | E35: KAVDEFENCE | F35: =_xlfn.XLOOKUP($D35,BB_Input!$C$4:$C$172,BB_Input!$G$4:$G$172) -> 30.544449 | G35: =_xlfn.XLOOKUP($D35,CCA_Defense!$D:$D,CCA_Defense!M:M) -> 31.6 | H35: =_xlfn.XLOOKUP($D35,CCA_Defense!$D:$D,CCA_Defense!N:N) -> 61.262396 | I35: =_xlfn.XLOOKUP($D35,CCA_Defense!$D:$D,CCA_Defense!O:O) -> 41.105771 | J35: =_xlfn.XLOOKUP($D35,CCA_Defense!$D:$D,CCA_Defense!P:P) -> 27.581102 | K35: =_xlfn.XLOOKUP($D35,CCA_Defense!$D:$D,CCA_Defense!Q:Q) -> 18.506335 | L35: =_xlfn.XLOOKUP($D35,CCA_Defense!$D:$D,CCA_Defense!R:R) -> 12.417359 | M35: =_xlfn.XLOOKUP($D35,CCA_Defense!$D:$D,CCA_Defense!T:T) | N35: =_xlfn.XLOOKUP($D35,CCA_Defense!$D:$D,CCA_Defense!U:U) -> 0.406 | O35: =IFERROR(_xlfn.XLOOKUP($D35,BB_Input!$C$4:$C$163,BB_Input!$CY$4:$CY$163),"") -> 171.2 | P35: =IFERROR(O35*(1+$N35),"") -> 240.7072 | Q35: =IFERROR(P35*(1+$N35),"") -> 338.43432 | R35: =IFERROR(Q35*(1+$N35),"") -> 475.83866 | S35: =IFERROR(R35*(1+$N35),"") -> 669.02915 | T35: =IFERROR(S35*(1+$N35),"") -> 940.65499
B36: =B35+1 -> 34 | C36: Taneja Aerospace & Aviation Ltd | D36: TAA | E36: TANEJAERO | F36: =_xlfn.XLOOKUP($D36,BB_Input!$C$4:$C$172,BB_Input!$G$4:$G$172) -> 83.637471 | G36: =_xlfn.XLOOKUP($D36,CCA_Defense!$D:$D,CCA_Defense!M:M) -> 53.5 | H36: =_xlfn.XLOOKUP($D36,CCA_Defense!$D:$D,CCA_Defense!N:N) -> 150.81606 | I36: =_xlfn.XLOOKUP($D36,CCA_Defense!$D:$D,CCA_Defense!O:O) -> 140.63933 | J36: =_xlfn.XLOOKUP($D36,CCA_Defense!$D:$D,CCA_Defense!P:P) -> 131.1493 | K36: =_xlfn.XLOOKUP($D36,CCA_Defense!$D:$D,CCA_Defense!Q:Q) -> 122.29964 | L36: =_xlfn.XLOOKUP($D36,CCA_Defense!$D:$D,CCA_Defense!R:R) -> 114.04714 | M36: =_xlfn.XLOOKUP($D36,CCA_Defense!$D:$D,CCA_Defense!T:T) -> 0.021295688 | N36: =_xlfn.XLOOKUP($D36,CCA_Defense!$D:$D,CCA_Defense!U:U) -> 0 | O36: =IFERROR(_xlfn.XLOOKUP($D36,BB_Input!$C$4:$C$163,BB_Input!$CY$4:$CY$163),"") -> 406.169 | P36: =IFERROR(O36*(1+$M36),"") -> 414.81865 | Q36: =IFERROR(P36*(1+$M36),"") -> 423.6525 | R36: =IFERROR(Q36*(1+$M36),"") -> 432.67447 | S36: =IFERROR(R36*(1+$M36),"") -> 441.88857 | T36: =IFERROR(S36*(1+$M36),"") -> 451.29889
B37: =B36+1 -> 35 | C37: Krishna Defence & Allied Industries | D37: KRISHNDF | E37: KRISHNADEF | F37: =_xlfn.XLOOKUP($D37,BB_Input!$C$4:$C$172,BB_Input!$G$4:$G$172) -> 130.14987 | G37: =_xlfn.XLOOKUP($D37,CCA_Defense!$D:$D,CCA_Defense!M:M) -> 57 | H37: =_xlfn.XLOOKUP($D37,CCA_Defense!$D:$D,CCA_Defense!N:N) -> 41.345254 | I37: =_xlfn.XLOOKUP($D37,CCA_Defense!$D:$D,CCA_Defense!O:O) -> 27.15616 | J37: =_xlfn.XLOOKUP($D37,CCA_Defense!$D:$D,CCA_Defense!P:P) -> 17.836558 | K37: =_xlfn.XLOOKUP($D37,CCA_Defense!$D:$D,CCA_Defense!Q:Q) -> 11.715309 | L37: =_xlfn.XLOOKUP($D37,CCA_Defense!$D:$D,CCA_Defense!R:R) -> 7.6947844 | M37: =_xlfn.XLOOKUP($D37,CCA_Defense!$D:$D,CCA_Defense!T:T) -> 0.3160171 | N37: =_xlfn.XLOOKUP($D37,CCA_Defense!$D:$D,CCA_Defense!U:U) -> 0.45 | O37: =IFERROR(_xlfn.XLOOKUP($D37,BB_Input!$C$4:$C$163,BB_Input!$CY$4:$CY$163),"") -> 1948.661 | P37: =IFERROR(O37*(1+$N37),"") -> 2825.5584 | Q37: =IFERROR(P37*(1+$N37),"") -> 4097.0598 | R37: =IFERROR(Q37*(1+$N37),"") -> 5940.7366 | S37: =IFERROR(R37*(1+$N37),"") -> 8614.0681 | T37: =IFERROR(S37*(1+$N37),"") -> 12490.399
B38: =B37+1 -> 36 | C38: HBL Power Systems Ltd | D38: HBLENGINE | E38: HBLENGINE | F38: =_xlfn.XLOOKUP($D38,BB_Input!$C$4:$C$172,BB_Input!$G$4:$G$172) -> 2722.5174 | G38: =_xlfn.XLOOKUP($D38,CCA_Defense!$D:$D,CCA_Defense!M:M) -> 43 | H38: =_xlfn.XLOOKUP($D38,CCA_Defense!$D:$D,CCA_Defense!N:N) -> 39.533631 | I38: =_xlfn.XLOOKUP($D38,CCA_Defense!$D:$D,CCA_Defense!O:O) -> 31.151943 | J38: =_xlfn.XLOOKUP($D38,CCA_Defense!$D:$D,CCA_Defense!P:P) -> 28.716612 | K38: =_xlfn.XLOOKUP($D38,CCA_Defense!$D:$D,CCA_Defense!Q:Q) | L38: =_xlfn.XLOOKUP($D38,CCA_Defense!$D:$D,CCA_Defense!R:R) | M38: =_xlfn.XLOOKUP($D38,CCA_Defense!$D:$D,CCA_Defense!T:T) -> 0.11304961 | N38: =_xlfn.XLOOKUP($D38,CCA_Defense!$D:$D,CCA_Defense!U:U) -> 0 | O38: =IFERROR(_xlfn.XLOOKUP($D38,BB_Input!$C$4:$C$163,BB_Input!$CY$4:$CY$163),"") -> 19672.015 | P38: =IFERROR(O38*(1+$M38),"") -> 21895.929 | Q38: =IFERROR(P38*(1+$M38),"") -> 24371.255 | R38: =IFERROR(Q38*(1+$M38),"") -> 27126.416 | S38: =IFERROR(R38*(1+$M38),"") -> 30193.047 | T38: =IFERROR(S38*(1+$M38),"") -> 33606.359
B39: =B38+1 -> 37 | C39: Tata Advanced Systems | D39: 4624679Z | F39: =_xlfn.XLOOKUP($D39,BB_Input!$C$4:$C$172,BB_Input!$G$4:$G$172) -> #N/A | M39: =_xlfn.XLOOKUP($D39,CCA_Defense!$D:$D,CCA_Defense!T:T) | N39: =_xlfn.XLOOKUP($D39,CCA_Defense!$D:$D,CCA_Defense!U:U) -> 0 | O39: =IFERROR(_xlfn.XLOOKUP($D39,BB_Input!$C$4:$C$163,BB_Input!$CY$4:$CY$163),"") | P39: =IFERROR(O39*(1+$M39),"") | Q39: =IFERROR(P39*(1+$M39),"") | R39: =IFERROR(Q39*(1+$M39),"") | S39: =IFERROR(R39*(1+$M39),"") | T39: =IFERROR(S39*(1+$M39),"")
B40: =B39+1 -> 38 | C40: Reliance Defence | D40: 1254332D | F40: =_xlfn.XLOOKUP($D40,BB_Input!$C$4:$C$172,BB_Input!$G$4:$G$172) -> #N/A | M40: =_xlfn.XLOOKUP($D40,CCA_Defense!$D:$D,CCA_Defense!T:T) | N40: =_xlfn.XLOOKUP($D40,CCA_Defense!$D:$D,CCA_Defense!U:U) -> 0 | O40: =IFERROR(_xlfn.XLOOKUP($D40,BB_Input!$C$4:$C$163,BB_Input!$CY$4:$CY$163),"") | P40: =IFERROR(O40*(1+$M40),"") | Q40: =IFERROR(P40*(1+$M40),"") | R40: =IFERROR(Q40*(1+$M40),"") | S40: =IFERROR(R40*(1+$M40),"") | T40: =IFERROR(S40*(1+$M40),"")
B41: =B40+1 -> 39 | C41: Aimtron Electronics | D41: AIMTRON | E41: AIMTRON | F41: =_xlfn.XLOOKUP($D41,BB_Input!$C$4:$C$172,BB_Input!$G$4:$G$172) -> 186.68179 | G41: =_xlfn.XLOOKUP($D41,CCA_Defense!$D:$D,CCA_Defense!M:M) -> 50.25 | H41: =_xlfn.XLOOKUP($D41,CCA_Defense!$D:$D,CCA_Defense!N:N) | I41: =_xlfn.XLOOKUP($D41,CCA_Defense!$D:$D,CCA_Defense!O:O) | J41: =_xlfn.XLOOKUP($D41,CCA_Defense!$D:$D,CCA_Defense!P:P) | K41: =_xlfn.XLOOKUP($D41,CCA_Defense!$D:$D,CCA_Defense!Q:Q) | L41: =_xlfn.XLOOKUP($D41,CCA_Defense!$D:$D,CCA_Defense!R:R) | M41: =_xlfn.XLOOKUP($D41,CCA_Defense!$D:$D,CCA_Defense!T:T) -> 0.43413497 | N41: =_xlfn.XLOOKUP($D41,CCA_Defense!$D:$D,CCA_Defense!U:U) -> 0 | O41: =IFERROR(_xlfn.XLOOKUP($D41,BB_Input!$C$4:$C$163,BB_Input!$CY$4:$CY$163),"") -> 1582.477 | P41: =IFERROR(O41*(1+$M41),"") -> 2269.4856 | Q41: =IFERROR(P41*(1+$M41),"") -> 3254.7487 | R41: =IFERROR(Q41*(1+$M41),"") -> 4667.7489 | S41: =IFERROR(R41*(1+$M41),"") -> 6694.182 | T41: =IFERROR(S41*(1+$M41),"") -> 9600.3605
B42: =B41+1 -> 40 | C42: Ashok Leyland | D42: AL | E42: ASHOKLEY | F42: =_xlfn.XLOOKUP($D42,BB_Input!$C$4:$C$172,BB_Input!$G$4:$G$172) -> 11472.119 | G42: =_xlfn.XLOOKUP($D42,CCA_Defense!$D:$D,CCA_Defense!M:M) -> 23.8 | H42: =_xlfn.XLOOKUP($D42,CCA_Defense!$D:$D,CCA_Defense!N:N) -> 35.802943 | I42: =_xlfn.XLOOKUP($D42,CCA_Defense!$D:$D,CCA_Defense!O:O) -> 31.385383 | J42: =_xlfn.XLOOKUP($D42,CCA_Defense!$D:$D,CCA_Defense!P:P) -> 28.046469 | K42: =_xlfn.XLOOKUP($D42,CCA_Defense!$D:$D,CCA_Defense!Q:Q) -> 26.82103 | L42: =_xlfn.XLOOKUP($D42,CCA_Defense!$D:$D,CCA_Defense!R:R) -> 26.146572 | M42: =_xlfn.XLOOKUP($D42,CCA_Defense!$D:$D,CCA_Defense!T:T) -> 0.081747729 | N42: =_xlfn.XLOOKUP($D42,CCA_Defense!$D:$D,CCA_Defense!U:U) -> 0 | O42: =IFERROR(_xlfn.XLOOKUP($D42,BB_Input!$C$4:$C$163,BB_Input!$CY$4:$CY$163),"") -> 483417.6 | P42: =IFERROR(O42*(1+$M42),"") -> 522935.89 | Q42: =IFERROR(P42*(1+$M42),"") -> 565684.71 | R42: =IFERROR(Q42*(1+$M42),"") -> 611928.15 | S42: =IFERROR(R42*(1+$M42),"") -> 661951.89 | T42: =IFERROR(S42*(1+$M42),"") -> 716064.95
B43: =B42+1 -> 41 | C43: CFF Fluid Control | D43: CFF | E43: CFF | F43: =_xlfn.XLOOKUP($D43,BB_Input!$C$4:$C$172,BB_Input!$G$4:$G$172) -> 127.45359 | G43: =_xlfn.XLOOKUP($D43,CCA_Defense!$D:$D,CCA_Defense!M:M) -> 48 | H43: =_xlfn.XLOOKUP($D43,CCA_Defense!$D:$D,CCA_Defense!N:N) -> 40.805416 | I43: =_xlfn.XLOOKUP($D43,CCA_Defense!$D:$D,CCA_Defense!O:O) -> 31.81151 | J43: =_xlfn.XLOOKUP($D43,CCA_Defense!$D:$D,CCA_Defense!P:P) -> 25.599945 | K43: =_xlfn.XLOOKUP($D43,CCA_Defense!$D:$D,CCA_Defense!Q:Q) -> 20.60126 | L43: =_xlfn.XLOOKUP($D43,CCA_Defense!$D:$D,CCA_Defense!R:R) -> 16.578626 | M43: =_xlfn.XLOOKUP($D43,CCA_Defense!$D:$D,CCA_Defense!T:T) -> 0.24263976 | N43: =_xlfn.XLOOKUP($D43,CCA_Defense!$D:$D,CCA_Defense!U:U) -> 0 | O43: =IFERROR(_xlfn.XLOOKUP($D43,BB_Input!$C$4:$C$163,BB_Input!$CY$4:$CY$163),"") -> 1455.605 | P43: =IFERROR(O43*(1+$M43),"") -> 1808.7926 | Q43: =IFERROR(P43*(1+$M43),"") -> 2247.6777 | R43: =IFERROR(Q43*(1+$M43),"") -> 2793.0536 | S43: =IFERROR(R43*(1+$M43),"") -> 3470.7595 | T43: =IFERROR(S43*(1+$M43),"") -> 4312.9037
B44: =B43+1 -> 42 | C44: DEE Development Engineers | D44: DEEDEV | E44: DEEDEV | F44: =_xlfn.XLOOKUP($D44,BB_Input!$C$4:$C$172,BB_Input!$G$4:$G$172) -> 169.74634 | G44: =_xlfn.XLOOKUP($D44,CCA_Defense!$D:$D,CCA_Defense!M:M) -> 48 | H44: =_xlfn.XLOOKUP($D44,CCA_Defense!$D:$D,CCA_Defense!N:N) -> 27.308231 | I44: =_xlfn.XLOOKUP($D44,CCA_Defense!$D:$D,CCA_Defense!O:O) -> 22.42773 | J44: =_xlfn.XLOOKUP($D44,CCA_Defense!$D:$D,CCA_Defense!P:P) -> 18.529108 | K44: =_xlfn.XLOOKUP($D44,CCA_Defense!$D:$D,CCA_Defense!Q:Q) -> 16.485737 | L44: =_xlfn.XLOOKUP($D44,CCA_Defense!$D:$D,CCA_Defense!R:R) -> 14.667707 | M44: =_xlfn.XLOOKUP($D44,CCA_Defense!$D:$D,CCA_Defense!T:T) -> 0.12394779 | N44: =_xlfn.XLOOKUP($D44,CCA_Defense!$D:$D,CCA_Defense!U:U) -> 0 | O44: =IFERROR(_xlfn.XLOOKUP($D44,BB_Input!$C$4:$C$163,BB_Input!$CY$4:$CY$163),"") -> 8273.622 | P44: =IFERROR(O44*(1+$M44),"") -> 9299.1191 | Q44: =IFERROR(P44*(1+$M44),"") -> 10451.724 | R44: =IFERROR(Q44*(1+$M44),"") -> 11747.192 | S44: =IFERROR(R44*(1+$M44),"") -> 13203.231 | T44: =IFERROR(S44*(1+$M44),"") -> 14839.742
B45: =B44+1 -> 43 | C45: Droneacharya Aerial Innovations | D45: DRONACHR | E45: DRONACHRYA | F45: =_xlfn.XLOOKUP($D45,BB_Input!$C$4:$C$172,BB_Input!$G$4:$G$172) -> 12.771906 | G45: =_xlfn.XLOOKUP($D45,CCA_Defense!$D:$D,CCA_Defense!M:M) -> 41 | H45: =_xlfn.XLOOKUP($D45,CCA_Defense!$D:$D,CCA_Defense!N:N) | I45: =_xlfn.XLOOKUP($D45,CCA_Defense!$D:$D,CCA_Defense!O:O) | J45: =_xlfn.XLOOKUP($D45,CCA_Defense!$D:$D,CCA_Defense!P:P) | K45: =_xlfn.XLOOKUP($D45,CCA_Defense!$D:$D,CCA_Defense!Q:Q) | L45: =_xlfn.XLOOKUP($D45,CCA_Defense!$D:$D,CCA_Defense!R:R) | M45: =_xlfn.XLOOKUP($D45,CCA_Defense!$D:$D,CCA_Defense!T:T) -> 0.8478498 | N45: =_xlfn.XLOOKUP($D45,CCA_Defense!$D:$D,CCA_Defense!U:U) -> 0 | O45: =IFERROR(_xlfn.XLOOKUP($D45,BB_Input!$C$4:$C$163,BB_Input!$CY$4:$CY$163),"") -> 345.189 | P45: =IFERROR(O45*(1+$M45),"") -> 637.85742 | Q45: =IFERROR(P45*(1+$M45),"") -> 1178.6647 | R45: =IFERROR(Q45*(1+$M45),"") -> 2177.9953 | S45: =IFERROR(R45*(1+$M45),"") -> 4024.6083 | T45: =IFERROR(S45*(1+$M45),"") -> 7436.8716
B46: =B45+1 -> 44 | C46: MTAR Technologies Ltd | D46: MTARTECH | E46: MTARTECH | F46: =_xlfn.XLOOKUP($D46,BB_Input!$C$4:$C$172,BB_Input!$G$4:$G$172) -> 839.81666 | G46: =_xlfn.XLOOKUP($D46,CCA_Defense!$D:$D,CCA_Defense!M:M) -> 89 | H46: =_xlfn.XLOOKUP($D46,CCA_Defense!$D:$D,CCA_Defense!N:N) -> 302.44683 | I46: =_xlfn.XLOOKUP($D46,CCA_Defense!$D:$D,CCA_Defense!O:O) -> 234.91016 | J46: =_xlfn.XLOOKUP($D46,CCA_Defense!$D:$D,CCA_Defense!P:P) -> 182.45449 | K46: =_xlfn.XLOOKUP($D46,CCA_Defense!$D:$D,CCA_Defense!Q:Q) -> 141.71223 | L46: =_xlfn.XLOOKUP($D46,CCA_Defense!$D:$D,CCA_Defense!R:R) -> 110.06775 | M46: =_xlfn.XLOOKUP($D46,CCA_Defense!$D:$D,CCA_Defense!T:T) -> 0.34490168 | N46: =_xlfn.XLOOKUP($D46,CCA_Defense!$D:$D,CCA_Defense!U:U) -> 0.25 | O46: =IFERROR(_xlfn.XLOOKUP($D46,BB_Input!$C$4:$C$163,BB_Input!$CY$4:$CY$163),"") -> 6646.46 | P46: =IFERROR(O46*(1+$N46),"") -> 8308.075 | Q46: =IFERROR(P46*(1+$N46),"") -> 10385.094 | R46: =IFERROR(Q46*(1+$N46),"") -> 12981.367 | S46: =IFERROR(R46*(1+$N46),"") -> 16226.709 | T46: =IFERROR(S46*(1+$N46),"") -> 20283.386
B47: =B46+1 -> 45 | C47: Godrej Aerospace | D47: 1436Z | F47: =_xlfn.XLOOKUP($D47,BB_Input!$C$4:$C$172,BB_Input!$G$4:$G$172) -> #N/A | M47: =_xlfn.XLOOKUP($D47,CCA_Defense!$D:$D,CCA_Defense!T:T) | N47: =_xlfn.XLOOKUP($D47,CCA_Defense!$D:$D,CCA_Defense!U:U) -> 0 | O47: =IFERROR(_xlfn.XLOOKUP($D47,BB_Input!$C$4:$C$163,BB_Input!$CY$4:$CY$163),"") | P47: =IFERROR(O47*(1+$M47),"") | Q47: =IFERROR(P47*(1+$M47),"") | R47: =IFERROR(Q47*(1+$M47),"") | S47: =IFERROR(R47*(1+$M47),"") | T47: =IFERROR(S47*(1+$M47),"")
B48: =B47+1 -> 46 | C48: HFCL | D48: HMFC | E48: HFCL | F48: =_xlfn.XLOOKUP($D48,BB_Input!$C$4:$C$172,BB_Input!$G$4:$G$172) -> 1032.4931 | G48: =_xlfn.XLOOKUP($D48,CCA_Defense!$D:$D,CCA_Defense!M:M) -> 70 | H48: =_xlfn.XLOOKUP($D48,CCA_Defense!$D:$D,CCA_Defense!N:N) | I48: =_xlfn.XLOOKUP($D48,CCA_Defense!$D:$D,CCA_Defense!O:O) | J48: =_xlfn.XLOOKUP($D48,CCA_Defense!$D:$D,CCA_Defense!P:P) | K48: =_xlfn.XLOOKUP($D48,CCA_Defense!$D:$D,CCA_Defense!Q:Q) | L48: =_xlfn.XLOOKUP($D48,CCA_Defense!$D:$D,CCA_Defense!R:R) | M48: =_xlfn.XLOOKUP($D48,CCA_Defense!$D:$D,CCA_Defense!T:T) -> -0.029945711 | N48: =_xlfn.XLOOKUP($D48,CCA_Defense!$D:$D,CCA_Defense!U:U) -> 0 | O48: =IFERROR(_xlfn.XLOOKUP($D48,BB_Input!$C$4:$C$163,BB_Input!$CY$4:$CY$163),"") -> 40645.2 | P48: =IFERROR(O48*(1+$M48),"") -> 39428.051 | Q48: =IFERROR(P48*(1+$M48),"") -> 38247.35 | R48: =IFERROR(Q48*(1+$M48),"") -> 37102.005 | S48: =IFERROR(R48*(1+$M48),"") -> 35990.96 | T48: =IFERROR(S48*(1+$M48),"") -> 34913.185
B49: =B48+1 -> 47 | C49: High Energy Batteries (India) | D49: HIGH | E49: HIGHEEBAT | F49: =_xlfn.XLOOKUP($D49,BB_Input!$C$4:$C$172,BB_Input!$G$4:$G$172) -> 54.330874 | G49: =_xlfn.XLOOKUP($D49,CCA_Defense!$D:$D,CCA_Defense!M:M) -> 45 | H49: =_xlfn.XLOOKUP($D49,CCA_Defense!$D:$D,CCA_Defense!N:N) -> 33.478578 | I49: =_xlfn.XLOOKUP($D49,CCA_Defense!$D:$D,CCA_Defense!O:O) -> 33.40627 | J49: =_xlfn.XLOOKUP($D49,CCA_Defense!$D:$D,CCA_Defense!P:P) -> 34.286521 | K49: =_xlfn.XLOOKUP($D49,CCA_Defense!$D:$D,CCA_Defense!Q:Q) -> 35.218716 | L49: =_xlfn.XLOOKUP($D49,CCA_Defense!$D:$D,CCA_Defense!R:R) -> 35.142649 | M49: =_xlfn.XLOOKUP($D49,CCA_Defense!$D:$D,CCA_Defense!T:T) -> 0.0021645224 | N49: =_xlfn.XLOOKUP($D49,CCA_Defense!$D:$D,CCA_Defense!U:U) -> 0 | O49: =IFERROR(_xlfn.XLOOKUP($D49,BB_Input!$C$4:$C$163,BB_Input!$CY$4:$CY$163),"") -> 807.522 | P49: =IFERROR(O49*(1+$M49),"") -> 809.2699 | Q49: =IFERROR(P49*(1+$M49),"") -> 811.02158 | R49: =IFERROR(Q49*(1+$M49),"") -> 812.77706 | S49: =IFERROR(R49*(1+$M49),"") -> 814.53633 | T49: =IFERROR(S49*(1+$M49),"") -> 816.29941
B50: =B49+1 -> 48 | C50: Premier Explosives Ltd | D50: PRE | E50: PREMEXPLN | F50: =_xlfn.XLOOKUP($D50,BB_Input!$C$4:$C$172,BB_Input!$G$4:$G$172) -> 308.39378 | G50: =_xlfn.XLOOKUP($D50,CCA_Defense!$D:$D,CCA_Defense!M:M) -> 77 | H50: =_xlfn.XLOOKUP($D50,CCA_Defense!$D:$D,CCA_Defense!N:N) -> 43.697925 | I50: =_xlfn.XLOOKUP($D50,CCA_Defense!$D:$D,CCA_Defense!O:O) -> 36.502349 | J50: =_xlfn.XLOOKUP($D50,CCA_Defense!$D:$D,CCA_Defense!P:P) -> 30.491642 | K50: =_xlfn.XLOOKUP($D50,CCA_Defense!$D:$D,CCA_Defense!Q:Q) -> 25.470696 | L50: =_xlfn.XLOOKUP($D50,CCA_Defense!$D:$D,CCA_Defense!R:R) -> 21.276531 | M50: =_xlfn.XLOOKUP($D50,CCA_Defense!$D:$D,CCA_Defense!T:T) -> 0.16894796 | N50: =_xlfn.XLOOKUP($D50,CCA_Defense!$D:$D,CCA_Defense!U:U) -> 0.1912 | O50: =IFERROR(_xlfn.XLOOKUP($D50,BB_Input!$C$4:$C$163,BB_Input!$CY$4:$CY$163),"") -> 4174.523 | P50: =IFERROR(O50*(1+$N50),"") -> 4972.6918 | Q50: =IFERROR(P50*(1+$N50),"") -> 5923.4705 | R50: =IFERROR(Q50*(1+$N50),"") -> 7056.038 | S50: =IFERROR(R50*(1+$N50),"") -> 8405.1525 | T50: =IFERROR(S50*(1+$N50),"") -> 10012.218
B51: =B50+1 -> 49 | C51: Marine Electricals (India) | D51: MARINE | E51: MARINE | F51: =_xlfn.XLOOKUP($D51,BB_Input!$C$4:$C$172,BB_Input!$G$4:$G$172) -> 324.63404 | G51: =_xlfn.XLOOKUP($D51,CCA_Defense!$D:$D,CCA_Defense!M:M) -> 73 | H51: =_xlfn.XLOOKUP($D51,CCA_Defense!$D:$D,CCA_Defense!N:N) | I51: =_xlfn.XLOOKUP($D51,CCA_Defense!$D:$D,CCA_Defense!O:O) | J51: =_xlfn.XLOOKUP($D51,CCA_Defense!$D:$D,CCA_Defense!P:P) | K51: =_xlfn.XLOOKUP($D51,CCA_Defense!$D:$D,CCA_Defense!Q:Q) | L51: =_xlfn.XLOOKUP($D51,CCA_Defense!$D:$D,CCA_Defense!R:R) | M51: =_xlfn.XLOOKUP($D51,CCA_Defense!$D:$D,CCA_Defense!T:T) -> 0.15342351 | N51: =_xlfn.XLOOKUP($D51,CCA_Defense!$D:$D,CCA_Defense!U:U) -> 0 | O51: =IFERROR(_xlfn.XLOOKUP($D51,BB_Input!$C$4:$C$163,BB_Input!$CY$4:$CY$163),"") -> 7670.953 | P51: =IFERROR(O51*(1+$M51),"") -> 8847.8575 | Q51: =IFERROR(P51*(1+$M51),"") -> 10205.327 | R51: =IFERROR(Q51*(1+$M51),"") -> 11771.064 | S51: =IFERROR(R51*(1+$M51),"") -> 13577.022 | T51: =IFERROR(S51*(1+$M51),"") -> 15660.056
B52: =B51+1 -> 50 | C52: Lokesh Machines | D52: LOKM | E52: LOKESHMACH | F52: =_xlfn.XLOOKUP($D52,BB_Input!$C$4:$C$172,BB_Input!$G$4:$G$172) -> 36.711698 | G52: =_xlfn.XLOOKUP($D52,CCA_Defense!$D:$D,CCA_Defense!M:M) -> 518 | H52: =_xlfn.XLOOKUP($D52,CCA_Defense!$D:$D,CCA_Defense!N:N) -> 140.75056 | I52: =_xlfn.XLOOKUP($D52,CCA_Defense!$D:$D,CCA_Defense!O:O) -> 138.65048 | J52: =_xlfn.XLOOKUP($D52,CCA_Defense!$D:$D,CCA_Defense!P:P) -> 136.58174 | K52: =_xlfn.XLOOKUP($D52,CCA_Defense!$D:$D,CCA_Defense!Q:Q) -> 134.54386 | L52: =_xlfn.XLOOKUP($D52,CCA_Defense!$D:$D,CCA_Defense!R:R) -> 132.53639 | M52: =_xlfn.XLOOKUP($D52,CCA_Defense!$D:$D,CCA_Defense!T:T) -> 0.025400566 | N52: =_xlfn.XLOOKUP($D52,CCA_Defense!$D:$D,CCA_Defense!U:U) -> 0 | O52: =IFERROR(_xlfn.XLOOKUP($D52,BB_Input!$C$4:$C$163,BB_Input!$CY$4:$CY$163),"") -> 2283.216 | P52: =IFERROR(O52*(1+$M52),"") -> 2341.211 | Q52: =IFERROR(P52*(1+$M52),"") -> 2400.6791 | R52: =IFERROR(Q52*(1+$M52),"") -> 2461.6577 | S52: =IFERROR(R52*(1+$M52),"") -> 2524.1852 | T52: =IFERROR(S52*(1+$M52),"") -> 2588.3009
B53: =B52+1 -> 51 | C53: Swan Energy | D53: SWANCORP | E53: SWANENERGY | F53: =_xlfn.XLOOKUP($D53,BB_Input!$C$4:$C$172,BB_Input!$G$4:$G$172) -> 1616.1622 | G53: =_xlfn.XLOOKUP($D53,CCA_Defense!$D:$D,CCA_Defense!M:M) -> 17.8 | H53: =_xlfn.XLOOKUP($D53,CCA_Defense!$D:$D,CCA_Defense!N:N) -> 15.83296 | I53: =_xlfn.XLOOKUP($D53,CCA_Defense!$D:$D,CCA_Defense!O:O) -> 13.454308 | J53: =_xlfn.XLOOKUP($D53,CCA_Defense!$D:$D,CCA_Defense!P:P) -> 10.732277 | K53: =_xlfn.XLOOKUP($D53,CCA_Defense!$D:$D,CCA_Defense!Q:Q) -> 9.1199217 | L53: =_xlfn.XLOOKUP($D53,CCA_Defense!$D:$D,CCA_Defense!R:R) -> 7.5076161 | M53: =_xlfn.XLOOKUP($D53,CCA_Defense!$D:$D,CCA_Defense!T:T) -> 0.58931627 | N53: =_xlfn.XLOOKUP($D53,CCA_Defense!$D:$D,CCA_Defense!U:U) -> 0 | O53: =IFERROR(_xlfn.XLOOKUP($D53,BB_Input!$C$4:$C$163,BB_Input!$CY$4:$CY$163),"") -> 49378.686 | P53: =IFERROR(O53*(1+$M53),"") -> 78478.349 | Q53: =IFERROR(P53*(1+$M53),"") -> 124726.92 | R53: =IFERROR(Q53*(1+$M53),"") -> 198230.52 | S53: =IFERROR(R53*(1+$M53),"") -> 315050.99 | T53: =IFERROR(S53*(1+$M53),"") -> 500715.66
B54: =B53+1 -> 52 | C54: Walchandnagar Industries | D54: WI | E54: WALCHANNAG | F54: =_xlfn.XLOOKUP($D54,BB_Input!$C$4:$C$172,BB_Input!$G$4:$G$172) -> 147.71937 | G54: =_xlfn.XLOOKUP($D54,CCA_Defense!$D:$D,CCA_Defense!M:M) -> 0 | H54: =_xlfn.XLOOKUP($D54,CCA_Defense!$D:$D,CCA_Defense!N:N) | I54: =_xlfn.XLOOKUP($D54,CCA_Defense!$D:$D,CCA_Defense!O:O) | J54: =_xlfn.XLOOKUP($D54,CCA_Defense!$D:$D,CCA_Defense!P:P) -> 371.6376 | K54: =_xlfn.XLOOKUP($D54,CCA_Defense!$D:$D,CCA_Defense!Q:Q) -> 229.45656 | L54: =_xlfn.XLOOKUP($D54,CCA_Defense!$D:$D,CCA_Defense!R:R) -> 196.76544 | M54: =_xlfn.XLOOKUP($D54,CCA_Defense!$D:$D,CCA_Defense!T:T) -> -0.028214491 | N54: =_xlfn.XLOOKUP($D54,CCA_Defense!$D:$D,CCA_Defense!U:U) -> 0 | O54: =IFERROR(_xlfn.XLOOKUP($D54,BB_Input!$C$4:$C$163,BB_Input!$CY$4:$CY$163),"") -> 2591.8 | P54: =IFERROR(O54*(1+$M54),"") -> 2518.6737 | Q54: =IFERROR(P54*(1+$M54),"") -> 2447.6106 | R54: =IFERROR(Q54*(1+$M54),"") -> 2378.5525 | S54: =IFERROR(R54*(1+$M54),"") -> 2311.4429 | T54: =IFERROR(S54*(1+$M54),"") -> 2246.2267
B55: =B54+1 -> 53 | C55: Advance Weapon Equipment India | D55: 1943634D | F55: =_xlfn.XLOOKUP($D55,BB_Input!$C$4:$C$172,BB_Input!$G$4:$G$172) -> #N/A | M55: =_xlfn.XLOOKUP($D55,CCA_Defense!$D:$D,CCA_Defense!T:T) | N55: =_xlfn.XLOOKUP($D55,CCA_Defense!$D:$D,CCA_Defense!U:U) -> 0 | O55: =IFERROR(_xlfn.XLOOKUP($D55,BB_Input!$C$4:$C$163,BB_Input!$CY$4:$CY$163),"") | P55: =IFERROR(O55*(1+$M55),"") | Q55: =IFERROR(P55*(1+$M55),"") | R55: =IFERROR(Q55*(1+$M55),"") | S55: =IFERROR(R55*(1+$M55),"") | T55: =IFERROR(S55*(1+$M55),"")
B56: =B55+1 -> 54 | C56: Armoured Vehicles Nigam | D56: 2300472D | F56: =_xlfn.XLOOKUP($D56,BB_Input!$C$4:$C$172,BB_Input!$G$4:$G$172) -> #N/A | M56: =_xlfn.XLOOKUP($D56,CCA_Defense!$D:$D,CCA_Defense!T:T) | N56: =_xlfn.XLOOKUP($D56,CCA_Defense!$D:$D,CCA_Defense!U:U) -> 0 | O56: =IFERROR(_xlfn.XLOOKUP($D56,BB_Input!$C$4:$C$163,BB_Input!$CY$4:$CY$163),"") | P56: =IFERROR(O56*(1+$M56),"") | Q56: =IFERROR(P56*(1+$M56),"") | R56: =IFERROR(Q56*(1+$M56),"") | S56: =IFERROR(R56*(1+$M56),"") | T56: =IFERROR(S56*(1+$M56),"")
B57: =B56+1 -> 55 | C57: Artemon Aerospace | D57: 1637857D | F57: =_xlfn.XLOOKUP($D57,BB_Input!$C$4:$C$172,BB_Input!$G$4:$G$172) -> #N/A | M57: =_xlfn.XLOOKUP($D57,CCA_Defense!$D:$D,CCA_Defense!T:T) | N57: =_xlfn.XLOOKUP($D57,CCA_Defense!$D:$D,CCA_Defense!U:U) -> 0 | O57: =IFERROR(_xlfn.XLOOKUP($D57,BB_Input!$C$4:$C$163,BB_Input!$CY$4:$CY$163),"") | P57: =IFERROR(O57*(1+$M57),"") | Q57: =IFERROR(P57*(1+$M57),"") | R57: =IFERROR(Q57*(1+$M57),"") | S57: =IFERROR(R57*(1+$M57),"") | T57: =IFERROR(S57*(1+$M57),"")
B58: =B57+1 -> 56 | C58: Gliders India | D58: 0824100D | F58: =_xlfn.XLOOKUP($D58,BB_Input!$C$4:$C$172,BB_Input!$G$4:$G$172) -> #N/A | M58: =_xlfn.XLOOKUP($D58,CCA_Defense!$D:$D,CCA_Defense!T:T) | N58: =_xlfn.XLOOKUP($D58,CCA_Defense!$D:$D,CCA_Defense!U:U) -> 0 | O58: =IFERROR(_xlfn.XLOOKUP($D58,BB_Input!$C$4:$C$163,BB_Input!$CY$4:$CY$163),"") | P58: =IFERROR(O58*(1+$M58),"") | Q58: =IFERROR(P58*(1+$M58),"") | R58: =IFERROR(Q58*(1+$M58),"") | S58: =IFERROR(R58*(1+$M58),"") | T58: =IFERROR(S58*(1+$M58),"")
B59: =B58+1 -> 57 | C59: Goa Shipyard | D59: 7559676Z | F59: =_xlfn.XLOOKUP($D59,BB_Input!$C$4:$C$172,BB_Input!$G$4:$G$172) -> #N/A | M59: =_xlfn.XLOOKUP($D59,CCA_Defense!$D:$D,CCA_Defense!T:T) | N59: =_xlfn.XLOOKUP($D59,CCA_Defense!$D:$D,CCA_Defense!U:U) -> 0 | O59: =IFERROR(_xlfn.XLOOKUP($D59,BB_Input!$C$4:$C$163,BB_Input!$CY$4:$CY$163),"") | P59: =IFERROR(O59*(1+$M59),"") | Q59: =IFERROR(P59*(1+$M59),"") | R59: =IFERROR(Q59*(1+$M59),"") | S59: =IFERROR(R59*(1+$M59),"") | T59: =IFERROR(S59*(1+$M59),"")
B60: =B59+1 -> 58 | C60: Hindustan Shipyard | D60: 6595300Z | F60: =_xlfn.XLOOKUP($D60,BB_Input!$C$4:$C$172,BB_Input!$G$4:$G$172) -> #N/A | M60: =_xlfn.XLOOKUP($D60,CCA_Defense!$D:$D,CCA_Defense!T:T) | N60: =_xlfn.XLOOKUP($D60,CCA_Defense!$D:$D,CCA_Defense!U:U) -> 0 | O60: =IFERROR(_xlfn.XLOOKUP($D60,BB_Input!$C$4:$C$163,BB_Input!$CY$4:$CY$163),"") | P60: =IFERROR(O60*(1+$M60),"") | Q60: =IFERROR(P60*(1+$M60),"") | R60: =IFERROR(Q60*(1+$M60),"") | S60: =IFERROR(R60*(1+$M60),"") | T60: =IFERROR(S60*(1+$M60),"")
B61: =B60+1 -> 59 | C61: India Optel | D61: 1633945D | F61: =_xlfn.XLOOKUP($D61,BB_Input!$C$4:$C$172,BB_Input!$G$4:$G$172) -> #N/A | M61: =_xlfn.XLOOKUP($D61,CCA_Defense!$D:$D,CCA_Defense!T:T) | N61: =_xlfn.XLOOKUP($D61,CCA_Defense!$D:$D,CCA_Defense!U:U) -> 0 | O61: =IFERROR(_xlfn.XLOOKUP($D61,BB_Input!$C$4:$C$163,BB_Input!$CY$4:$CY$163),"") | P61: =IFERROR(O61*(1+$M61),"") | Q61: =IFERROR(P61*(1+$M61),"") | R61: =IFERROR(Q61*(1+$M61),"") | S61: =IFERROR(R61*(1+$M61),"") | T61: =IFERROR(S61*(1+$M61),"")
B62: =B61+1 -> 60 | C62: Munitions India | D62: 1943632D | F62: =_xlfn.XLOOKUP($D62,BB_Input!$C$4:$C$172,BB_Input!$G$4:$G$172) -> #N/A | M62: =_xlfn.XLOOKUP($D62,CCA_Defense!$D:$D,CCA_Defense!T:T) | N62: =_xlfn.XLOOKUP($D62,CCA_Defense!$D:$D,CCA_Defense!U:U) -> 0 | O62: =IFERROR(_xlfn.XLOOKUP($D62,BB_Input!$C$4:$C$163,BB_Input!$CY$4:$CY$163),"") | P62: =IFERROR(O62*(1+$M62),"") | Q62: =IFERROR(P62*(1+$M62),"") | R62: =IFERROR(Q62*(1+$M62),"") | S62: =IFERROR(R62*(1+$M62),"") | T62: =IFERROR(S62*(1+$M62),"")
B63: =B62+1 -> 61 | C63: Raychem RPG | D63: 1315Z | F63: =_xlfn.XLOOKUP($D63,BB_Input!$C$4:$C$172,BB_Input!$G$4:$G$172) -> #N/A | M63: =_xlfn.XLOOKUP($D63,CCA_Defense!$D:$D,CCA_Defense!T:T) | N63: =_xlfn.XLOOKUP($D63,CCA_Defense!$D:$D,CCA_Defense!U:U) -> 0 | O63: =IFERROR(_xlfn.XLOOKUP($D63,BB_Input!$C$4:$C$163,BB_Input!$CY$4:$CY$163),"") | P63: =IFERROR(O63*(1+$M63),"") | Q63: =IFERROR(P63*(1+$M63),"") | R63: =IFERROR(Q63*(1+$M63),"") | S63: =IFERROR(R63*(1+$M63),"") | T63: =IFERROR(S63*(1+$M63),"")
B64: =B63+1 -> 62 | C64: Sagar Defence and Engineering Private | D64: 2250224D | F64: =_xlfn.XLOOKUP($D64,BB_Input!$C$4:$C$172,BB_Input!$G$4:$G$172) -> #N/A | M64: =_xlfn.XLOOKUP($D64,CCA_Defense!$D:$D,CCA_Defense!T:T) | N64: =_xlfn.XLOOKUP($D64,CCA_Defense!$D:$D,CCA_Defense!U:U) -> 0 | O64: =IFERROR(_xlfn.XLOOKUP($D64,BB_Input!$C$4:$C$163,BB_Input!$CY$4:$CY$163),"") | P64: =IFERROR(O64*(1+$M64),"") | Q64: =IFERROR(P64*(1+$M64),"") | R64: =IFERROR(Q64*(1+$M64),"") | S64: =IFERROR(R64*(1+$M64),"") | T64: =IFERROR(S64*(1+$M64),"")
B65: =B64+1 -> 63 | C65: Troop Comforts | D65: 1359165D | F65: =_xlfn.XLOOKUP($D65,BB_Input!$C$4:$C$172,BB_Input!$G$4:$G$172) -> #N/A | M65: =_xlfn.XLOOKUP($D65,CCA_Defense!$D:$D,CCA_Defense!T:T) | N65: =_xlfn.XLOOKUP($D65,CCA_Defense!$D:$D,CCA_Defense!U:U) -> 0 | O65: =IFERROR(_xlfn.XLOOKUP($D65,BB_Input!$C$4:$C$163,BB_Input!$CY$4:$CY$163),"") | P65: =IFERROR(O65*(1+$M65),"") | Q65: =IFERROR(P65*(1+$M65),"") | R65: =IFERROR(Q65*(1+$M65),"") | S65: =IFERROR(R65*(1+$M65),"") | T65: =IFERROR(S65*(1+$M65),"")
B66: =B65+1 -> 64 | C66: Vijayan Trishul Defence Solutions | D66: 2582619D | F66: =_xlfn.XLOOKUP($D66,BB_Input!$C$4:$C$172,BB_Input!$G$4:$G$172) -> #N/A | M66: =_xlfn.XLOOKUP($D66,CCA_Defense!$D:$D,CCA_Defense!T:T) | N66: =_xlfn.XLOOKUP($D66,CCA_Defense!$D:$D,CCA_Defense!U:U) -> 0 | O66: =IFERROR(_xlfn.XLOOKUP($D66,BB_Input!$C$4:$C$163,BB_Input!$CY$4:$CY$163),"") | P66: =IFERROR(O66*(1+$M66),"") | Q66: =IFERROR(P66*(1+$M66),"") | R66: =IFERROR(Q66*(1+$M66),"") | S66: =IFERROR(R66*(1+$M66),"") | T66: =IFERROR(S66*(1+$M66),"")
B67: =B66+1 -> 65 | C67: Yantra India | D67: 1943633D | F67: =_xlfn.XLOOKUP($D67,BB_Input!$C$4:$C$172,BB_Input!$G$4:$G$172) -> #N/A | M67: =_xlfn.XLOOKUP($D67,CCA_Defense!$D:$D,CCA_Defense!T:T) | N67: =_xlfn.XLOOKUP($D67,CCA_Defense!$D:$D,CCA_Defense!U:U) -> 0 | O67: =IFERROR(_xlfn.XLOOKUP($D67,BB_Input!$C$4:$C$163,BB_Input!$CY$4:$CY$163),"") | P67: =IFERROR(O67*(1+$M67),"") | Q67: =IFERROR(P67*(1+$M67),"") | R67: =IFERROR(Q67*(1+$M67),"") | S67: =IFERROR(R67*(1+$M67),"") | T67: =IFERROR(S67*(1+$M67),"")
B68: =B67+1 -> 66 | C68: Sail Ltd | D68: SAIL | E68: SAIL | F68: =_xlfn.XLOOKUP($D68,BB_Input!$C$4:$C$172,BB_Input!$G$4:$G$172) -> 6066.7163 | G68: =_xlfn.XLOOKUP($D68,CCA_Defense!$D:$D,CCA_Defense!M:M) -> 23.7 | H68: =_xlfn.XLOOKUP($D68,CCA_Defense!$D:$D,CCA_Defense!N:N) -> 15.589056 | I68: =_xlfn.XLOOKUP($D68,CCA_Defense!$D:$D,CCA_Defense!O:O) -> 12.706685 | J68: =_xlfn.XLOOKUP($D68,CCA_Defense!$D:$D,CCA_Defense!P:P) -> 11.629351 | K68: =_xlfn.XLOOKUP($D68,CCA_Defense!$D:$D,CCA_Defense!Q:Q) -> 12.473984 | L68: =_xlfn.XLOOKUP($D68,CCA_Defense!$D:$D,CCA_Defense!R:R) | M68: =_xlfn.XLOOKUP($D68,CCA_Defense!$D:$D,CCA_Defense!T:T) -> -0.0020937533 | N68: =_xlfn.XLOOKUP($D68,CCA_Defense!$D:$D,CCA_Defense!U:U) -> 0 | O68: =IFERROR(_xlfn.XLOOKUP($D68,BB_Input!$C$4:$C$163,BB_Input!$CY$4:$CY$163),"") -> 1017402.6 | P68: =IFERROR(O68*(1+$M68),"") -> 1015272.4 | Q68: =IFERROR(P68*(1+$M68),"") -> 1013146.7 | R68: =IFERROR(Q68*(1+$M68),"") -> 1011025.4 | S68: =IFERROR(R68*(1+$M68),"") -> 1008908.6 | T68: =IFERROR(S68*(1+$M68),"") -> 1006796.2
B69: =B68+1 -> 67 | C69: Rossell Techsys Ltd | D69: ROSSTECH | E69: ROSSTECH | F69: =_xlfn.XLOOKUP($D69,BB_Input!$C$4:$C$172,BB_Input!$G$4:$G$172) -> 266.42668 | G69: =_xlfn.XLOOKUP($D69,CCA_Defense!$D:$D,CCA_Defense!M:M) -> 353 | H69: =_xlfn.XLOOKUP($D69,CCA_Defense!$D:$D,CCA_Defense!N:N) -> 77.575308 | I69: =_xlfn.XLOOKUP($D69,CCA_Defense!$D:$D,CCA_Defense!O:O) -> 72.408744 | J69: =_xlfn.XLOOKUP($D69,CCA_Defense!$D:$D,CCA_Defense!P:P) -> 67.586277 | K69: =_xlfn.XLOOKUP($D69,CCA_Defense!$D:$D,CCA_Defense!Q:Q) -> 63.084989 | L69: =_xlfn.XLOOKUP($D69,CCA_Defense!$D:$D,CCA_Defense!R:R) -> 58.88349 | M69: =_xlfn.XLOOKUP($D69,CCA_Defense!$D:$D,CCA_Defense!T:T) -> 0.10286313 | N69: =_xlfn.XLOOKUP($D69,CCA_Defense!$D:$D,CCA_Defense!U:U) -> 0 | O69: =IFERROR(_xlfn.XLOOKUP($D69,BB_Input!$C$4:$C$163,BB_Input!$CY$4:$CY$163),"") -> 7593.819 | P69: =IFERROR(O69*(1+$M69),"") -> 8374.943 | Q69: =IFERROR(P69*(1+$M69),"") -> 9236.4159 | R69: =IFERROR(Q69*(1+$M69),"") -> 10186.503 | S69: =IFERROR(R69*(1+$M69),"") -> 11234.318 | T69: =IFERROR(S69*(1+$M69),"") -> 12389.915
B70: =B69+1 -> 68 | C70: Mahindra Defence Systems | D70: 1313978D | F70: =_xlfn.XLOOKUP($D70,BB_Input!$C$4:$C$172,BB_Input!$G$4:$G$172) -> #N/A | M70: =_xlfn.XLOOKUP($D70,CCA_Defense!$D:$D,CCA_Defense!T:T) | N70: =_xlfn.XLOOKUP($D70,CCA_Defense!$D:$D,CCA_Defense!U:U) -> 0 | O70: =IFERROR(_xlfn.XLOOKUP($D70,BB_Input!$C$4:$C$163,BB_Input!$CY$4:$CY$163),"") | P70: =IFERROR(O70*(1+$M70),"") | Q70: =IFERROR(P70*(1+$M70),"") | R70: =IFERROR(Q70*(1+$M70),"") | S70: =IFERROR(R70*(1+$M70),"") | T70: =IFERROR(S70*(1+$M70),"")
B71: =B70+1 -> 69 | C71: Brahmos Aerospace | D71: 2339955Z | F71: =_xlfn.XLOOKUP($D71,BB_Input!$C$4:$C$172,BB_Input!$G$4:$G$172) -> #N/A | M71: =_xlfn.XLOOKUP($D71,CCA_Defense!$D:$D,CCA_Defense!T:T) | N71: =_xlfn.XLOOKUP($D71,CCA_Defense!$D:$D,CCA_Defense!U:U) -> 0 | O71: =IFERROR(_xlfn.XLOOKUP($D71,BB_Input!$C$4:$C$163,BB_Input!$CY$4:$CY$163),"") | P71: =IFERROR(O71*(1+$M71),"") | Q71: =IFERROR(P71*(1+$M71),"") | R71: =IFERROR(Q71*(1+$M71),"") | S71: =IFERROR(R71*(1+$M71),"") | T71: =IFERROR(S71*(1+$M71),"")
B72: =B71+1 -> 70 | C72: MKU Ltd | D72: 1471388D | F72: =_xlfn.XLOOKUP($D72,BB_Input!$C$4:$C$172,BB_Input!$G$4:$G$172) -> #N/A | M72: =_xlfn.XLOOKUP($D72,CCA_Defense!$D:$D,CCA_Defense!T:T) | N72: =_xlfn.XLOOKUP($D72,CCA_Defense!$D:$D,CCA_Defense!U:U) -> 0 | O72: =IFERROR(_xlfn.XLOOKUP($D72,BB_Input!$C$4:$C$163,BB_Input!$CY$4:$CY$163),"") | P72: =IFERROR(O72*(1+$M72),"") | Q72: =IFERROR(P72*(1+$M72),"") | R72: =IFERROR(Q72*(1+$M72),"") | S72: =IFERROR(R72*(1+$M72),"") | T72: =IFERROR(S72*(1+$M72),"")
B73: =B72+1 -> 71 | C73: Samtel Avionics | D73: 6594164Z | F73: =_xlfn.XLOOKUP($D73,BB_Input!$C$4:$C$172,BB_Input!$G$4:$G$172) -> #N/A | M73: =_xlfn.XLOOKUP($D73,CCA_Defense!$D:$D,CCA_Defense!T:T) | N73: =_xlfn.XLOOKUP($D73,CCA_Defense!$D:$D,CCA_Defense!U:U) -> 0 | O73: =IFERROR(_xlfn.XLOOKUP($D73,BB_Input!$C$4:$C$163,BB_Input!$CY$4:$CY$163),"") | P73: =IFERROR(O73*(1+$M73),"") | Q73: =IFERROR(P73*(1+$M73),"") | R73: =IFERROR(Q73*(1+$M73),"") | S73: =IFERROR(R73*(1+$M73),"") | T73: =IFERROR(S73*(1+$M73),"")
B74: =B73+1 -> 72 | C74: Tonbo Imaging | D74: 1537114D | F74: =_xlfn.XLOOKUP($D74,BB_Input!$C$4:$C$172,BB_Input!$G$4:$G$172) -> #N/A | M74: =_xlfn.XLOOKUP($D74,CCA_Defense!$D:$D,CCA_Defense!T:T) | N74: =_xlfn.XLOOKUP($D74,CCA_Defense!$D:$D,CCA_Defense!U:U) -> 0 | O74: =IFERROR(_xlfn.XLOOKUP($D74,BB_Input!$C$4:$C$163,BB_Input!$CY$4:$CY$163),"") | P74: =IFERROR(O74*(1+$M74),"") | Q74: =IFERROR(P74*(1+$M74),"") | R74: =IFERROR(Q74*(1+$M74),"") | S74: =IFERROR(R74*(1+$M74),"") | T74: =IFERROR(S74*(1+$M74),"")
B75: =B74+1 -> 73 | C75: VEM Technologies | D75: 0496525D | F75: =_xlfn.XLOOKUP($D75,BB_Input!$C$4:$C$172,BB_Input!$G$4:$G$172) -> #N/A | M75: =_xlfn.XLOOKUP($D75,CCA_Defense!$D:$D,CCA_Defense!T:T) | N75: =_xlfn.XLOOKUP($D75,CCA_Defense!$D:$D,CCA_Defense!U:U) -> 0 | O75: =IFERROR(_xlfn.XLOOKUP($D75,BB_Input!$C$4:$C$163,BB_Input!$CY$4:$CY$163),"") | P75: =IFERROR(O75*(1+$M75),"") | Q75: =IFERROR(P75*(1+$M75),"") | R75: =IFERROR(Q75*(1+$M75),"") | S75: =IFERROR(R75*(1+$M75),"") | T75: =IFERROR(S75*(1+$M75),"")
B76: =B75+1 -> 74 | C76: Alpha Design Technologies | D76: 1606516D | F76: =_xlfn.XLOOKUP($D76,BB_Input!$C$4:$C$172,BB_Input!$G$4:$G$172) -> #N/A | M76: =_xlfn.XLOOKUP($D76,CCA_Defense!$D:$D,CCA_Defense!T:T) | N76: =_xlfn.XLOOKUP($D76,CCA_Defense!$D:$D,CCA_Defense!U:U) -> 0 | O76: =IFERROR(_xlfn.XLOOKUP($D76,BB_Input!$C$4:$C$163,BB_Input!$CY$4:$CY$163),"") | P76: =IFERROR(O76*(1+$M76),"") | Q76: =IFERROR(P76*(1+$M76),"") | R76: =IFERROR(Q76*(1+$M76),"") | S76: =IFERROR(R76*(1+$M76),"") | T76: =IFERROR(S76*(1+$M76),"")
B77: =B76+1 -> 75 | C77: Unimech Aerospace & Manufacturing Ltd | D77: UNIMECH | E77: UNIMECH | F77: =_xlfn.XLOOKUP($D77,BB_Input!$C$4:$C$172,BB_Input!$G$4:$G$172) -> 528.31031 | G77: =_xlfn.XLOOKUP($D77,CCA_Defense!$D:$D,CCA_Defense!M:M) -> 64 | H77: =_xlfn.XLOOKUP($D77,CCA_Defense!$D:$D,CCA_Defense!N:N) -> 68.982587 | I77: =_xlfn.XLOOKUP($D77,CCA_Defense!$D:$D,CCA_Defense!O:O) -> 40.407863 | J77: =_xlfn.XLOOKUP($D77,CCA_Defense!$D:$D,CCA_Defense!P:P) -> 23.669674 | K77: =_xlfn.XLOOKUP($D77,CCA_Defense!$D:$D,CCA_Defense!Q:Q) -> 13.864962 | L77: =_xlfn.XLOOKUP($D77,CCA_Defense!$D:$D,CCA_Defense!R:R) -> 8.1216651 | M77: =_xlfn.XLOOKUP($D77,CCA_Defense!$D:$D,CCA_Defense!T:T) -> 0.70715754 | N77: =_xlfn.XLOOKUP($D77,CCA_Defense!$D:$D,CCA_Defense!U:U) -> 0.375 | O77: =IFERROR(_xlfn.XLOOKUP($D77,BB_Input!$C$4:$C$163,BB_Input!$CY$4:$CY$163),"") -> 2429.258 | P77: =IFERROR(O77*(1+$N77),"") -> 3340.2297 | Q77: =IFERROR(P77*(1+$N77),"") -> 4592.8159 | R77: =IFERROR(Q77*(1+$N77),"") -> 6315.1219 | S77: =IFERROR(R77*(1+$N77),"") -> 8683.2926 | T77: =IFERROR(S77*(1+$N77),"") -> 11939.527
B78: =B77+1 -> 76 | C78: Techera Engineering | D78: TECHERA | E78: TECHERA | F78: =_xlfn.XLOOKUP($D78,BB_Input!$C$4:$C$172,BB_Input!$G$4:$G$172) -> 40.354108 | G78: =_xlfn.XLOOKUP($D78,CCA_Defense!$D:$D,CCA_Defense!M:M) -> 107 | H78: =_xlfn.XLOOKUP($D78,CCA_Defense!$D:$D,CCA_Defense!N:N) -> 72.40895 | I78: =_xlfn.XLOOKUP($D78,CCA_Defense!$D:$D,CCA_Defense!O:O) -> 46.848027 | J78: =_xlfn.XLOOKUP($D78,CCA_Defense!$D:$D,CCA_Defense!P:P) -> 30.310309 | K78: =_xlfn.XLOOKUP($D78,CCA_Defense!$D:$D,CCA_Defense!Q:Q) -> 19.610534 | L78: =_xlfn.XLOOKUP($D78,CCA_Defense!$D:$D,CCA_Defense!R:R) -> 12.687863 | M78: =_xlfn.XLOOKUP($D78,CCA_Defense!$D:$D,CCA_Defense!T:T) -> 0.48616696 | N78: =_xlfn.XLOOKUP($D78,CCA_Defense!$D:$D,CCA_Defense!U:U) -> 0 | O78: =IFERROR(_xlfn.XLOOKUP($D78,BB_Input!$C$4:$C$163,BB_Input!$CY$4:$CY$163),"") -> 495.017 | P78: =IFERROR(O78*(1+$M78),"") -> 735.67791 | Q78: =IFERROR(P78*(1+$M78),"") -> 1093.3402 | R78: =IFERROR(Q78*(1+$M78),"") -> 1624.8861 | S78: =IFERROR(R78*(1+$M78),"") -> 2414.852 | T78: =IFERROR(S78*(1+$M78),"") -> 3588.8733
B79: =B78+1 -> 77 | C79: PTC Industries | D79: PTCIL | E79: PTCIL | F79: =_xlfn.XLOOKUP($D79,BB_Input!$C$4:$C$172,BB_Input!$G$4:$G$172) -> 3055.6101 | G79: =_xlfn.XLOOKUP($D79,CCA_Defense!$D:$D,CCA_Defense!M:M) -> 396 | H79: =_xlfn.XLOOKUP($D79,CCA_Defense!$D:$D,CCA_Defense!N:N) -> 282.73659 | I79: =_xlfn.XLOOKUP($D79,CCA_Defense!$D:$D,CCA_Defense!O:O) -> 109.57991 | J79: =_xlfn.XLOOKUP($D79,CCA_Defense!$D:$D,CCA_Defense!P:P) -> 40.911531 | K79: =_xlfn.XLOOKUP($D79,CCA_Defense!$D:$D,CCA_Defense!Q:Q) -> 23.174123 | L79: =_xlfn.XLOOKUP($D79,CCA_Defense!$D:$D,CCA_Defense!R:R) | M79: =_xlfn.XLOOKUP($D79,CCA_Defense!$D:$D,CCA_Defense!T:T) -> 0.1145288 | N79: =_xlfn.XLOOKUP($D79,CCA_Defense!$D:$D,CCA_Defense!U:U) -> 0 | O79: =IFERROR(_xlfn.XLOOKUP($D79,BB_Input!$C$4:$C$163,BB_Input!$CY$4:$CY$163),"") -> 3080.74 | P79: =IFERROR(O79*(1+$M79),"") -> 3433.5734 | Q79: =IFERROR(P79*(1+$M79),"") -> 3826.8165 | R79: =IFERROR(Q79*(1+$M79),"") -> 4265.0972 | S79: =IFERROR(R79*(1+$M79),"") -> 4753.5736 | T79: =IFERROR(S79*(1+$M79),"") -> 5297.9947
B80: =B79+1 -> 78 | C80: Investment & Precision Castings (IPCL) | D80: IPC | E80: IPCL | F80: =_xlfn.XLOOKUP($D80,BB_Input!$C$4:$C$172,BB_Input!$G$4:$G$172) -> 54.377921 | G80: =_xlfn.XLOOKUP($D80,CCA_Defense!$D:$D,CCA_Defense!M:M) -> 68.9 | H80: =_xlfn.XLOOKUP($D80,CCA_Defense!$D:$D,CCA_Defense!N:N) | I80: =_xlfn.XLOOKUP($D80,CCA_Defense!$D:$D,CCA_Defense!O:O) | J80: =_xlfn.XLOOKUP($D80,CCA_Defense!$D:$D,CCA_Defense!P:P) | K80: =_xlfn.XLOOKUP($D80,CCA_Defense!$D:$D,CCA_Defense!Q:Q) | L80: =_xlfn.XLOOKUP($D80,CCA_Defense!$D:$D,CCA_Defense!R:R) | M80: =_xlfn.XLOOKUP($D80,CCA_Defense!$D:$D,CCA_Defense!T:T) | N80: =_xlfn.XLOOKUP($D80,CCA_Defense!$D:$D,CCA_Defense!U:U) -> 0 | O80: =IFERROR(_xlfn.XLOOKUP($D80,BB_Input!$C$4:$C$163,BB_Input!$CY$4:$CY$163),"") -> 1625.483 | P80: =IFERROR(O80*(1+$M80),"") | Q80: =IFERROR(P80*(1+$M80),"") | R80: =IFERROR(Q80*(1+$M80),"") | S80: =IFERROR(R80*(1+$M80),"") | T80: =IFERROR(S80*(1+$M80),"")
D82: placeholders
F85: =MATCH(F86,INDIRECT($C$86&"!$C$3:$DF$3"),0) -> #REF!
F86: cur_mkt_cap(currency=USD)/1000000

Sheet BBdata
D1: Market capitalization | G1: Enterprise value | J1: P/E | L1: EV/EBITDA | O1: Price/Book | R1: Return on equity metrics | U1: Return on capital metrics | AA1: Net debt or (net cash) | AC1: Net debt/EBITDA | AE1: ShsOutstanding | AF1: FreeFloat% | AH1: Avg daily trading volumes | AL1: Share price | AO1: EPS - historical | AU1: EPS - estimates | AZ1: EBITDA - historical | BF1: EBITDA - estimates | BK1: revenue - historical | BQ1: revenue - estimates
D2: $USD | E2: ₹INR | G2: $USD | H2: ₹INR | J2: T12M | K2: EST | L2: T12M | M2: EST | O2: P/BV | P2: P/TBV | R2: ROE1 | S2: ROE3 | T2: ROTE | U2: ROCE | V2: ROIC1 | W2: ROIC2 | X2: ROIC3 | Y2: ROC | AA2: $USD | AB2: ₹INR | AC2: Net debt/EBITDA | AE2: Shares (mm) | AF2: FreeFloat% | AH2: 5Dvol (mm) | AI2: 10Dvol (mm) | AJ2: 30Dvol (mm) | AL2: $USD | AM2: ₹INR | AO2: 2020eps | AP2: 2021eps | AQ2: 2022eps | AR2: 2023eps | AS2: 2024eps | AT2: 2025eps | AU2: 2026eps | AV2: 2027eps | AW2: 2028eps | AX2: 2029eps | AZ2: 2020ebitda | BA2: 2021ebitda | BB2: 2022ebitda | BC2: 2023ebitda | BD2: 2024ebitda | BE2: 2025ebitda | BF2: 2026ebitda | BG2: 2027ebitda | BH2: 2028ebitda | BI2: 2029ebitda | BK2: 2020rev | BL2: 2021rev | BM2: 2022rev | BN2: 2023rev | BO2: 2024rev | BP2: 2025rev | BQ2: 2026rev | BR2: 2027rev | BS2: 2028rev | BT2: 2029rev
